Workbook

Sheet Listas
A1: Estado | B1: Descripción | D1: Prioridades
A2: Por hacer | B2: No iniciado. En Backlog
A3: En análisis Funcional | B3: En análisis y/o diseño
A4: En análisis Técnico | B4: En análisis y/o diseño
A5: En desarrollo | B5: En construcción
A6: QA | B6: En pruebas finales de sistemas
A7: UAT | B7: En prueba de usuario
A8: Para implementar | B8: En instalación en el ambiente de producción
A9: Cerrado | B9: Cuando el requerimiento se encuentra instalado
A10: Cancelado | B10: Cuando el requerimiento se descarta. Puede estar en cualquier estado existente.
A11: Suspendido | B11: Cuando el requerimiento se encuentra en los estados "En análisis", "En desarrollo", En Testing", "UAT" o "Para implementar".
A12: Implementado / Soporte | B12: Cuando se encuentra Implementado pero no cerrado.
A13: Validar estado | B13: Puede ser que se haya implemantado. Hay que validar si se solucionó
... A17: Planificado | B17: Ticket Planificado

Sheet Jira Exportar Excel CSV (OLD)
A1: Tipo | B1: Clave | D1: Fecha solicitado | E1: Fecha finalizado | F1: Tarea princ | G1: Resumen | H1: Cliente | I1: Componente | J1: Asignada | K1: Area | L1: Informador | M1: Prioridad | N1: Estado | O1: Sprint | P1: Fecha comprometida | Q1: Comentario | R1: Descripción
A2: Tarea | B2: MAN-2 | C2: =VALUE(RIGHT(B2,LEN(B2)-4)) -> 2 | D2: 45649 | E2: 45663 | G2: RN SAA MAN-10283. Reporte histórico de premios mayores | H2: Rio Negro | I2: SAA | J2: Santiago Obregon | K2: SAC | L2: Maria Luz Britos | M2: Medium | N2: Finalizada | O2: Sprint 4
A3: Subtarea | B3: MAN-3 | C3: =VALUE(RIGHT(B3,LEN(B3)-4)) -> 3 | F3: MAN-2 | G3: Analisis funcional | L3: Fabiana Vallejos | M3: Medium | N3: Finalizada | O3: Sprint 4
A4: Tarea | B4: MAN-4 | C4: =VALUE(RIGHT(B4,LEN(B4)-4)) -> 4 | D4: 45649 | E4: 45672 | G4: COR LOTEMOVIL MAN-10246. Listado de reporte login de agentes | H4: Corrientes | I4: Lotemovil | J4: Santiago Obregon | K4: SAC | L4: Maria Luz Britos | M4: Medium | N4: Finalizada | O4: Sprint 4
A5: Tarea | B5: MAN-5 | C5: =VALUE(RIGHT(B5,LEN(B5)-4)) -> 5 | D5: 45649 | E5: 45722 | G5: TDF SAA MAN-9935-Sprint 2 Validar fecha en carga de extracto por archivo | H5: Tierra del Fuego | I5: SAA | J5: Claudia Saissac | K5: SAP | L5: Maria Luz Britos | M5: Medium | N5: Finalizada | O5: Sprint 4
A6: Tarea | B6: MAN-6 | C6: =VALUE(RIGHT(B6,LEN(B6)-4)) -> 6 | D6: 45649 | E6: 45687 | G6: SLA SAA MAN-10330 - Sprint 4 - Modificar cáculo de Total Neto en M5/M9 de Sunmi | H6: Salta | I6: SAA | J6: Claudia Saissac | K6: SAP | L6: Maria Luz Britos | M6: Medium | N6: Finalizada | O6: Sprint 4 | R6: Solo debe restarse lo recaudado por medios digitales para que el total neto coincida con el físico
A7: Tarea | B7: MAN-7 | C7: =VALUE(RIGHT(B7,LEN(B7)-4)) -> 7 | D7: 45649 | G7: RN SAA MAN-9325 Patagonia Telebingo- Modificar forma de seleccion de cupon | H7: Rio Negro | I7: SAA | J7: leandro guadagno | K7: Sistemas | L7: Maria Luz Britos | M7: Medium | N7: Finalizada | O7: Sprint 4 | R7: En procesos de pruebas. Pidieron ellos para que se pueda seleccionar el carton por nro de recupero
A8: Tarea | B8: MAN-8 | C8: =VALUE(RIGHT(B8,LEN(B8)-4)) -> 8 | D8: 45649 | E8: 45687 | G8: MAN-10263-Se solicita quitar el mail tecnoaccion@tecnoaccion.com.ar de la pagina de tecnoaccion.com.ar y se lo reemplace con un formulario de contacto | H8: Interno | I8: Web tecno | J8: leandro guadagno | K8: Sistemas | L8: Maria Luz Britos | M8: Medium | N8: Finalizada | O8: Sprint 4
A9: Tarea | B9: MAN-9 | C9: =VALUE(RIGHT(B9,LEN(B9)-4)) -> 9 | D9: 45649 | E9: 45663 | G9: PMP SIGA MAN-9881-Sprint 3 Incorporación de los premios de Telekino en formato pre - impreso | H9: La Pampa | I9: Siga | J9: Santiago Obregon | K9: SAC | L9: Maria Luz Britos | M9: Medium | N9: Finalizada | O9: Sprint 4 | R9: Necesita validar y luego realizar pruebas
A10: Tarea | B10: MAN-10 | C10: =VALUE(RIGHT(B10,LEN(B10)-4)) -> 10 | D10: 45649 | E10: 45659 | G10: MAN-9854-Sprint 2 - Templates de facturación manualmente en Netsuite y reportes en excel con detalle de las recaudaciones que toma FABI para facturar | H10: Interno | I10: FABI | J10: Maria Luz Britos | K10: Sistemas | L10: Maria Luz Britos | M10: Medium | N10: Finalizada | O10: Sprint 4
A11: Subtarea | B11: MAN-11 | C11: =VALUE(RIGHT(B11,LEN(B11)-4)) -> 11 | F11: MAN-4 | G11: Analisis y Seguimiento. COR LOTEMOVIL. Listado de reporte login de agentes | J11: leandro guadagno | L11: leandro guadagno | M11: Medium | N11: Finalizada | O11: Sprint 4 | R11: Analisis y Seguimiento. COR LOTEMOVIL. Listado de reporte login de agentes
A12: Tarea | B12: MAN-12 | C12: =VALUE(RIGHT(B12,LEN(B12)-4)) -> 12 | D12: 45649 | E12: 45674 | G12: SC SIGA MAN-10342. Implementar pago premios con retención en agencias | H12: Santa Cruz | I12: Siga | J12: leandro guadagno | K12: Sistemas | L12: Maria Luz Britos | M12: Medium | N12: Finalizada | O12: Sprint 5
A13: Tarea | B13: MAN-13 | C13: =VALUE(RIGHT(B13,LEN(B13)-4)) -> 13 | D13: 45649 | E13: 45684 | G13: SDE SIGA MAN-10288. Carga de extractos sorteos de lotería santiagueña | H13: Sgo del Estero | I13: Siga | J13: Hector Gabaldo | K13: Sistemas | L13: Maria Luz Britos | M13: Medium | N13: Finalizada | O13: Sprint 5 | R13: Plantilla de siga. Se realizó corrección . Se espera validación del cliente y confirmación de SAC.
A14: Tarea | B14: MAN-14 | C14: =VALUE(RIGHT(B14,LEN(B14)-4)) -> 14 | D14: 45649 | E14: 45677 | G14: NQN MAN-10245-PROGRAMA PREMIOS FIN DE FIESTAS 2025 | H14: Neuquen | I14: Speta | J14: Santiago Obregon | K14: SAC | L14: Maria Luz Britos | M14: Medium | N14: Finalizada | O14: Sprint 5 | R14: PROVINCIA Neuquén APLICACIÓN Speta DESCRIPCIÓN Se requiere programar los valores para la adjudicación del sorteo de fin de fiestas en Speta. Sorteo : 2570 Fecha de sorteo : 18/01/2025 5 partes de $1.000 Importe mínimo : $ 1.000 Importe máximo : $ 5.000 IMPACTO El impacto es alto , premiación del sorteo especial de fin de fiestas. DETALLES DE DESPLIEGUE Implica la actualización de las tablas de la base de datos del Speta : Tabla : lote.lo_programa_de_premios Para n_progra = 7 Campo : i_minimo = 1000 Campo : i_maximo = 5000
A15: Tarea | B15: MAN-15 | C15: =VALUE(RIGHT(B15,LEN(B15)-4)) -> 15 | D15: 45649 | E15: 45670 | G15: NQN MAN-10244 PROGRAMA PREMIOS REYES 2025 | H15: Neuquen | I15: Speta | J15: Santiago Obregon | K15: SAC | L15: Maria Luz Britos | M15: Medium | N15: Finalizada | O15: Sprint 5 | R15: PROVINCIA Neuquén APLICACIÓN Speta DESCRIPCIÓN Se requiere programar los valores para la adjudicacion del sorteo de reyes en Speta. Sorteo : 2569 Fecha de sorteo : 11/01/2025 5 partes de $2.000 Importe mínimo : $ 2.000 Importe máximo : $ 10.000 IMPACTO El impacto es alto , premiación del sorteo especial de reyes. DETALLES DE DESPLIEGUE Implica la actualización de las tablas de la base de datos del Speta : Tabla : lote.lo_programa_de_premios Para n_progra = 6 Campo : i_minimo = 2000 Campo : i_maximo = 10000 FECHA SUGERIDA DE DESPLIEGUE A disponer por el área según recursos y disponibilidad. La fecha de la actualización deberá ser anterior a la fecha del sorteo : 11 de Enero de 2025.
A16: Tarea | B16: MAN-16 | C16: =VALUE(RIGHT(B16,LEN(B16)-4)) -> 16 | D16: 45649 | E16: 45680 | G16: SLA LOTLINE MAN-10336. Activar solicitud ingreso de CUIL a usuarios | H16: Salta | I16: Lotline | J16: leandro guadagno | K16: Sistemas | L16: Maria Luz Britos | M16: Medium | N16: Finalizada | Q16: Sale de mantenimiento y pasa a proyecto
A17: Tarea | B17: MAN-17 | C17: =VALUE(RIGHT(B17,LEN(B17)-4)) -> 17 | D17: 45649 | E17: 45649 | G17: SLA LOTLINE MAN-10146- Sprint 5 - Agregar en página Lotline opción de descarga de la aplicación. | H17: Salta | I17: Lotline | J17: leandro guadagno | K17: Sistemas | L17: Maria Luz Britos | M17: Medium | N17: Finalizada | Q17: Sale de mantenimiento y pasa a proyecto
A18: Tarea | B18: MAN-18 | C18: =VALUE(RIGHT(B18,LEN(B18)-4)) -> 18 | D18: 45649 | E18: 45693 | G18: COR NOGA MAN-10139. Agregar columna con nombre de juego | H18: Corrientes | I18: Noga | J18: leandro guadagno | K18: Sistemas | L18: Maria Luz Britos | M18: Medium | N18: Finalizada | O18: Sprint 6
A19: Subtarea | B19: MAN-19 | C19: =VALUE(RIGHT(B19,LEN(B19)-4)) -> 19 | F19: MAN-7 | G19: Analisis, Seguimiento y prueba. | J19: leandro guadagno | L19: leandro guadagno | M19: Medium | N19: Finalizada | O19: Sprint 4 | R19: Analisis, Seguimiento y prueba.
A20: Tarea | B20: MAN-20 | C20: =VALUE(RIGHT(B20,LEN(B20)-4)) -> 20 | D20: 45649 | E20: 45653 | G20: PMP MAN-10345 SGC carga de ejercicio 2025 | H20: La Pampa | I20: SCG | J20: Hector Gabaldo | K20: Sistemas | L20: Maria Luz Britos | M20: Medium | N20: Finalizada | O20: Sprint 5 | R20: No aparece el ejercicio nuevo 2025. Todos los años se carga un ejercicio nuevo para SGC . Se crea Ejercicio nuevo y periodo.
A21: Subtarea | B21: MAN-21 | C21: =VALUE(RIGHT(B21,LEN(B21)-4)) -> 21 | F21: MAN-8 | G21: Análisis funcional. Modificación en Página Tecnoacción. | J21: leandro guadagno | L21: Claudia Saissac | M21: Medium | N21: Finalizada | O21: Sprint 4 | R21: Análisis funcional. Modificación en Página Tecnoacción.
A22: Subtarea | B22: MAN-22 | C22: =VALUE(RIGHT(B22,LEN(B22)-4)) -> 22 | F22: MAN-12 | G22: Analisis y Seguimiento. SC SIGA. Implementar pago premios con retención en agencias | J22: leandro guadagno | L22: leandro guadagno | M22: Medium | N22: Finalizada | O22: Sprint 5 | R22: Analisis y Seguimiento. SC SIGA. Implementar pago premios con retención en agencias
A23: Subtarea | B23: MAN-23 | C23: =VALUE(RIGHT(B23,LEN(B23)-4)) -> 23 | F23: MAN-14 | G23: Implementar | L23: Maria Luz Britos | M23: Medium | N23: Finalizada | O23: Sprint 5
A24: Subtarea | B24: MAN-24 | C24: =VALUE(RIGHT(B24,LEN(B24)-4)) -> 24 | F24: MAN-5 | G24: Analisis funcional | J24: Hector Gabaldo | L24: Maria Luz Britos | M24: Medium | N24: Finalizada | O24: Sprint 4
A25: Tarea | B25: MAN-25 | C25: =VALUE(RIGHT(B25,LEN(B25)-4)) -> 25 | D25: 45652 | E25: 45672 | G25: SC SIGA. Retenciones de sorteos extaordinarios unificada | H25: Santa Cruz | I25: Siga | J25: Santiago Obregon | K25: SAC | L25: Santiago Obregon | M25: Medium | N25: Finalizada | O25: Sprint 5 | R25: Lotería de Santa Cruz solicita no aplicar retenciones a los premios que recuperan el valor del entero al igual que se hizo en Neuquén y Rio Negro
A26: Tarea | B26: MAN-26 | C26: =VALUE(RIGHT(B26,LEN(B26)-4)) -> 26 | D26: 45652 | G26: NQN LOTLINE. Análisis por bug en carga de stock de lotería | H26: Neuquen | I26: Lotline | J26: leandro guadagno | K26: Sistemas | L26: Maria Luz Britos | M26: Medium | N26: Por hacer | R26: A partir de un pedido de C.Lopez de tener todos los juegos disponibles para jugar en la plataforma Lotline se encontró un error que no trae billetes de "Lotería". El bug se encontró en el "appService" que no soporta letras en el stock cargado. A.Iribarren estuvo y está trabajando desde principio de la semana del 09/12. Ambiente de prueba: http://humberto.tecnoaccion.com.ar:8080/feweb206LOTLINENQNFULL https://testnqn.tecnoaccion.com.ar.
A27: Subtarea | B27: MAN-27 | C27: =VALUE(RIGHT(B27,LEN(B27)-4)) -> 27 | F27: MAN-26 | G27: Analisis y Seguimiento. APPService - Análisis por bug en carga de stock de lotería. | J27: leandro guadagno | L27: Maria Luz Britos | M27: Medium | N27: En curso | R27: *Analisis y Seguimiento. APPService - Análisis por bug en carga de stock de lotería*
A28: Subtarea | B28: MAN-28 | C28: =VALUE(RIGHT(B28,LEN(B28)-4)) -> 28 | F28: MAN-26 | G28: Análisis y Desarrollo por bug en carga de stock de lotería. | J28: Alexis Gutierrez | L28: Maria Luz Britos | M28: Medium | N28: Por hacer | R28: A partir de un pedido de C.Lopez de tener todos los juegos disponibles para jugar en la plataforma Lotline se encontró un error que no trae billetes de "Lotería". El bug se encontró en el "appService" que no soporta letras en el stock cargado. A.Iribarren estuvo y está trabajando desde principio de la semana del 09/12. Ambiente de prueba: http://humberto.tecnoaccion.com.ar:8080/feweb206LOTLINENQNFULL https://testnqn.tecnoaccion.com.ar.
A29: Tarea | B29: MAN-29 | C29: =VALUE(RIGHT(B29,LEN(B29)-4)) -> 29 | D29: 45652 | G29: SLA PREJUEGO. Trackeo de boton compartir de Whatsapp. | H29: Salta | I29: Prejuego | L29: Santiago Obregon | M29: Medium | N29: Finalizada | R29: Salta solicita incorporar el trackeo del botón compartir de whatsapp en plataforma Prejuego.
A30: Subtarea | B30: MAN-30 | C30: =VALUE(RIGHT(B30,LEN(B30)-4)) -> 30 | F30: MAN-25 | G30: Prueba e implementación | J30: Claudia Saissac | L30: hector Gabaldo | M30: Medium | N30: Finalizada | O30: Sprint 5 | R30: JIRA https://tecnoproyectos.atlassian.net/browse/MAN-25 SUBTAREA https://tecnoproyectos.atlassian.net/browse/MAN-30 PROVINCIA Santa Cruz APLICACIÓN Base de datos Oracle Santa Cruz. DESCRIPCIÓN Actualizar versión de base de datos SAA productivas de : Versión 78_04 a la 78_05. IMPACTO El impacto es alto, a fin de actualizar base de datos para modificar la forma del calculo de retenciones en Front-end y Siga. Provincia de Santa Cruz. DETALLES Coordinar actualización con el área de infraestructura. FECHA SUGERIDA DE DESPLIEGUE A disponer por el área según recursos y disponibilidad. La fecha de la actualización deberá ser anterior al Sábado 04/01/2025.
A31: Tarea | B31: MAN-31 | C31: =VALUE(RIGHT(B31,LEN(B31)-4)) -> 31 | D31: 45652 | E31: 45693 | G31: COR SAA. No salen los importes de cupones a caducar en consulta de TJ. | H31: Corrientes | I31: SAA | J31: Claudia Saissac | K31: SAP | L31: Santiago Obregon | M31: Medium | N31: Finalizada | R31: En el ticket de la consulta Premios a caducar en agencia de TJ no salen los importes de los cupones a caducar.
A32: Tarea | B32: MAN-32 | C32: =VALUE(RIGHT(B32,LEN(B32)-4)) -> 32 | D32: 45652 | E32: 45656 | G32: NQN SGC. Cargar nuevo ejercicio 2025 | H32: Neuquen | I32: SCG | J32: Hector Gabaldo | K32: Sistemas | L32: Santiago Obregon | M32: Medium | N32: Finalizada | R32: La contadora Adriana Durazzi del IJAN solicita la creación del ejercicio contable 2025 en SGC con exportación del plan de cuentas del 2024.
A33: Subtarea | B33: MAN-33 | C33: =VALUE(RIGHT(B33,LEN(B33)-4)) -> 33 | F33: MAN-6 | G33: Analisis funcional | J33: Maria Luz Britos | L33: Maria Luz Britos | M33: Medium | N33: Finalizada | O33: Sprint 4
A34: Subtarea | B34: MAN-34 | C34: =VALUE(RIGHT(B34,LEN(B34)-4)) -> 34 | F34: MAN-25 | G34: Prueba e implementación | J34: Claudia Saissac | L34: hector Gabaldo | M34: Medium | N34: Finalizada | O34: Sprint 5 | R34: JIRA https://tecnoproyectos.atlassian.net/browse/MAN-25 SUBTAREA https://tecnoproyectos.atlassian.net/browse/MAN-34 PROVINCIA Santa Cruz APLICACIÓN Siga DESCRIPCIÓN Se requiere actualizar SP de la aplicación Siga Santa Cruz para contemplar cambios funcionales de premiación de sorteos extraordinarios IMPACTO El impacto es alto, a fin de actualizar Siga para modificar la forma del calculo de retenciones. Provincias de Santa Cruz. DETALLES Coordinar actualización con Ricardo Tejerina. FECHA SUGERIDA DE DESPLIEGUE A disponer por el área según recursos y disponibilidad. La fecha de la actualización deberá ser anterior al Sábado 04/01.
A35: Subtarea | B35: MAN-35 | C35: =VALUE(RIGHT(B35,LEN(B35)-4)) -> 35 | F35: MAN-18 | G35: Analisis funcional. MAN-10139-COR NOGA. Agregar columna con nombre de juego | J35: leandro guadagno | L35: hector Gabaldo | M35: Medium | N35: Finalizada | O35: Sprint 6 | R35: Analisis funcional. MAN-10139-COR NOGA. Agregar columna con nombre de juego
A36: Tarea | B36: MAN-36 | C36: =VALUE(RIGHT(B36,LEN(B36)-4)) -> 36 | D36: 45653 | E36: 45653 | G36: TDF LOTEMOVIL. Extracto Santa Fe se visualiza 2 veces | H36: Tierra del Fuego | I36: Lotemovil | L36: Santiago Obregon | M36: Medium | N36: Finalizada | R36: El extracto de Santa Fe se muestra duplicado en resultados quiniela de Lotemóvil.
A37: Error | B37: MAN-37 | C37: =VALUE(RIGHT(B37,LEN(B37)-4)) -> 37 | D37: 45653 | E37: 45686 | G37: SDE SAA. Selección de listado minuta CC da error agregando agencia 1035. | H37: Sgo del Estero | I37: SAA | J37: Maria Luz Britos | K37: Sistemas | L37: Santiago Obregon | M37: Medium | N37: Finalizada | R37: Buen día. El departamento de Sistemas solicita que se revisen los filtros de Agencias en la Minuta de Cuenta Corriente. Puntualmente el error ocurre cuando se lista hasta la Agencia 1035. No así cuando se lista hasta la Agencia 1033 o se lista solamente a la Agencia 1035.
A38: Tarea | B38: MAN-38 | C38: =VALUE(RIGHT(B38,LEN(B38)-4)) -> 38 | D38: 45653 | E38: 45665 | G38: NQN SIGA. Carga premios especiales unificada año nuevo. | H38: Neuquen | I38: Siga | J38: Claudia Saissac | K38: SAP | L38: Santiago Obregon | M38: Medium | N38: Finalizada | R38: Se solicita la carga de los premios especiales de la unificada de año nuevo de fecha 04/01/2025.
A39: Subtarea | B39: MAN-39 | C39: =VALUE(RIGHT(B39,LEN(B39)-4)) -> 39 | F39: MAN-10 | G39: Analisis funcional | J39: Maria Luz Britos | L39: Maria Luz Britos | M39: Medium | N39: Finalizada | O39: Sprint 4
A40: Subtarea | B40: MAN-40 | C40: =VALUE(RIGHT(B40,LEN(B40)-4)) -> 40 | F40: MAN-10 | G40: Prueba e implementación | J40: Claudia Saissac | L40: Maria Luz Britos | M40: Medium | N40: Finalizada | O40: Sprint 4
A41: Subtarea | B41: MAN-41 | C41: =VALUE(RIGHT(B41,LEN(B41)-4)) -> 41 | F41: MAN-38 | G41: Prueba e implementación | J41: Claudia Saissac | L41: hector Gabaldo | M41: Medium | N41: Finalizada
A42: Tarea | B42: MAN-42 | C42: =VALUE(RIGHT(B42,LEN(B42)-4)) -> 42 | D42: 45653 | G42: SLA WEB. No carga formulario apertura PDV. | H42: Salta | I42: Salta Web | L42: Santiago Obregon | M42: Medium | N42: Finalizada | O42: Sprint 8 | Q42: Resuelto desde Salta. | R42: Solicito creación de Jira: no se carga el formulario para apertura de Punto de Venta en la página Web de Salta. (abajo la muestra).
A43: Subtarea | B43: MAN-43 | C43: =VALUE(RIGHT(B43,LEN(B43)-4)) -> 43 | F43: MAN-10 | G43: Implementacion | L43: Claudia Saissac | M43: Medium | N43: Finalizada | O43: Sprint 4
A44: Subtarea | B44: MAN-44 | C44: =VALUE(RIGHT(B44,LEN(B44)-4)) -> 44 | F44: MAN-5 | G44: Prueba e implementación | J44: Claudia Saissac | L44: hector Gabaldo | M44: Medium | N44: Por hacer | O44: Sprint 4 | R44: JIRA [MAN-5] MAN-9935-Sprint 2 - SAA TDF Validar fecha en carga de extracto por archivo - Jira SUBTAREA [MAN-44] Prueba e implementación - Jira PROVINCIA Tierra del Fuego APLICACIÓN SAA DESCRIPCIÓN Validar fecha en carga de extracto por archivo IMPACTO DETALLES Version: 1957 build.date=07/01/2025 11:38:56 Developer: root Git user: FECHA SUGERIDA DE DESPLIEGUE A disponer por el área según recursos y disponibilidad.
A45: Tarea | B45: MAN-45 | C45: =VALUE(RIGHT(B45,LEN(B45)-4)) -> 45 | D45: 45656 | E45: 45665 | G45: SLA SAA.Cambio de valoresen juegos 08 Enero. | H45: Salta | I45: SAA | J45: Claudia Saissac | K45: SAP | L45: Santiago Obregon | M45: Medium | N45: Finalizada | R45: Lotería de Salta solicita el cambio nuevos valores de comercialización para los juegos propios, estos valores deben estar vigentes para el miércoles 8 de enero. Ver tabla de nuevos valores en nota adjunta.
A46: Tarea | B46: MAN-46 | C46: =VALUE(RIGHT(B46,LEN(B46)-4)) -> 46 | D46: 45656 | E46: 45680 | G46: NQN Aumento umbral premios UIF | H46: Neuquen | I46: SCG | J46: Claudia Saissac | K46: SAP | L46: Santiago Obregon | M46: Medium | N46: Finalizada | R46: Se modificó el umbral de información de premios ante la UIF. Antes era de $3.500.000 y ahora pasó a ser para premios mayores a $4.195.770 desde el 01/01/2025. Por lo cual solicitamos que modifiquen ese umbral en el SGC y para premios ONLINE
A47: Tarea | B47: MAN-47 | C47: =VALUE(RIGHT(B47,LEN(B47)-4)) -> 47 | D47: 45656 | E47: 45660 | G47: NQN SAA. Actualizar premios unificada sin retenciones en BD y SIGA | H47: Neuquen | I47: SAA | J47: Hector Gabaldo | K47: Sistemas | L47: Santiago Obregon | M47: Medium | N47: Finalizada | R47: De acuerdo a lo solicitado les envió esquema de premios a pagar SIN RETENCIÓN según el sorteo: AÑO NUEVO: Hasta $14.000 (Pesos catorce mil con 00/100 ) REYES: Hasta $10.000 (Pesos diez mil con 00/100 ) FIN DE FIESTA : Hasta $5.000 (Pesos cinco mil con 00/100 ) NO DEBERÁ REALIZAR CÁLCULO NI DESCUENTO POR RETENCIÓN ALGUNA. en el caso de LOTERÍA DE AÑO NUEVO SORTEO N°2569 Según el programa de premios del sorteo de Año Nuevo (Res. 269/24) se solicita acreditar en cuenta corriente de agencias los siguientes premios: (Los mismos podrán ser considerados vendidos en fracciones y por lo tanto podrán ser abonados directamente por el agenciero sin cálculo de retenciones). Premios de $14.000 por las 8100 Terminaciones de una (1) última cifra iguales a las del premio mayor, excluido éste y las anteriores, de $14.000 c/u. Premios de $14.000 por las 3596 Terminaciones de dos (2) últimas cifras iguales a las del 2do., 3er., 4to. y 5to. Premio, excluidos éstos, de $14.000 c/u Premios de $14.000 por los 8.997 Duplicadores iguales al duplicador premiado, de $14.000 c/u *Para el resto de los sorteos deberíamos ver el programa y la cantidad de fracciones que contienen
A48: Tarea | B48: MAN-48 | C48: =VALUE(RIGHT(B48,LEN(B48)-4)) -> 48 | D48: 45656 | E48: 45680 | G48: SDE LOTEMOVIL. (MAN-10316) No visualiza extracto MonoFechas. | H48: Sgo del Estero | I48: Lotemovil | J48: Horacio Braun | K48: SAC | L48: Santiago Obregon | M48: Medium | N48: Finalizada | O48: Sprint 6 | R48: Estamos teniendo problemas con la visualización de los extractos de mono fechas, al cargar la pagina no muestra el último extracto, para poder verlo uno debe ir a la lupa y seleccionar el extracto para visualizarlo. Adjunto imagen de lotemovil.
A49: Tarea | B49: MAN-49 | C49: =VALUE(RIGHT(B49,LEN(B49)-4)) -> 49 | D49: 45656 | E49: 45656 | G49: RN SPETA. Programa premios Reyes y Fin de Fiesta | H49: Rio Negro | I49: Speta | L49: Santiago Obregon | M49: Medium | N49: Finalizada | R49: Se solicita incorporar el programa de premios de extraordinaria de unificada de Reyes y Fin de Fiesta.
A50: Tarea | B50: MAN-50 | C50: =VALUE(RIGHT(B50,LEN(B50)-4)) -> 50 | D50: 45656 | E50: 45678 | G50: RN SIGA. Actualizacion de importe de premios- acreditacion directa en cta cte | H50: Rio Negro | I50: Siga | J50: Claudia Saissac | K50: SAP | L50: Santiago Obregon | M50: Medium | N50: Finalizada | R50: A partir del 01/01/2025 el umbral para los premios mayores será de *$4.195.770* por lo cual se solicita aumentar a ese límite la acreditación de premios automáticos.
A51: Tarea | B51: MAN-51 | C51: =VALUE(RIGHT(B51,LEN(B51)-4)) -> 51 | D51: 45656 | E51: 45656 | G51: RN PGO. Actualizar nuevo valor de Patagonia Telebingo | H51: Rio Negro | I51: PGO | L51: Santiago Obregon | M51: Medium | N51: Finalizada | R51: Nuevos mínimos de venta de patagonia telebingo a partir del sorteo nro 378 con inicio de venta el 6 de enero de 2025: Venta de patagonia telebingo: $40.000 (10 2x1) Venta semanal de quiniela: $1.100.000 Tambien se deberá tener en cuenta a partir del 06-01-2025 la devolucion de 2x1 en cta cte. hacerlo sobre el nuevo valor de $ 2.000
A52: Tarea | B52: MAN-52 | C52: =VALUE(RIGHT(B52,LEN(B52)-4)) -> 52 | D52: 45656 | E52: 45696 | G52: COR MediosDigi CNQ. Implementacion MODO | H52: Corrientes | I52: MediosDigi | J52: Claudia Saissac | K52: SAP | L52: leandro guadagno | M52: Medium | N52: Finalizada | O52: Sprint 6 | R52: El Lunes 06/01 se implementará MODO en Corrientes. Se requiere que se verifique si hay que hacer algo al respecto en SIGA / P. de Agente.
A53: Subtarea | B53: MAN-53 | C53: =VALUE(RIGHT(B53,LEN(B53)-4)) -> 53 | F53: MAN-52 | G53: Analisis y Seguimiento. MODO CNQ. Verificar SIGA / P.de Agente. | L53: leandro guadagno | M53: Medium | N53: Finalizada | O53: Sprint 6 | R53: El Lunes 06/01 se implementará MODO en Corrientes. Se requiere que se verifique si hay que hacer algo al respecto en SIGA / P. de Agente.
A54: Subtarea | B54: MAN-54 | C54: =VALUE(RIGHT(B54,LEN(B54)-4)) -> 54 | F54: MAN-52 | G54: Desarrollo. MODO CNQ. Verificar SIGA / P.de Agente. | J54: Ricardo Horacio Tejerina Perezlindo | L54: leandro guadagno | M54: Medium | N54: Por hacer | O54: Sprint 6 | R54: El Lunes 06/01 se implementará MODO en Corrientes. Se requiere que se verifique si hay que hacer algo al respecto en SIGA / P. de Agente.
A55: Tarea | B55: MAN-55 | C55: =VALUE(RIGHT(B55,LEN(B55)-4)) -> 55 | D55: 45656 | E55: 45735 | G55: JUY MODO Jujuy. Endpoint detalle de pagos. Error time out | H55: Jujuy | I55: Modo | J55: Hector Gabaldo | K55: Sistemas | L55: Claudia Saissac | M55: High | N55: Para implementar | O55: Sprint 9 | R55: El endpoint “consultardetallepagos” de MODO de Gamma genera el error “504- Gateway time out”. En un primer análisis técnico realizado se presume que al estar desarrollado con tecnología JPA se produce el error por el volumen de los datos.
A56: Tarea | B56: MAN-56 | C56: =VALUE(RIGHT(B56,LEN(B56)-4)) -> 56 | D56: 45659 | E56: 45663 | G56: RN SIGA. Liquidación unificada Año Nuevo | H56: Rio Negro | I56: Siga | L56: Santiago Obregon | M56: Medium | N56: Finalizada | R56: Liquidación de Lotería de Año Nuevo sorteo 2568, el día lunes 06/01/2025 al realizar la cta. cte. del día 04/01/2025 debe salir cobro de ventas desde 15/07/2024 hasta 04/01/2025. Recaudación, comisión, premios y retenciones.
A57: Tarea | B57: MAN-57 | C57: =VALUE(RIGHT(B57,LEN(B57)-4)) -> 57 | D57: 45659 | E57: 45667 | G57: SLA GAMMA. Reporte de cierre Diciembre 2024 | H57: Salta | I57: Gamma | L57: Santiago Obregon | M57: Medium | N57: Finalizada | R57: Se solicita el reporte de liquidación de GAMMA de Diciembre 2024.
A58: Subtarea | B58: MAN-58 | C58: =VALUE(RIGHT(B58,LEN(B58)-4)) -> 58 | F58: MAN-15 | G58: Modificación Siga Sorteo especial (fraccion y entero) Reyes | J58: Claudia Saissac | L58: hector Gabaldo | M58: Medium | N58: Finalizada
A59: Tarea | B59: MAN-59 | C59: =VALUE(RIGHT(B59,LEN(B59)-4)) -> 59 | D59: 45659 | E59: 45677 | G59: PMP SGC. Período 2025 mal cargado. | H59: La Pampa | I59: SCG | J59: Ricardo Horacio Tejerina Perezlindo | K59: Sistemas | L59: Santiago Obregon | M59: Highest | N59: Finalizada | R59: El primer comprobante del año salió continuó con la numeración del 2024 en lugar de comenzar por el N°1.
A60: Tarea | B60: MAN-60 | C60: =VALUE(RIGHT(B60,LEN(B60)-4)) -> 60 | D60: 45659 | E60: 45679 | G60: SDE- Despliegue Ver.206 Tj10-Lahuan | H60: Sgo del Estero | I60: Version 206 | J60: Claudia Saissac | K60: SAP | L60: Claudia Saissac | M60: High | N60: Finalizada | R60: Implementacion Ver 206 de Tj y Lahuan
A61: Subtarea | B61: MAN-61 | C61: =VALUE(RIGHT(B61,LEN(B61)-4)) -> 61 | F61: MAN-60 | G61: MAN-60 - SDE Ver 206 -Actualizacion BD SAA | L61: Claudia Saissac | M61: Medium | N61: Finalizada
A62: Subtarea | B62: MAN-62 | C62: =VALUE(RIGHT(B62,LEN(B62)-4)) -> 62 | F62: MAN-60 | G62: MAN-60 SDE ver 206 - Actualizar Ver Servjue206 | L62: Claudia Saissac | M62: Medium | N62: Por hacer
A63: Subtarea | B63: MAN-63 | C63: =VALUE(RIGHT(B63,LEN(B63)-4)) -> 63 | F63: MAN-60 | G63: MAN-60 - SDE Ver 206- Actualizar Gateway TJ | L63: Claudia Saissac | M63: Medium | N63: Por hacer
A64: Subtarea | B64: MAN-64 | C64: =VALUE(RIGHT(B64,LEN(B64)-4)) -> 64 | F64: MAN-60 | G64: MAN-60 SDE Ver 206 tj - SIGA? | L64: Claudia Saissac | M64: Medium | N64: Por hacer
A65: Subtarea | B65: MAN-65 | C65: =VALUE(RIGHT(B65,LEN(B65)-4)) -> 65 | F65: MAN-60 | G65: MAN60 - SDE Ver 206 - LotericoAPP | L65: Claudia Saissac | M65: Medium | N65: Por hacer
A66: Subtarea | B66: MAN-66 | C66: =VALUE(RIGHT(B66,LEN(B66)-4)) -> 66 | F66: MAN-60 | G66: MAN-60 - SDE Ver 206 Tj - Desplegar para terminales | L66: Claudia Saissac | M66: Medium | N66: Por hacer
A67: Subtarea | B67: MAN-67 | C67: =VALUE(RIGHT(B67,LEN(B67)-4)) -> 67 | F67: MAN-52 | G67: Reuniones con Loteria COR | L67: Claudia Saissac | M67: Medium | N67: Por hacer | O67: Sprint 6
A68: Subtarea | B68: MAN-68 | C68: =VALUE(RIGHT(B68,LEN(B68)-4)) -> 68 | F68: MAN-52 | G68: Testing Ver 206 con MODO | L68: Claudia Saissac | M68: Medium | N68: Por hacer | O68: Sprint 6
A69: Tarea | B69: MAN-69 | C69: =VALUE(RIGHT(B69,LEN(B69)-4)) -> 69 | D69: 45660 | G69: SLA GAMMA MAN-9516 No genera resumenes para algunas agencias. | H69: Salta | I69: Gamma | L69: Santiago Obregon | M69: Highest | N69: Por hacer | Q69: A desarrollar | R69: Cuando el PDV solo tiene movimientos de CSA en su cuenta corriente para la fecha a liquidar, no se genera un resumen para el PDV, Ejemplo prod salta: Fecha a liquidar 16/01/25 PDV 451 Movimientos a liquidar CSA $1200 - IVA CSA $252 Finaliza la liquidación sin resumen para el PDV 451, los movimientos se marcan como liquidados.
A70: Tarea | B70: MAN-70 | C70: =VALUE(RIGHT(B70,LEN(B70)-4)) -> 70 | D70: 45660 | G70: SLA GAMMA MAN-9521 Modulo contabilidad aplica filtro al descargar archivos | H70: Salta | I70: Gamma | L70: Santiago Obregon | M70: Highest | N70: Por hacer | Q70: Vuelve a desarrollo. Validar.
A71: Tarea | B71: MAN-71 | C71: =VALUE(RIGHT(B71,LEN(B71)-4)) -> 71 | D71: 45660 | G71: SLA GAMMA MAN-9524 Modulo Contabilidad-Generacion de constancias no guarda nro de presentacion en tablas | H71: Salta | I71: Gamma | L71: Santiago Obregon | M71: Highest | N71: Por hacer | Q71: Vuelve a desarrollo. Validar.
A72: Tarea | B72: MAN-72 | C72: =VALUE(RIGHT(B72,LEN(B72)-4)) -> 72 | D72: 45660 | G72: SLA GAMMA MAN-9561 Comisiones Betwarrior | H72: Salta | I72: Gamma | L72: Santiago Obregon | M72: Highest | N72: En curso | P72: 45751 | Q72: En proceso de prueba
A73: Error | B73: MAN-73 | C73: =VALUE(RIGHT(B73,LEN(B73)-4)) -> 73 | D73: 45660 | E73: 45660 | G73: SLA GAMMA MAN-9950 Al marcar una baja en PDV 000 no deja avanzar con liquidación | H73: Salta | I73: Gamma | L73: Santiago Obregon | M73: Medium | N73: Finalizada
A74: Error | B74: MAN-74 | C74: =VALUE(RIGHT(B74,LEN(B74)-4)) -> 74 | D74: 45660 | E74: 45660 | G74: SLA GAMMA MAN-10044 Problemas en la liquidación | H74: Salta | I74: Gamma | J74: Ricardo Horacio Tejerina Perezlindo | K74: Sistemas | L74: Santiago Obregon | M74: Highest | N74: Finalizada
A75: Error | B75: MAN-75 | C75: =VALUE(RIGHT(B75,LEN(B75)-4)) -> 75 | D75: 45660 | E75: 45660 | G75: SLA GAMMA MAN-10155 No permite editar dos veces una fecha en el calendario | H75: Salta | I75: Gamma | L75: Santiago Obregon | M75: Medium | N75: Finalizada
A76: Tarea | B76: MAN-76 | C76: =VALUE(RIGHT(B76,LEN(B76)-4)) -> 76 | D76: 45660 | E76: 45664 | G76: SLA SAA MAN-10330 Modificación de calculo del total neto en M5/M9 | H76: Salta | I76: Gamma | L76: Santiago Obregon | M76: Medium | N76: Finalizada
A77: Subtarea | B77: MAN-77 | C77: =VALUE(RIGHT(B77,LEN(B77)-4)) -> 77 | F77: MAN-6 | G77: Prueba e implementación. MAN-10330-SLA SAA. Modificar cáculo de Total Neto en M5/M9 de Sunmi | J77: Claudia Saissac | L77: Maria Luz Britos | M77: Medium | N77: Por hacer | O77: Sprint 4 | R77: JIRA [MAN-6] MAN-10330-SLA SAA. Modificar cáculo de Total Neto en M5/M9 de Sunmi - Jira SUBTAREA [MAN-77] Prueba e implementación. MAN-10330-SLA SAA. Modificar cáculo de Total Neto en M5/M9 de Sunmi - Jira PROVINCIA Salta APLICACIÓN Medios Digitales VERSIÓN 3903 DESCRIPCIÓN Se realizo el cambio que corrige el problema del total neto que no descontaba lo cobrado por medios de pagos digitales DETALLES Servjue Versión: 3903 Branch: dev git-hash: c237bf9 link servjue205: http://hodor:8088/test/servjue/servjue205-dev-3903 link servjue206: http://hodor:8088/test/servjue/servjue206-dev-3903
A78: Tarea | B78: MAN-78 | C78: =VALUE(RIGHT(B78,LEN(B78)-4)) -> 78 | D78: 45663 | E78: 45685 | G78: PMP SAA. Formulario de mínimos no permite agregar mas de 6 cifras. | H78: La Pampa | I78: SAA | J78: Alberto Iribarren | K78: Sistemas | L78: Santiago Obregon | M78: Medium | N78: Finalizada | O78: Sprint 7 | R78: El formulario de minimos del SAA no deja agregar mas de 6 cifras (automáticamente le pone el punto decimal).
A79: Subtarea | B79: MAN-79 | C79: =VALUE(RIGHT(B79,LEN(B79)-4)) -> 79 | F79: MAN-17 | G79: Analisis y Seguimiento. MAN-10146-SLA LOTLINE. Agregar en página Lotline opción de descarga de la aplicación. | L79: leandro guadagno | M79: Medium | N79: Finalizada | R79: Analisis y Seguimiento. MAN-10146-SLA LOTLINE. Agregar en página Lotline opción de descarga de la aplicación.
A80: Tarea | B80: MAN-80 | C80: =VALUE(RIGHT(B80,LEN(B80)-4)) -> 80 | D80: 45663 | E80: 45664 | G80: SLA SAA. Cambiar nombre y logo del Bingo de las Colectividades | H80: Salta | I80: SAA | L80: Santiago Obregon | M80: High | N80: Finalizada | R80: Cambiar el nombre del bingo que actualmente en el sistema se llama Bingo de las Colectividades por: Bingo de la Amistad Valor de la impresión $ 7.000 Sortea el 16/02/2025 (esto no afecta ya que cuando cargue el sorteo pongo estos datos) Se adjunta la resolución de ENREJA y el logo que debería incorporarse para el mismo.
A81: Subtarea | B81: MAN-81 | C81: =VALUE(RIGHT(B81,LEN(B81)-4)) -> 81 | F81: MAN-5 | G81: Desarrollo | J81: Alberto Iribarren | L81: Maria Luz Britos | M81: Medium | N81: Finalizada | O81: Sprint 4
A82: Tarea | B82: MAN-82 | C82: =VALUE(RIGHT(B82,LEN(B82)-4)) -> 82 | D82: 45664 | E82: 45685 | G82: PMP SAA MAN-10049 Listado premios mayores no trae resultados de 10 digitos | H82: La Pampa | I82: SAA | J82: Claudia Saissac | K82: SAP | L82: Maria Luz Britos | M82: Medium | N82: Finalizada | O82: Sprint 7 | R82: El error se producía cuando se ejecutaba el listado con un valor mayor a 2.147.483.647 (o sea, este era el máximo, los usuarios ponían valores como 9.999.999.999) en el filtro "Premio Hasta".
A83: Subtarea | B83: MAN-83 | C83: =VALUE(RIGHT(B83,LEN(B83)-4)) -> 83 | F83: MAN-82 | G83: Desarrollo | J83: Alberto Iribarren | L83: Maria Luz Britos | M83: Medium | N83: Finalizada | O83: Sprint 7
A84: Subtarea | B84: MAN-84 | C84: =VALUE(RIGHT(B84,LEN(B84)-4)) -> 84 | F84: MAN-82 | G84: Analisis funcional | J84: Maria Luz Britos | L84: Maria Luz Britos | M84: Medium | N84: Finalizada | O84: Sprint 7
A85: Tarea | B85: MAN-85 | C85: =VALUE(RIGHT(B85,LEN(B85)-4)) -> 85 | D85: 45664 | E85: 45670 | G85: NQN LOTEMOVIL. No asigna subagencia 0 nuevo titular de agencia 18 | H85: Neuquen | I85: Lotemovil | J85: Claudia Saissac | K85: SAP | L85: Santiago Obregon | M85: Medium | N85: Finalizada | R85: Loteria asignó a un nuevo propietario la agencia 18 que estaba dada de baja, por lo que dicen cargaron todos los datos en Siga y en Front End y no aparece la sub agencia 0 en el panel de agentes.
A86: Tarea | B86: MAN-86 | C86: =VALUE(RIGHT(B86,LEN(B86)-4)) -> 86 | D86: 45664 | E86: 45705 | G86: CTC Smartview. Cambiar logo de Catamarca en extracto Smartview. | H86: Catamarca | I86: Smartview | J86: Diego Cano | K86: Sistemas | L86: Santiago Obregon | M86: Medium | N86: Finalizada | O86: Sprint 8 | R86: Debe modificarse en la barra lateral donde aparecen los extractos / resultados.
A87: Tarea | B87: MAN-87 | C87: =VALUE(RIGHT(B87,LEN(B87)-4)) -> 87 | D87: 45664 | G87: SLA LOTLINE. Ingreso a plataforma con gmail sin registración. | H87: Salta | I87: Lotline | J87: Horacio Braun | K87: SAC | L87: Santiago Obregon | M87: High | N87: Finalizada | R87: Se solicita que cualquier persona pueda ingresar a la plataforma de Lotline y conocerla con el simple ingreso de su Gmail (como muestra la foto de ejemplo), en el caso que la persona desee JUGAR (cargar saldo con su billetera virtual /o jugar dinero que posee en la cuenta) que solicite ingresar con su usuario y contraseña registrada que ya haya pasado por el proceso de registración completo.
A88: Tarea | B88: MAN-88 | C88: =VALUE(RIGHT(B88,LEN(B88)-4)) -> 88 | D88: 45664 | E88: 45693 | G88: SLA LOTLINE MAN-10297. No funciona enlace a reglamentos de juegos. | H88: Salta | I88: Lotline | L88: Claudia Saissac | M88: High | N88: Finalizada | O88: Sprint 7 | R88: Actualizar redireccionamiento de donde tiene que apuntar lotline para buscar los reglamentos de juego.
A89: Subtarea | B89: MAN-89 | C89: =VALUE(RIGHT(B89,LEN(B89)-4)) -> 89 | F89: MAN-82 | G89: Prueba e implementación | J89: Claudia Saissac | L89: Maria Luz Britos | M89: Medium | N89: Finalizada | O89: Sprint 7 | R89: JIRA [MAN-82] MAN-10049-PMP-SAA Listo premios mayores no trae resultados de 10 digitos - Jira SUBTAREA [MAN-89] Prueba e implementación - Jira PROVINCIA La Pampa APLICACIÓN SAA DESCRIPCIÓN MAN-10049 Listado premios mayores no trae resultados de 10 dígitos IMPACTO DETALLES Version: 1961 build.date=08/01/2025 10:16:15 Developer: root Git user: FECHA SUGERIDA DE DESPLIEGUE A disponer por el área según recursos y disponibilidad.
A90: Subtarea | B90: MAN-90 | C90: =VALUE(RIGHT(B90,LEN(B90)-4)) -> 90 | F90: MAN-7 | G90: Desarrollo | J90: Alberto Iribarren | L90: leandro guadagno | M90: Medium | N90: Finalizada | O90: Sprint 4 | R90: Se requiere que para el juego P.Telebingo se pueda seleccionar cartón del juego mediante el número de recupero.
A91: Subtarea | B91: MAN-91 | C91: =VALUE(RIGHT(B91,LEN(B91)-4)) -> 91 | F91: MAN-52 | G91: Pruebas | L91: Claudia Saissac | M91: Medium | N91: Por hacer | O91: Sprint 6
A92: Tarea | B92: MAN-92 | C92: =VALUE(RIGHT(B92,LEN(B92)-4)) -> 92 | D92: 45665 | E92: 45693 | G92: SLA SAA- Listado 103 Recaudación por extracto-MAN-9823 | H92: Salta | I92: SAA | J92: Maria Luz Britos | K92: Sistemas | L92: Maria Luz Britos | M92: Medium | N92: Finalizada | O92: Sprint 7 | R92: Agregar en el filtro hora desde y hora hasta, Que se visualice con franja horaria 00:00 a 23:59
A93: Subtarea | B93: MAN-93 | C93: =VALUE(RIGHT(B93,LEN(B93)-4)) -> 93 | F93: MAN-92 | G93: Desarrollo | J93: Alberto Iribarren | L93: Maria Luz Britos | M93: Medium | N93: Finalizada | O93: Sprint 7
A94: Subtarea | B94: MAN-94 | C94: =VALUE(RIGHT(B94,LEN(B94)-4)) -> 94 | F94: MAN-92 | G94: Análisis funcional. MAN-92. SLA SAA- Listado 103 Recaudación por extracto-MAN-9823 | J94: Maria Luz Britos | L94: Maria Luz Britos | M94: Medium | N94: Finalizada | O94: Sprint 7
A95: Tarea | B95: MAN-95 | C95: =VALUE(RIGHT(B95,LEN(B95)-4)) -> 95 | D95: 45666 | E95: 45701 | G95: RN SIGA. Liquidación de lotería de Reyes sorteo 2569 | H95: Rio Negro | I95: Siga | J95: Claudia Saissac | K95: SAP | L95: Santiago Obregon | M95: High | N95: Finalizada | R95: Liquidación de la Loteria de Reyes sorteo 2569, el dia lunes 13/01/2025 al realizar la cta cte. del dia 11/01/2025 debe salir cobro de ventas desde 15/07/2024 al 11/01/2025. Recaudacion, comisión, premios y retenciones.
A96: Tarea | B96: MAN-96 | C96: =VALUE(RIGHT(B96,LEN(B96)-4)) -> 96 | D96: 45666 | G96: MENU WEB-Falla relanzado del ServPipe - MAN-9704 | H96: Interno | I96: Menu Web | J96: Claudia Saissac | K96: SAP | L96: Maria Luz Britos | M96: Medium | N96: En curso | Q96: SAP- DC
A97: Tarea | B97: MAN-97 | C97: =VALUE(RIGHT(B97,LEN(B97)-4)) -> 97 | D97: 45666 | G97: PUNTO DE VENTA-Estadísticas de COMM no reporta todas las SIMS - MAN-9382 | H97: Interno | I97: PDV | J97: Claudia Saissac | K97: SAP | L97: Maria Luz Britos | M97: Medium | N97: En curso | Q97: SAP- DC
A98: Tarea | B98: MAN-98 | C98: =VALUE(RIGHT(B98,LEN(B98)-4)) -> 98 | D98: 45666 | G98: SLA LOTLINE. Incluir onboarding de Tombo Express. | H98: Salta | I98: Lotline | L98: Santiago Obregon | M98: Medium | N98: Finalizada | R98: Incluir el onboarding del juego tombo Express en Lotline. Fecha límite para su implementación 15/02/2025.
A99: Tarea | B99: MAN-99 | C99: =VALUE(RIGHT(B99,LEN(B99)-4)) -> 99 | D99: 45666 | G99: BETWARRIOR-Analytics Betwarrior - Diferenciación de Propiedades Provincia - MAN-10346 | H99: Interno | I99: Betwarrior | J99: Hector Gabaldo | K99: Sistemas | L99: Maria Luz Britos | M99: Medium | N99: Finalizada | O99: Sprint 9 | Q99: esta ok lo trakeado con el detalle que ellos lo quieren diferenciado por geolocalizacion , implica tiempo de entendimiento y desarrollo. Lo tiene que ver de nuevo Andre. Se adjunta mail de confirmacion de cierre del requerimiento | R99: *Betwarrior Salta ID de medición GA4 → G-LDL82HH2NC Contenedor GTM → GTM-MQS8LW6N Flujo de datos → 10022123504 *Betwarrior Jujuy ID de medición GA4 → G-LYBFDB52NL Contenedor GTM → GTM-T7HP74D4 Flujo de datos → 10022149318 *Betwarrior La Rioja ID de medición GA4 → G-9CGEYZQX8V Contenedor GTM → GTM-TD2ZMNLL Flujo de datos → 10022127789
A100: Tarea | B100: MAN-100 | C100: =VALUE(RIGHT(B100,LEN(B100)-4)) -> 100 | D100: 45667 | E100: 45687 | G100: Gamma- Integracion Netsuite -Actualizacion ambiente UAT | H100: Clientes | I100: Gamma | J100: Claudia Saissac | K100: SAP | L100: Claudia Saissac | M100: Medium | N100: Finalizada | R100: *Coordinación con PO (Sabrina Amarilla-Lotería de Salta) *Backup de ambiente UAT (Gustavo Duarte) *NO borrar bases de datos UAT: ta_business, keycloak, users, application_abaco (Gustavo Duarte) *Replicar demás bases de datos PROD a UAT (Gustavo Duarte) *Control de UAT (Fabián Romero – SAP) *Ejecutar scripts de actualización códigos contables para Netsuite (Ricardo Marino) *Actualizar servicios para Netsuite (Ricardo Marino) *Control Lotería de Salta (Sabrina Amarilla-Lotería de Salta)
...

Sheet Hoja1
A3: Suma de Desarrollo | B3: Estado
A4: Evaluación real del caso | B4: A estimar | C4: A planificar | D4: A priorizar | E4: Para implementar | F4: Validar estado | G4: En desarrollo | H4: Planificado | I4: QA | J4: Total general
A5: Consulta | D5: 0 | J5: 0
A6: Mantenimiento correctivo | C6: 287 | D6: 476 | F6: 32 | H6: 304 | I6: 0 | J6: 1099
A7: Mantenimiento evolutivo | B7: 40 | C7: 899 | D7: 2280 | F7: 0 | G7: 1268 | I7: 0 | J7: 4487
A8: Mantenimiento preventivo | C8: 28 | D8: 36 | G8: 0 | J8: 64
A9: Total general | B9: 40 | C9: 1214 | D9: 2792 | F9: 32 | G9: 1268 | H9: 304 | I9: 0 | J9: 5650

Sheet Backlog
A1: Clave del caso | B1: Evaluación real del caso | C1: Prioridad real | D1: Fecha alta de la solicitud | E1: Título o Asunto | F1: Descripción detallada y completa del caso | G1: Cliente que solicita | H1: Componente | I1: Area responsable de traccionar | J1: OP | K1: Estado | L1: Fecha Requerida en Producción | M1: Fecha comprometida (para UAT) | N1: Fecha Real de Cierre | O1: Comentarios Funcionales | P1: Comentarios Técnicos | Q1: Referencia al documento | R1: Análisis | S1: Estimación Desarrollo | T1: Desarrollo Realidad | U1: QA/UAT | V1: Implementación | W1: Total | X1: Visto | Y1: Columna3 | Z1: Columna4 | AA1: Fase | AB1: Dias_abiertos | AC1: En_plazo | AJ1: Comentarios SAC
A2: 16613 | B2: Mantenimiento correctivo | C2: Muy alta | D2: 46142 | E2: CNQ-GAMMA-GAMMA-DIFERENCIA CALCULO CSA | F2: EL calculo de CSA tiene diferencias debido a que no esta calculando para todas las maquinas de un PDV motivo: Gamma no actualiza las maquinas activas y habilitadas en los PDV al momento de hacer los cálculos de CSA, tomando solo los datos que ya tenia grabados antes de la nueva implementación del día 6/04/2026. Este problema tambien afecta al cobro de CSA en SALTA | H2: Gamma | K2: Para implementar | AA2: =_xlfn.XLOOKUP(Backlog[[#This Row],[Estado]],CatEstados[Estado],CatEstados[Fase],"Otro") -> Implementación | AB2: =IF(OR(ISBLANK(Backlog[[#This Row],[Fecha comprometida (para UAT)]]),Backlog[[#This Row],[Fecha comprometida (para UAT)]]=""), "Sin fecha comprometida", IF( Backlog[[#This Row],[Fecha Real de Cierre]]="", TODAY()-Backlog[[#This Row],[Fecha comprometida (para UAT)]], Backlog[[#This Row],[Fecha Real de Cierre]]-Backlog[[#This Row],[Fecha comprometida (para UAT)]] ) ) -> Sin fecha comprometida | AC2: =IF(OR(#REF!="",NOT(ISNUMBER(Backlog[[#This Row],[Dias_abiertos]]))),"",IF(Backlog[[#This Row],[Dias_abiertos]]<=7,"En plazo",IFERROR(IF(Backlog[[#This Row],[Dias_abiertos]]=_xlfn.XLOOKUP(TRIM(#REF!),CatSLA[Prioridad],CatSLA[SLA_dias],""),"En plazo","Fuera de plazo"),"Sin SLA"))) -> #REF!
A3: GAMMA-817 SF16721 | B3: Mantenimiento correctivo | C3: Muy alta | D3: 46149 | E3: End-point de adjudicaciones | F3: Se necesita la incorporación del campo fechaTotPremios en la respuesta del end-point de adjudicaciones para la Provincia de La Pampa. Se detecto en esta provincia el faltante de este campo lo que no permite realizar la liquidaciones a sorteo cerrado con premios. | G3: La Pampa | H3: Saaservice | I3: Mantenimiento | K3: Planificado | AA3: =_xlfn.XLOOKUP(Backlog[[#This Row],[Estado]],CatEstados[Estado],CatEstados[Fase],"Otro") -> Por hacer | AB3: =IF(OR(ISBLANK(Backlog[[#This Row],[Fecha comprometida (para UAT)]]),Backlog[[#This Row],[Fecha comprometida (para UAT)]]=""), "Sin fecha comprometida", IF( Backlog[[#This Row],[Fecha Real de Cierre]]="", TODAY()-Backlog[[#This Row],[Fecha comprometida (para UAT)]], Backlog[[#This Row],[Fecha Real de Cierre]]-Backlog[[#This Row],[Fecha comprometida (para UAT)]] ) ) -> Sin fecha comprometida | AC3: =IF(OR(#REF!="",NOT(ISNUMBER(Backlog[[#This Row],[Dias_abiertos]]))),"",IF(Backlog[[#This Row],[Dias_abiertos]]<=7,"En plazo",IFERROR(IF(Backlog[[#This Row],[Dias_abiertos]]=_xlfn.XLOOKUP(TRIM(#REF!),CatSLA[Prioridad],CatSLA[SLA_dias],""),"En plazo","Fuera de plazo"),"Sin SLA"))) -> #REF!
A4: GAMMA-746 SF16529 | B4: Mantenimiento preventivo | C4: Alta | D4: 46140 | E4: Se necesita eliminar el servicio Extract | F4: Servicio Extract: Servicio en desuso que se utilizaba para buscar datos en sistemas externos a gamma. Se necesita Eliminar el servicio. | H4: Gamma | K4: A planificar | AA4: =_xlfn.XLOOKUP(Backlog[[#This Row],[Estado]],CatEstados[Estado],CatEstados[Fase],"Otro") -> Por hacer | AB4: =IF(OR(ISBLANK(Backlog[[#This Row],[Fecha comprometida (para UAT)]]),Backlog[[#This Row],[Fecha comprometida (para UAT)]]=""), "Sin fecha comprometida", IF( Backlog[[#This Row],[Fecha Real de Cierre]]="", TODAY()-Backlog[[#This Row],[Fecha comprometida (para UAT)]], Backlog[[#This Row],[Fecha Real de Cierre]]-Backlog[[#This Row],[Fecha comprometida (para UAT)]] ) ) -> Sin fecha comprometida | AC4: =IF(OR(#REF!="",NOT(ISNUMBER(Backlog[[#This Row],[Dias_abiertos]]))),"",IF(Backlog[[#This Row],[Dias_abiertos]]<=7,"En plazo",IFERROR(IF(Backlog[[#This Row],[Dias_abiertos]]=_xlfn.XLOOKUP(TRIM(#REF!),CatSLA[Prioridad],CatSLA[SLA_dias],""),"En plazo","Fuera de plazo"),"Sin SLA"))) -> #REF!
A5: GAMMA-747 SF16530 | B5: Mantenimiento preventivo | C5: Alta | D5: 46140 | E5: Se necesita Depurar la BD Extract | F5: BD Extract Bd relacionada con servicio Extract y las configuraciones necesarias para lo que se procesaba Se necesita Depurar la BD Tablas con información de procesos executions Borrar todos los registros movement_executions_status Borrar todos los registros | H5: Gamma | K5: A planificar | AA5: =_xlfn.XLOOKUP(Backlog[[#This Row],[Estado]],CatEstados[Estado],CatEstados[Fase],"Otro") -> Por hacer | AB5: =IF(OR(ISBLANK(Backlog[[#This Row],[Fecha comprometida (para UAT)]]),Backlog[[#This Row],[Fecha comprometida (para UAT)]]=""), "Sin fecha comprometida", IF( Backlog[[#This Row],[Fecha Real de Cierre]]="", TODAY()-Backlog[[#This Row],[Fecha comprometida (para UAT)]], Backlog[[#This Row],[Fecha Real de Cierre]]-Backlog[[#This Row],[Fecha comprometida (para UAT)]] ) ) -> Sin fecha comprometida | AC5: =IF(OR(#REF!="",NOT(ISNUMBER(Backlog[[#This Row],[Dias_abiertos]]))),"",IF(Backlog[[#This Row],[Dias_abiertos]]<=7,"En plazo",IFERROR(IF(Backlog[[#This Row],[Dias_abiertos]]=_xlfn.XLOOKUP(TRIM(#REF!),CatSLA[Prioridad],CatSLA[SLA_dias],""),"En plazo","Fuera de plazo"),"Sin SLA"))) -> #REF!
A6: GAMMA-748 SF16531 | B6: Mantenimiento preventivo | C6: Alta | D6: 46140 | E6: Se necesita Eliminar el servicio Transform | F6: Descripción Servicio Transform servicio en desuso que se utilizaba para procesar la información extraída por "Extract" Se necesita Eliminar el servicio. | H6: Gamma | K6: A planificar | AA6: =_xlfn.XLOOKUP(Backlog[[#This Row],[Estado]],CatEstados[Estado],CatEstados[Fase],"Otro") -> Por hacer | AB6: =IF(OR(ISBLANK(Backlog[[#This Row],[Fecha comprometida (para UAT)]]),Backlog[[#This Row],[Fecha comprometida (para UAT)]]=""), "Sin fecha comprometida", IF( Backlog[[#This Row],[Fecha Real de Cierre]]="", TODAY()-Backlog[[#This Row],[Fecha comprometida (para UAT)]], Backlog[[#This Row],[Fecha Real de Cierre]]-Backlog[[#This Row],[Fecha comprometida (para UAT)]] ) ) -> Sin fecha comprometida | AC6: =IF(OR(#REF!="",NOT(ISNUMBER(Backlog[[#This Row],[Dias_abiertos]]))),"",IF(Backlog[[#This Row],[Dias_abiertos]]<=7,"En plazo",IFERROR(IF(Backlog[[#This Row],[Dias_abiertos]]=_xlfn.XLOOKUP(TRIM(#REF!),CatSLA[Prioridad],CatSLA[SLA_dias],""),"En plazo","Fuera de plazo"),"Sin SLA"))) -> #REF!
A7: GAMMA-749 SF16532 | B7: Mantenimiento preventivo | C7: Alta | D7: 46140 | E7: Se necesita Depurar la BD Transform | F7: Descripción BD Transform BD relacionada con el servicio Transform Se necesita Depurar la BD Tablas con información del proceso no hay datos | H7: Gamma | K7: A planificar | AA7: =_xlfn.XLOOKUP(Backlog[[#This Row],[Estado]],CatEstados[Estado],CatEstados[Fase],"Otro") -> Por hacer | AB7: =IF(OR(ISBLANK(Backlog[[#This Row],[Fecha comprometida (para UAT)]]),Backlog[[#This Row],[Fecha comprometida (para UAT)]]=""), "Sin fecha comprometida", IF( Backlog[[#This Row],[Fecha Real de Cierre]]="", TODAY()-Backlog[[#This Row],[Fecha comprometida (para UAT)]], Backlog[[#This Row],[Fecha Real de Cierre]]-Backlog[[#This Row],[Fecha comprometida (para UAT)]] ) ) -> Sin fecha comprometida | AC7: =IF(OR(#REF!="",NOT(ISNUMBER(Backlog[[#This Row],[Dias_abiertos]]))),"",IF(Backlog[[#This Row],[Dias_abiertos]]<=7,"En plazo",IFERROR(IF(Backlog[[#This Row],[Dias_abiertos]]=_xlfn.XLOOKUP(TRIM(#REF!),CatSLA[Prioridad],CatSLA[SLA_dias],""),"En plazo","Fuera de plazo"),"Sin SLA"))) -> #REF!
A8: GAMMA-750 SF16533 | B8: Mantenimiento preventivo | C8: Alta | D8: 46140 | E8: Se necesita Eliminar el servicio Load | F8: Servicio Load servicio que se utilizaba para homologar(guardar) la información generada por "Transform" y otros servicios Se necesita Eliminar el servicio. | H8: Gamma | K8: A planificar | AA8: =_xlfn.XLOOKUP(Backlog[[#This Row],[Estado]],CatEstados[Estado],CatEstados[Fase],"Otro") -> Por hacer | AB8: =IF(OR(ISBLANK(Backlog[[#This Row],[Fecha comprometida (para UAT)]]),Backlog[[#This Row],[Fecha comprometida (para UAT)]]=""), "Sin fecha comprometida", IF( Backlog[[#This Row],[Fecha Real de Cierre]]="", TODAY()-Backlog[[#This Row],[Fecha comprometida (para UAT)]], Backlog[[#This Row],[Fecha Real de Cierre]]-Backlog[[#This Row],[Fecha comprometida (para UAT)]] ) ) -> Sin fecha comprometida | AC8: =IF(OR(#REF!="",NOT(ISNUMBER(Backlog[[#This Row],[Dias_abiertos]]))),"",IF(Backlog[[#This Row],[Dias_abiertos]]<=7,"En plazo",IFERROR(IF(Backlog[[#This Row],[Dias_abiertos]]=_xlfn.XLOOKUP(TRIM(#REF!),CatSLA[Prioridad],CatSLA[SLA_dias],""),"En plazo","Fuera de plazo"),"Sin SLA"))) -> #REF!
A9: GAMMA-751 SF16534 | B9: Mantenimiento preventivo | C9: Alta | D9: 46140 | E9: Se necesita Depurar la BD Load | F9: BD Load BD relacionada con el servicio Load Se necesita Depurar la BD Tablas con información del proceso errors Borrar todos los registros non_homologated_movements Borrar todos los registros non_homologated_raffles Borrar todos los registros raffles Borrar todos los registros success_movements Borrar todos los registros | H9: Gamma | K9: A planificar | AA9: =_xlfn.XLOOKUP(Backlog[[#This Row],[Estado]],CatEstados[Estado],CatEstados[Fase],"Otro") -> Por hacer | AB9: =IF(OR(ISBLANK(Backlog[[#This Row],[Fecha comprometida (para UAT)]]),Backlog[[#This Row],[Fecha comprometida (para UAT)]]=""), "Sin fecha comprometida", IF( Backlog[[#This Row],[Fecha Real de Cierre]]="", TODAY()-Backlog[[#This Row],[Fecha comprometida (para UAT)]], Backlog[[#This Row],[Fecha Real de Cierre]]-Backlog[[#This Row],[Fecha comprometida (para UAT)]] ) ) -> Sin fecha comprometida | AC9: =IF(OR(#REF!="",NOT(ISNUMBER(Backlog[[#This Row],[Dias_abiertos]]))),"",IF(Backlog[[#This Row],[Dias_abiertos]]<=7,"En plazo",IFERROR(IF(Backlog[[#This Row],[Dias_abiertos]]=_xlfn.XLOOKUP(TRIM(#REF!),CatSLA[Prioridad],CatSLA[SLA_dias],""),"En plazo","Fuera de plazo"),"Sin SLA"))) -> #REF!
A10: GAMMA-752 SF16535 | B10: Mantenimiento preventivo | C10: Alta | D10: 46140 | E10: Se necesita Eliminar el servicio Rulesengine | F10: Servicio Rulesengine servicio que se utilizaba para administrar y procesar las reglas de la loteria ademas de procesar informacion para las mismas Se necesita Eliminar el servicio. | H10: Gamma | K10: A planificar | AA10: =_xlfn.XLOOKUP(Backlog[[#This Row],[Estado]],CatEstados[Estado],CatEstados[Fase],"Otro") -> Por hacer | AB10: =IF(OR(ISBLANK(Backlog[[#This Row],[Fecha comprometida (para UAT)]]),Backlog[[#This Row],[Fecha comprometida (para UAT)]]=""), "Sin fecha comprometida", IF( Backlog[[#This Row],[Fecha Real de Cierre]]="", TODAY()-Backlog[[#This Row],[Fecha comprometida (para UAT)]], Backlog[[#This Row],[Fecha Real de Cierre]]-Backlog[[#This Row],[Fecha comprometida (para UAT)]] ) ) -> Sin fecha comprometida | AC10: =IF(OR(#REF!="",NOT(ISNUMBER(Backlog[[#This Row],[Dias_abiertos]]))),"",IF(Backlog[[#This Row],[Dias_abiertos]]<=7,"En plazo",IFERROR(IF(Backlog[[#This Row],[Dias_abiertos]]=_xlfn.XLOOKUP(TRIM(#REF!),CatSLA[Prioridad],CatSLA[SLA_dias],""),"En plazo","Fuera de plazo"),"Sin SLA"))) -> #REF!
A11: GAMMA-753 SF16536 | B11: Mantenimiento preventivo | C11: Alta | D11: 46140 | E11: Se necesita Depurar la BD Rulesengine | F11: BD Rulesengine BD relacionada con el servicio Rulesengine Se necesita Depurar la BD Tablas con informacion del proceso adjacent_rules Borrar todos los registros execution_history Borrar todos los registros item_conditions Borrar todos los registros kafka_errors Borrar todos los registros processable_item_groups Borrar todos los registros processable_items Borrar todos los registros processed_items Borrar todos los registros processed_items_relations Borrar todos los registros rule_conditions Borrar todos los registros rule_indexes Borrar todos los registros rules Borrar todos los registros | H11: Gamma | K11: A planificar | AA11: =_xlfn.XLOOKUP(Backlog[[#This Row],[Estado]],CatEstados[Estado],CatEstados[Fase],"Otro") -> Por hacer | AB11: =IF(OR(ISBLANK(Backlog[[#This Row],[Fecha comprometida (para UAT)]]),Backlog[[#This Row],[Fecha comprometida (para UAT)]]=""), "Sin fecha comprometida", IF( Backlog[[#This Row],[Fecha Real de Cierre]]="", TODAY()-Backlog[[#This Row],[Fecha comprometida (para UAT)]], Backlog[[#This Row],[Fecha Real de Cierre]]-Backlog[[#This Row],[Fecha comprometida (para UAT)]] ) ) -> Sin fecha comprometida | AC11: =IF(OR(#REF!="",NOT(ISNUMBER(Backlog[[#This Row],[Dias_abiertos]]))),"",IF(Backlog[[#This Row],[Dias_abiertos]]<=7,"En plazo",IFERROR(IF(Backlog[[#This Row],[Dias_abiertos]]=_xlfn.XLOOKUP(TRIM(#REF!),CatSLA[Prioridad],CatSLA[SLA_dias],""),"En plazo","Fuera de plazo"),"Sin SLA"))) -> #REF!
A12: GAMMA-754 SF16537 | B12: Mantenimiento preventivo | C12: Alta | D12: 46140 | E12: Depurar BD ETL | F12: BD ETL Tablas con informacion del proceso a depurar no_homologated Borrado selectivo Registros con fecha de borrado logico borrar todos Registros sin fecha de borrado logico borrar los registros de mas de 31 dias de antiguidad procesos Borrado selectivo Borrar los registros de mas de 31 dias de antiguidad | H12: Gamma | K12: A planificar | AA12: =_xlfn.XLOOKUP(Backlog[[#This Row],[Estado]],CatEstados[Estado],CatEstados[Fase],"Otro") -> Por hacer | AB12: =IF(OR(ISBLANK(Backlog[[#This Row],[Fecha comprometida (para UAT)]]),Backlog[[#This Row],[Fecha comprometida (para UAT)]]=""), "Sin fecha comprometida", IF( Backlog[[#This Row],[Fecha Real de Cierre]]="", TODAY()-Backlog[[#This Row],[Fecha comprometida (para UAT)]], Backlog[[#This Row],[Fecha Real de Cierre]]-Backlog[[#This Row],[Fecha comprometida (para UAT)]] ) ) -> Sin fecha comprometida | AC12: =IF(OR(#REF!="",NOT(ISNUMBER(Backlog[[#This Row],[Dias_abiertos]]))),"",IF(Backlog[[#This Row],[Dias_abiertos]]<=7,"En plazo",IFERROR(IF(Backlog[[#This Row],[Dias_abiertos]]=_xlfn.XLOOKUP(TRIM(#REF!),CatSLA[Prioridad],CatSLA[SLA_dias],""),"En plazo","Fuera de plazo"),"Sin SLA"))) -> #REF!
A13: GAMMA-755 SF16538 | B13: Mantenimiento preventivo | C13: Alta | D13: 46140 | E13: Depurar BD Contability | F13: BD Contability Tablas con informacion del proceso a depurar entries Borrado selectivo Registros con fecha de borrado logico borrar todos entry_rows Borrado selectivo Registros con fecha de borrado logico borrar todos file_entries Borrado selectivo Registros con fecha de borrado logico borrar todos | H13: Gamma | K13: A planificar | AA13: =_xlfn.XLOOKUP(Backlog[[#This Row],[Estado]],CatEstados[Estado],CatEstados[Fase],"Otro") -> Por hacer | AB13: =IF(OR(ISBLANK(Backlog[[#This Row],[Fecha comprometida (para UAT)]]),Backlog[[#This Row],[Fecha comprometida (para UAT)]]=""), "Sin fecha comprometida", IF( Backlog[[#This Row],[Fecha Real de Cierre]]="", TODAY()-Backlog[[#This Row],[Fecha comprometida (para UAT)]], Backlog[[#This Row],[Fecha Real de Cierre]]-Backlog[[#This Row],[Fecha comprometida (para UAT)]] ) ) -> Sin fecha comprometida | AC13: =IF(OR(#REF!="",NOT(ISNUMBER(Backlog[[#This Row],[Dias_abiertos]]))),"",IF(Backlog[[#This Row],[Dias_abiertos]]<=7,"En plazo",IFERROR(IF(Backlog[[#This Row],[Dias_abiertos]]=_xlfn.XLOOKUP(TRIM(#REF!),CatSLA[Prioridad],CatSLA[SLA_dias],""),"En plazo","Fuera de plazo"),"Sin SLA"))) -> #REF!
A14: GAMMA-756 SF16539 | B14: Mantenimiento preventivo | C14: Alta | D14: 46140 | E14: Depurar BD Checking_account | F14: BD Checking_account Tablas con informacion del proceso a depurar agency_settlements Borrado selectivo Registros con fecha de borrado logico borrar todos execution_movements Borrar todos los registros kafka_errors Borrar todos los registros movements Borrado selectivo calculated_movements antes del borrado de movementes Borrado selectivo Registros con movimientos con fecha de borrado logico con mas de 31 dias de antiguidad Registros con fecha de borrado logico con mas de 31 dias de antiguidad movements_processed_items Borrar todos los registros processed_items Borrar todos los registros settlement_events Borrado selectivo Registros con fecha de borrado logico borrar todo settlements Borrado selectivo Registros con status cancelados borrar todos tmp_minimos Borrar todos los registros | H14: Gamma | K14: A planificar | AA14: =_xlfn.XLOOKUP(Backlog[[#This Row],[Estado]],CatEstados[Estado],CatEstados[Fase],"Otro") -> Por hacer | AB14: =IF(OR(ISBLANK(Backlog[[#This Row],[Fecha comprometida (para UAT)]]),Backlog[[#This Row],[Fecha comprometida (para UAT)]]=""), "Sin fecha comprometida", IF( Backlog[[#This Row],[Fecha Real de Cierre]]="", TODAY()-Backlog[[#This Row],[Fecha comprometida (para UAT)]], Backlog[[#This Row],[Fecha Real de Cierre]]-Backlog[[#This Row],[Fecha comprometida (para UAT)]] ) ) -> Sin fecha comprometida | AC14: =IF(OR(#REF!="",NOT(ISNUMBER(Backlog[[#This Row],[Dias_abiertos]]))),"",IF(Backlog[[#This Row],[Dias_abiertos]]<=7,"En plazo",IFERROR(IF(Backlog[[#This Row],[Dias_abiertos]]=_xlfn.XLOOKUP(TRIM(#REF!),CatSLA[Prioridad],CatSLA[SLA_dias],""),"En plazo","Fuera de plazo"),"Sin SLA"))) -> #REF!
A15: SF16554 | B15: Mantenimiento correctivo | C15: Muy alta | D15: 46140 | E15: CORR-NOA Error al cargar predistribución | F15: Al intentar cargar el archivo de redistribución se genera un error que deja como pendiente el proceso. Se necesita tener todo cargado los sorteos de mayo a más tardar resuelto el día jueves 30/04. Se adjunta imagen del error | G15: Corrientes | H15: NOA | I15: SAC | K15: A priorizar | O15: NOA tiene que filtrar las concentradoras | S15: 24 | AA15: =_xlfn.XLOOKUP(Backlog[[#This Row],[Estado]],CatEstados[Estado],CatEstados[Fase],"Otro") -> Por hacer | AB15: =IF(OR(ISBLANK(Backlog[[#This Row],[Fecha comprometida (para UAT)]]),Backlog[[#This Row],[Fecha comprometida (para UAT)]]=""), "Sin fecha comprometida", IF( Backlog[[#This Row],[Fecha Real de Cierre]]="", TODAY()-Backlog[[#This Row],[Fecha comprometida (para UAT)]], Backlog[[#This Row],[Fecha Real de Cierre]]-Backlog[[#This Row],[Fecha comprometida (para UAT)]] ) ) -> Sin fecha comprometida | AC15: =IF(OR(#REF!="",NOT(ISNUMBER(Backlog[[#This Row],[Dias_abiertos]]))),"",IF(Backlog[[#This Row],[Dias_abiertos]]<=7,"En plazo",IFERROR(IF(Backlog[[#This Row],[Dias_abiertos]]=_xlfn.XLOOKUP(TRIM(#REF!),CatSLA[Prioridad],CatSLA[SLA_dias],""),"En plazo","Fuera de plazo"),"Sin SLA"))) -> #REF!
A16: GAMMA - 000719 SF16366 | B16: Mantenimiento evolutivo | C16: Alta | D16: 46135 | E16: Adaptar archivo D&B para aceptar múltiples conceptos | F16: En SIGA hoy en dia cargan un archivo apuntado a varios codigos contables | G16: Santiago del Estero | H16: Gamma | I16: Mantenimiento | J16: 1 | K16: En desarrollo | L16: 46142 | O16: Autorizado por la direccción | P16: Desarrollado - Jimena | Q16: Adaptar archivo D&B para aceptar múltiples conceptos - 1.2.pdf | S16: 120 | T16: 9 | AA16: =_xlfn.XLOOKUP(Backlog[[#This Row],[Estado]],CatEstados[Estado],CatEstados[Fase],"Otro") -> En curso | AB16: =IF(OR(ISBLANK(Backlog[[#This Row],[Fecha comprometida (para UAT)]]),Backlog[[#This Row],[Fecha comprometida (para UAT)]]=""), "Sin fecha comprometida", IF( Backlog[[#This Row],[Fecha Real de Cierre]]="", TODAY()-Backlog[[#This Row],[Fecha comprometida (para UAT)]], Backlog[[#This Row],[Fecha Real de Cierre]]-Backlog[[#This Row],[Fecha comprometida (para UAT)]] ) ) -> Sin fecha comprometida | AC16: =IF(OR(#REF!="",NOT(ISNUMBER(Backlog[[#This Row],[Dias_abiertos]]))),"",IF(Backlog[[#This Row],[Dias_abiertos]]<=7,"En plazo",IFERROR(IF(Backlog[[#This Row],[Dias_abiertos]]=_xlfn.XLOOKUP(TRIM(#REF!),CatSLA[Prioridad],CatSLA[SLA_dias],""),"En plazo","Fuera de plazo"),"Sin SLA"))) -> #REF!
A17: GAMMA - 000722 SF16367 | B17: Mantenimiento evolutivo | C17: Alta | D17: 46135 | E17: Adaptar archivo D&B para aceptar operaciones de Embargos y Garantías | F17: En SIGA hoy en dia cargan un archivo donde indican un numero de porcentaje para que el sistema realice un calculo (Garantia, Embargo judicial, etc), a su vez, colocan en el archivo un importe de tope para descuento. GAMMA no acepta este tipo de archivos y no aplica calculos desde d&b. | G17: Santiago del Estero | H17: Gamma | I17: Mantenimiento | J17: 2 | K17: En desarrollo | L17: 46142 | O17: Autorizado por la direccción | P17: Desarrollado - Jimena | Q17: Adaptar archivo D&B para aceptar operaciones de Embargos y Garantías - 1.0.pdf | S17: 160 | T17: 13 | AA17: =_xlfn.XLOOKUP(Backlog[[#This Row],[Estado]],CatEstados[Estado],CatEstados[Fase],"Otro") -> En curso | AB17: =IF(OR(ISBLANK(Backlog[[#This Row],[Fecha comprometida (para UAT)]]),Backlog[[#This Row],[Fecha comprometida (para UAT)]]=""), "Sin fecha comprometida", IF( Backlog[[#This Row],[Fecha Real de Cierre]]="", TODAY()-Backlog[[#This Row],[Fecha comprometida (para UAT)]], Backlog[[#This Row],[Fecha Real de Cierre]]-Backlog[[#This Row],[Fecha comprometida (para UAT)]] ) ) -> Sin fecha comprometida | AC17: =IF(OR(#REF!="",NOT(ISNUMBER(Backlog[[#This Row],[Dias_abiertos]]))),"",IF(Backlog[[#This Row],[Dias_abiertos]]<=7,"En plazo",IFERROR(IF(Backlog[[#This Row],[Dias_abiertos]]=_xlfn.XLOOKUP(TRIM(#REF!),CatSLA[Prioridad],CatSLA[SLA_dias],""),"En plazo","Fuera de plazo"),"Sin SLA"))) -> #REF!
A18: 16608 | B18: Mantenimiento evolutivo | C18: Alta | D18: 46142 | E18: Configuracion particular de vencimientos por PDV | F18: En SIGA tienen configurado para cada agencia un dia de vencimiento en particular, con la particularidad de que cuando llega el dia previo al pago, el pago se saltea a la semana siguiente con el fin de que al PDV le quede, al menos, una recaudacion para su uso. | G18: Santiago del Estero | H18: Gamma | I18: Mantenimiento | J18: 5 | K18: En desarrollo | L18: 46147 | O18: Autorizado por la direccción | P18: Desarrollado - Jimena | Q18: SDE - GAMMA - Configuracion particular de vencimientos por PDV - 1.1.pdf | S18: 136 | T18: 9 | AA18: =_xlfn.XLOOKUP(Backlog[[#This Row],[Estado]],CatEstados[Estado],CatEstados[Fase],"Otro") -> En curso | AB18: =IF(OR(ISBLANK(Backlog[[#This Row],[Fecha comprometida (para UAT)]]),Backlog[[#This Row],[Fecha comprometida (para UAT)]]=""), "Sin fecha comprometida", IF( Backlog[[#This Row],[Fecha Real de Cierre]]="", TODAY()-Backlog[[#This Row],[Fecha comprometida (para UAT)]], Backlog[[#This Row],[Fecha Real de Cierre]]-Backlog[[#This Row],[Fecha comprometida (para UAT)]] ) ) -> Sin fecha comprometida | AC18: =IF(OR(#REF!="",NOT(ISNUMBER(Backlog[[#This Row],[Dias_abiertos]]))),"",IF(Backlog[[#This Row],[Dias_abiertos]]<=7,"En plazo",IFERROR(IF(Backlog[[#This Row],[Dias_abiertos]]=_xlfn.XLOOKUP(TRIM(#REF!),CatSLA[Prioridad],CatSLA[SLA_dias],""),"En plazo","Fuera de plazo"),"Sin SLA"))) -> #REF!
A19: 16609 | B19: Mantenimiento evolutivo | C19: Alta | D19: 46142 | E19: Republicacion de deuda | F19: Al momento de aplicarse el nuevo sistema bancario (2026) la Loteria iniciara a realizar la republicacion de deuda. Hoy en dia en SIGA se encuentra esta opcion disponible generandose un nuevo archivos con dos opciones de habilitarlo: 1) Dia de emision de cta.cte: genera archivo con todas las agencias que no cancelaron el resumen colocandole nueva fecha de vencimiento. 2) Por agencia: Permite seleccionar los resumenes pendientes que se deciden abonar, genera un archivo con la informacion preseleccionada y se le coloca la nueva fecha de vencimiento. | G19: Santiago del Estero | H19: Gamma | I19: Mantenimiento | J19: 6 | K19: A planificar | O19: Autorizado por la direccción | Q19: SDE - GAMMA - Republicación de deuda - 1.0.docx | S19: 160 | AA19: =_xlfn.XLOOKUP(Backlog[[#This Row],[Estado]],CatEstados[Estado],CatEstados[Fase],"Otro") -> Por hacer | AB19: =IF(OR(ISBLANK(Backlog[[#This Row],[Fecha comprometida (para UAT)]]),Backlog[[#This Row],[Fecha comprometida (para UAT)]]=""), "Sin fecha comprometida", IF( Backlog[[#This Row],[Fecha Real de Cierre]]="", TODAY()-Backlog[[#This Row],[Fecha comprometida (para UAT)]], Backlog[[#This Row],[Fecha Real de Cierre]]-Backlog[[#This Row],[Fecha comprometida (para UAT)]] ) ) -> Sin fecha comprometida | AC19: =IF(OR(#REF!="",NOT(ISNUMBER(Backlog[[#This Row],[Dias_abiertos]]))),"",IF(Backlog[[#This Row],[Dias_abiertos]]<=7,"En plazo",IFERROR(IF(Backlog[[#This Row],[Dias_abiertos]]=_xlfn.XLOOKUP(TRIM(#REF!),CatSLA[Prioridad],CatSLA[SLA_dias],""),"En plazo","Fuera de plazo"),"Sin SLA"))) -> #REF!
A20: GAMMA - 000739 16403 | B20: Mantenimiento evolutivo | C20: Alta | D20: 46136 | E20: ID717 - Ampliar funcional de roles y perfiles | F20: En GAMMA actualmente se puede realizar BP desde el modulo "Loteria" y desde el modulo de "Caja" por cualquier usuario con un rol que permita el ingreso a esos modulos. La Loteria solicita que la accion del BP no pueda ser realizada por cualquier usuario, sino por alguien autorizado (rol personalizado) | G20: Santiago del Estero | H20: Gamma | I20: Mantenimiento | J20: 3 | K20: A planificar | O20: Autorizado por la direccción | Q20: ID717 - Gamma - Cambios en los roles actuales - 2.0.docx | S20: 400 | AA20: =_xlfn.XLOOKUP(Backlog[[#This Row],[Estado]],CatEstados[Estado],CatEstados[Fase],"Otro") -> Por hacer | AB20: =IF(OR(ISBLANK(Backlog[[#This Row],[Fecha comprometida (para UAT)]]),Backlog[[#This Row],[Fecha comprometida (para UAT)]]=""), "Sin fecha comprometida", IF( Backlog[[#This Row],[Fecha Real de Cierre]]="", TODAY()-Backlog[[#This Row],[Fecha comprometida (para UAT)]], Backlog[[#This Row],[Fecha Real de Cierre]]-Backlog[[#This Row],[Fecha comprometida (para UAT)]] ) ) -> Sin fecha comprometida | AC20: =IF(OR(#REF!="",NOT(ISNUMBER(Backlog[[#This Row],[Dias_abiertos]]))),"",IF(Backlog[[#This Row],[Dias_abiertos]]<=7,"En plazo",IFERROR(IF(Backlog[[#This Row],[Dias_abiertos]]=_xlfn.XLOOKUP(TRIM(#REF!),CatSLA[Prioridad],CatSLA[SLA_dias],""),"En plazo","Fuera de plazo"),"Sin SLA"))) -> #REF!
A21: GAMMA - 000738 16404 | B21: Mantenimiento evolutivo | C21: Alta | D21: 46136 | E21: Resumen para pago en banco con código de barras | F21: hoy en dia SIGA genera un reporte/listado con los resumenes bancarios a pagar colocandole un talon de pago con codigo de barra, GAMMA genera el reporte SIN el talon de pago. | G21: Santiago del Estero | H21: Gamma | I21: Mantenimiento | J21: 8 | K21: En desarrollo | L21: 46147 | O21: Autorizado por la direccción | P21: Alejandro Falta pruebas unitarias | Q21: SDE - Gamma - Código de barras para el resumen de agentes - 1.1.pdf | S21: 32 | T21: 8 | AA21: =_xlfn.XLOOKUP(Backlog[[#This Row],[Estado]],CatEstados[Estado],CatEstados[Fase],"Otro") -> En curso | AB21: =IF(OR(ISBLANK(Backlog[[#This Row],[Fecha comprometida (para UAT)]]),Backlog[[#This Row],[Fecha comprometida (para UAT)]]=""), "Sin fecha comprometida", IF( Backlog[[#This Row],[Fecha Real de Cierre]]="", TODAY()-Backlog[[#This Row],[Fecha comprometida (para UAT)]], Backlog[[#This Row],[Fecha Real de Cierre]]-Backlog[[#This Row],[Fecha comprometida (para UAT)]] ) ) -> Sin fecha comprometida | AC21: =IF(OR(#REF!="",NOT(ISNUMBER(Backlog[[#This Row],[Dias_abiertos]]))),"",IF(Backlog[[#This Row],[Dias_abiertos]]<=7,"En plazo",IFERROR(IF(Backlog[[#This Row],[Dias_abiertos]]=_xlfn.XLOOKUP(TRIM(#REF!),CatSLA[Prioridad],CatSLA[SLA_dias],""),"En plazo","Fuera de plazo"),"Sin SLA"))) -> #REF!
A22: 16453 | B22: Mantenimiento evolutivo | C22: Alta | D22: 46136 | E22: Adaptar GAMMA para poder liquidar día abierto | F22: GAMMA no está permitiendo liquidar con la config a día abierto >>> DC Probar lunes 15 x la noche (2340hs / 00.05hs) >> Martes evaluar resultados | G22: Santiago del Estero | H22: Gamma | I22: Mantenimiento | J22: 9 | K22: En desarrollo | L22: 46150 | O22: Autorizado por la direccción | P22: Desarrollado - Tejerina | Q22: SDE - GAMMA - Adaptar GAMMA para poder liquidar día abierto - v1.2.pdf | S22: 400 | AA22: =_xlfn.XLOOKUP(Backlog[[#This Row],[Estado]],CatEstados[Estado],CatEstados[Fase],"Otro") -> En curso | AB22: =IF(OR(ISBLANK(Backlog[[#This Row],[Fecha comprometida (para UAT)]]),Backlog[[#This Row],[Fecha comprometida (para UAT)]]=""), "Sin fecha comprometida", IF( Backlog[[#This Row],[Fecha Real de Cierre]]="", TODAY()-Backlog[[#This Row],[Fecha comprometida (para UAT)]], Backlog[[#This Row],[Fecha Real de Cierre]]-Backlog[[#This Row],[Fecha comprometida (para UAT)]] ) ) -> Sin fecha comprometida | AC22: =IF(OR(#REF!="",NOT(ISNUMBER(Backlog[[#This Row],[Dias_abiertos]]))),"",IF(Backlog[[#This Row],[Dias_abiertos]]<=7,"En plazo",IFERROR(IF(Backlog[[#This Row],[Dias_abiertos]]=_xlfn.XLOOKUP(TRIM(#REF!),CatSLA[Prioridad],CatSLA[SLA_dias],""),"En plazo","Fuera de plazo"),"Sin SLA"))) -> #REF!
A23: 16454 | B23: Mantenimiento evolutivo | C23: Alta | D23: 46136 | E23: Buzón para envió de documentación con indicador de lectura (envío masivo de cert de IIBB) | F23: El buzón se encuentra en fase de pruebas QA pero el pedido de la lotería es que se pueda realizar envío masivo de los cert de IIBB | G23: Santiago del Estero | H23: Gamma | I23: Mantenimiento | J23: 48 | K23: En desarrollo | O23: Autorizado por la direccción | P23: Alejandro. Desarrollado. | Q23: Lotemovil – Envío masivo de certificados IIBB con acuse de lectura - 1.2.docx | S23: 100 | AA23: =_xlfn.XLOOKUP(Backlog[[#This Row],[Estado]],CatEstados[Estado],CatEstados[Fase],"Otro") -> En curso | AB23: =IF(OR(ISBLANK(Backlog[[#This Row],[Fecha comprometida (para UAT)]]),Backlog[[#This Row],[Fecha comprometida (para UAT)]]=""), "Sin fecha comprometida", IF( Backlog[[#This Row],[Fecha Real de Cierre]]="", TODAY()-Backlog[[#This Row],[Fecha comprometida (para UAT)]], Backlog[[#This Row],[Fecha Real de Cierre]]-Backlog[[#This Row],[Fecha comprometida (para UAT)]] ) ) -> Sin fecha comprometida | AC23: =IF(OR(#REF!="",NOT(ISNUMBER(Backlog[[#This Row],[Dias_abiertos]]))),"",IF(Backlog[[#This Row],[Dias_abiertos]]<=7,"En plazo",IFERROR(IF(Backlog[[#This Row],[Dias_abiertos]]=_xlfn.XLOOKUP(TRIM(#REF!),CatSLA[Prioridad],CatSLA[SLA_dias],""),"En plazo","Fuera de plazo"),"Sin SLA"))) -> #REF!
A24: 16455 | B24: Mantenimiento evolutivo | C24: Alta | D24: 46137 | E24: Visualizar estado de resúmenes en pantalla | F24: Estado de los resúmenes para que el dueño de agencias pueda ver y controlar | G24: Santiago del Estero | H24: Gamma | I24: Mantenimiento | J24: 49 | K24: En desarrollo | O24: Autorizado por la direccción | P24: Alejandro. Desarrollado. | Q24: https://tecnoaccionsa.sharepoint.com/:w:/s/GAMMA.2024/IQAaIvvg3eg5SJVxUyCXE6IBAc_JlFy7qcMdpOnljAxsJmY?e=ffUJif | S24: 60 | AA24: =_xlfn.XLOOKUP(Backlog[[#This Row],[Estado]],CatEstados[Estado],CatEstados[Fase],"Otro") -> En curso | AB24: =IF(OR(ISBLANK(Backlog[[#This Row],[Fecha comprometida (para UAT)]]),Backlog[[#This Row],[Fecha comprometida (para UAT)]]=""), "Sin fecha comprometida", IF( Backlog[[#This Row],[Fecha Real de Cierre]]="", TODAY()-Backlog[[#This Row],[Fecha comprometida (para UAT)]], Backlog[[#This Row],[Fecha Real de Cierre]]-Backlog[[#This Row],[Fecha comprometida (para UAT)]] ) ) -> Sin fecha comprometida | AC24: =IF(OR(#REF!="",NOT(ISNUMBER(Backlog[[#This Row],[Dias_abiertos]]))),"",IF(Backlog[[#This Row],[Dias_abiertos]]<=7,"En plazo",IFERROR(IF(Backlog[[#This Row],[Dias_abiertos]]=_xlfn.XLOOKUP(TRIM(#REF!),CatSLA[Prioridad],CatSLA[SLA_dias],""),"En plazo","Fuera de plazo"),"Sin SLA"))) -> #REF!
A25: 16456 | B25: Mantenimiento evolutivo | C25: Alta | D25: 46136 | E25: Control y cierre de TJ's - ver cierres m9 y m5 | F25: Control de las operaciones de m9 (se usa para el cierre de sorteo y/o consultas) y m5 (fin de jornada) por TJ | G25: Santiago del Estero | H25: Gamma | I25: Mantenimiento | J25: 50 | K25: En desarrollo | O25: Autorizado por la direccción | P25: Paolo y Marcos en desarrollo | Q25: Lotemovil – Control y cierre de TJ ver cierres M9 y M5 - 1.0.docx | S25: 100 | AA25: =_xlfn.XLOOKUP(Backlog[[#This Row],[Estado]],CatEstados[Estado],CatEstados[Fase],"Otro") -> En curso | AB25: =IF(OR(ISBLANK(Backlog[[#This Row],[Fecha comprometida (para UAT)]]),Backlog[[#This Row],[Fecha comprometida (para UAT)]]=""), "Sin fecha comprometida", IF( Backlog[[#This Row],[Fecha Real de Cierre]]="", TODAY()-Backlog[[#This Row],[Fecha comprometida (para UAT)]], Backlog[[#This Row],[Fecha Real de Cierre]]-Backlog[[#This Row],[Fecha comprometida (para UAT)]] ) ) -> Sin fecha comprometida | AC25: =IF(OR(#REF!="",NOT(ISNUMBER(Backlog[[#This Row],[Dias_abiertos]]))),"",IF(Backlog[[#This Row],[Dias_abiertos]]<=7,"En plazo",IFERROR(IF(Backlog[[#This Row],[Dias_abiertos]]=_xlfn.XLOOKUP(TRIM(#REF!),CatSLA[Prioridad],CatSLA[SLA_dias],""),"En plazo","Fuera de plazo"),"Sin SLA"))) -> #REF!
A26: 16458 | B26: Mantenimiento evolutivo | C26: Alta | D26: 46136 | E26: Control y cierre de TJ's - ver productividad por máquina con apertura igual a la de lotermovil viejo | F26: Control y cierre de TJ's - ver productividad por máquina con apertura igual a la de lotermovil viejo | G26: Santiago del Estero | H26: Gamma | I26: Mantenimiento | J26: 51 | K26: En desarrollo | O26: Autorizado por la direccción | P26: Paolo y Marcos en desarrollo. | Q26: Lotemovil – Control y cierre de TJ ver productividad por terminal - 1.2.docx | S26: 100 | AA26: =_xlfn.XLOOKUP(Backlog[[#This Row],[Estado]],CatEstados[Estado],CatEstados[Fase],"Otro") -> En curso | AB26: =IF(OR(ISBLANK(Backlog[[#This Row],[Fecha comprometida (para UAT)]]),Backlog[[#This Row],[Fecha comprometida (para UAT)]]=""), "Sin fecha comprometida", IF( Backlog[[#This Row],[Fecha Real de Cierre]]="", TODAY()-Backlog[[#This Row],[Fecha comprometida (para UAT)]], Backlog[[#This Row],[Fecha Real de Cierre]]-Backlog[[#This Row],[Fecha comprometida (para UAT)]] ) ) -> Sin fecha comprometida | AC26: =IF(OR(#REF!="",NOT(ISNUMBER(Backlog[[#This Row],[Dias_abiertos]]))),"",IF(Backlog[[#This Row],[Dias_abiertos]]<=7,"En plazo",IFERROR(IF(Backlog[[#This Row],[Dias_abiertos]]=_xlfn.XLOOKUP(TRIM(#REF!),CatSLA[Prioridad],CatSLA[SLA_dias],""),"En plazo","Fuera de plazo"),"Sin SLA"))) -> #REF!
A27: 16667 | B27: Mantenimiento evolutivo | C27: Alta | D27: 46146 | E27: Listado - estado general de resúmenes histórico | F27: Listados/Listados Generales/Contaduría/ Liquidaciones Agentes/Resúmenes para Lotería/estado general de resúmenes histórico | G27: Santiago del Estero | H27: Gamma | I27: Mantenimiento | J27: 13 | K27: A planificar | O27: Autorizado por la direccción | Q27: SDE - GAMMA - Listado - estado general de resúmenes histórico - 1.0.docx | S27: 24 | AA27: =_xlfn.XLOOKUP(Backlog[[#This Row],[Estado]],CatEstados[Estado],CatEstados[Fase],"Otro") -> Por hacer | AB27: =IF(OR(ISBLANK(Backlog[[#This Row],[Fecha comprometida (para UAT)]]),Backlog[[#This Row],[Fecha comprometida (para UAT)]]=""), "Sin fecha comprometida", IF( Backlog[[#This Row],[Fecha Real de Cierre]]="", TODAY()-Backlog[[#This Row],[Fecha comprometida (para UAT)]], Backlog[[#This Row],[Fecha Real de Cierre]]-Backlog[[#This Row],[Fecha comprometida (para UAT)]] ) ) -> Sin fecha comprometida | AC27: =IF(OR(#REF!="",NOT(ISNUMBER(Backlog[[#This Row],[Dias_abiertos]]))),"",IF(Backlog[[#This Row],[Dias_abiertos]]<=7,"En plazo",IFERROR(IF(Backlog[[#This Row],[Dias_abiertos]]=_xlfn.XLOOKUP(TRIM(#REF!),CatSLA[Prioridad],CatSLA[SLA_dias],""),"En plazo","Fuera de plazo"),"Sin SLA"))) -> #REF!
A28: 16410 | B28: Mantenimiento evolutivo | C28: Alta | D28: 46136 | E28: Listado - movimientos por imputación/sorteo/código | F28: Listados/Listados Generales/Contaduría/ Liquidaciones Agentes/Resúmenes para Lotería/movimientos por imputación/sorteo/código | G28: Santiago del Estero | H28: Gamma | I28: Mantenimiento | J28: 16 | K28: A planificar | O28: Autorizado por la direccción | Q28: SDE - GAMMA - Listado - Movimientos por imputación-sorteo-codigo - 1.0.docx | S28: 24 | AA28: =_xlfn.XLOOKUP(Backlog[[#This Row],[Estado]],CatEstados[Estado],CatEstados[Fase],"Otro") -> Por hacer | AB28: =IF(OR(ISBLANK(Backlog[[#This Row],[Fecha comprometida (para UAT)]]),Backlog[[#This Row],[Fecha comprometida (para UAT)]]=""), "Sin fecha comprometida", IF( Backlog[[#This Row],[Fecha Real de Cierre]]="", TODAY()-Backlog[[#This Row],[Fecha comprometida (para UAT)]], Backlog[[#This Row],[Fecha Real de Cierre]]-Backlog[[#This Row],[Fecha comprometida (para UAT)]] ) ) -> Sin fecha comprometida | AC28: =IF(OR(#REF!="",NOT(ISNUMBER(Backlog[[#This Row],[Dias_abiertos]]))),"",IF(Backlog[[#This Row],[Dias_abiertos]]<=7,"En plazo",IFERROR(IF(Backlog[[#This Row],[Dias_abiertos]]=_xlfn.XLOOKUP(TRIM(#REF!),CatSLA[Prioridad],CatSLA[SLA_dias],""),"En plazo","Fuera de plazo"),"Sin SLA"))) -> #REF!
A29: 16668 | B29: Mantenimiento evolutivo | C29: Alta | D29: 46146 | E29: Listado - Crédito autorizados por sucursal | F29: Listados/Listados Generales/Contaduría/Bancos/Crédito autorizados por sucursal | G29: Santiago del Estero | H29: Gamma | I29: Mantenimiento | J29: 19 | K29: A planificar | O29: Autorizado por la direccción | Q29: SDE - GAMMA - Listados - Creditos Autorizados por Sucursal - 1.0.docx | S29: 24 | AA29: =_xlfn.XLOOKUP(Backlog[[#This Row],[Estado]],CatEstados[Estado],CatEstados[Fase],"Otro") -> Por hacer | AB29: =IF(OR(ISBLANK(Backlog[[#This Row],[Fecha comprometida (para UAT)]]),Backlog[[#This Row],[Fecha comprometida (para UAT)]]=""), "Sin fecha comprometida", IF( Backlog[[#This Row],[Fecha Real de Cierre]]="", TODAY()-Backlog[[#This Row],[Fecha comprometida (para UAT)]], Backlog[[#This Row],[Fecha Real de Cierre]]-Backlog[[#This Row],[Fecha comprometida (para UAT)]] ) ) -> Sin fecha comprometida | AC29: =IF(OR(#REF!="",NOT(ISNUMBER(Backlog[[#This Row],[Dias_abiertos]]))),"",IF(Backlog[[#This Row],[Dias_abiertos]]<=7,"En plazo",IFERROR(IF(Backlog[[#This Row],[Dias_abiertos]]=_xlfn.XLOOKUP(TRIM(#REF!),CatSLA[Prioridad],CatSLA[SLA_dias],""),"En plazo","Fuera de plazo"),"Sin SLA"))) -> #REF!
A30: 16670 | B30: Mantenimiento evolutivo | C30: Alta | D30: 46146 | E30: Listado - Débitos autorizados por sucursal | F30: Listados/Listados Generales/Contaduría/Bancos/Débitos autorizados por sucursal | G30: Santiago del Estero | H30: Gamma | I30: Mantenimiento | J30: 22 | K30: A planificar | O30: Autorizado por la direccción | Q30: SDE - GAMMA - Listados - Debitos Autorizados por Sucursal - 1.0.docx | S30: 24 | AA30: =_xlfn.XLOOKUP(Backlog[[#This Row],[Estado]],CatEstados[Estado],CatEstados[Fase],"Otro") -> Por hacer | AB30: =IF(OR(ISBLANK(Backlog[[#This Row],[Fecha comprometida (para UAT)]]),Backlog[[#This Row],[Fecha comprometida (para UAT)]]=""), "Sin fecha comprometida", IF( Backlog[[#This Row],[Fecha Real de Cierre]]="", TODAY()-Backlog[[#This Row],[Fecha comprometida (para UAT)]], Backlog[[#This Row],[Fecha Real de Cierre]]-Backlog[[#This Row],[Fecha comprometida (para UAT)]] ) ) -> Sin fecha comprometida | AC30: =IF(OR(#REF!="",NOT(ISNUMBER(Backlog[[#This Row],[Dias_abiertos]]))),"",IF(Backlog[[#This Row],[Dias_abiertos]]<=7,"En plazo",IFERROR(IF(Backlog[[#This Row],[Dias_abiertos]]=_xlfn.XLOOKUP(TRIM(#REF!),CatSLA[Prioridad],CatSLA[SLA_dias],""),"En plazo","Fuera de plazo"),"Sin SLA"))) -> #REF!
A31: 16671 | B31: Mantenimiento evolutivo | C31: Alta | D31: 46146 | E31: Listado - Liquidación | F31: Listados/Listados Generales/Contaduría/Bancos/Liquidación | G31: Santiago del Estero | H31: Gamma | I31: Mantenimiento | J31: 23 | K31: A planificar | O31: autorizado por la direccción | S31: 24 | AA31: =_xlfn.XLOOKUP(Backlog[[#This Row],[Estado]],CatEstados[Estado],CatEstados[Fase],"Otro") -> Por hacer | AB31: =IF(OR(ISBLANK(Backlog[[#This Row],[Fecha comprometida (para UAT)]]),Backlog[[#This Row],[Fecha comprometida (para UAT)]]=""), "Sin fecha comprometida", IF( Backlog[[#This Row],[Fecha Real de Cierre]]="", TODAY()-Backlog[[#This Row],[Fecha comprometida (para UAT)]], Backlog[[#This Row],[Fecha Real de Cierre]]-Backlog[[#This Row],[Fecha comprometida (para UAT)]] ) ) -> Sin fecha comprometida | AC31: =IF(OR(#REF!="",NOT(ISNUMBER(Backlog[[#This Row],[Dias_abiertos]]))),"",IF(Backlog[[#This Row],[Dias_abiertos]]<=7,"En plazo",IFERROR(IF(Backlog[[#This Row],[Dias_abiertos]]=_xlfn.XLOOKUP(TRIM(#REF!),CatSLA[Prioridad],CatSLA[SLA_dias],""),"En plazo","Fuera de plazo"),"Sin SLA"))) -> #REF!
A32: 16452 | B32: Mantenimiento evolutivo | C32: Alta | D32: 46136 | E32: Listado - certificado Retenciones IB | F32: Listados/Listados Generales/Contaduría/Impuestos/Rentas/certificado Retenciones IB (Se envia a las agencias a través del panel de agentes) | G32: Santiago del Estero | H32: Gamma | I32: Mantenimiento | J32: 26 | K32: A planificar | O32: autorizado por la direccción | Q32: SDE - GAMMA - Certificado Retenciones IIBB - 1.0.docx | S32: 24 | AA32: =_xlfn.XLOOKUP(Backlog[[#This Row],[Estado]],CatEstados[Estado],CatEstados[Fase],"Otro") -> Por hacer | AB32: =IF(OR(ISBLANK(Backlog[[#This Row],[Fecha comprometida (para UAT)]]),Backlog[[#This Row],[Fecha comprometida (para UAT)]]=""), "Sin fecha comprometida", IF( Backlog[[#This Row],[Fecha Real de Cierre]]="", TODAY()-Backlog[[#This Row],[Fecha comprometida (para UAT)]], Backlog[[#This Row],[Fecha Real de Cierre]]-Backlog[[#This Row],[Fecha comprometida (para UAT)]] ) ) -> Sin fecha comprometida | AC32: =IF(OR(#REF!="",NOT(ISNUMBER(Backlog[[#This Row],[Dias_abiertos]]))),"",IF(Backlog[[#This Row],[Dias_abiertos]]<=7,"En plazo",IFERROR(IF(Backlog[[#This Row],[Dias_abiertos]]=_xlfn.XLOOKUP(TRIM(#REF!),CatSLA[Prioridad],CatSLA[SLA_dias],""),"En plazo","Fuera de plazo"),"Sin SLA"))) -> #REF!
A33: 16672 | B33: Mantenimiento evolutivo | C33: Alta | D33: 46146 | E33: Listado - códigos | F33: Listados/Listados Generales/Contaduría/Liquidaciones Agentes/códigos | G33: Santiago del Estero | H33: Gamma | I33: Mantenimiento | J33: 30 | K33: A planificar | O33: autorizado por la direccción | Q33: SDE - GAMMA - Listado - Códigos - 1.0.docx | S33: 24 | AA33: =_xlfn.XLOOKUP(Backlog[[#This Row],[Estado]],CatEstados[Estado],CatEstados[Fase],"Otro") -> Por hacer | AB33: =IF(OR(ISBLANK(Backlog[[#This Row],[Fecha comprometida (para UAT)]]),Backlog[[#This Row],[Fecha comprometida (para UAT)]]=""), "Sin fecha comprometida", IF( Backlog[[#This Row],[Fecha Real de Cierre]]="", TODAY()-Backlog[[#This Row],[Fecha comprometida (para UAT)]], Backlog[[#This Row],[Fecha Real de Cierre]]-Backlog[[#This Row],[Fecha comprometida (para UAT)]] ) ) -> Sin fecha comprometida | AC33: =IF(OR(#REF!="",NOT(ISNUMBER(Backlog[[#This Row],[Dias_abiertos]]))),"",IF(Backlog[[#This Row],[Dias_abiertos]]<=7,"En plazo",IFERROR(IF(Backlog[[#This Row],[Dias_abiertos]]=_xlfn.XLOOKUP(TRIM(#REF!),CatSLA[Prioridad],CatSLA[SLA_dias],""),"En plazo","Fuera de plazo"),"Sin SLA"))) -> #REF!
A34: 16416 | B34: Mantenimiento evolutivo | C34: Alta | D34: 46136 | E34: Listado - resumen asiento con agentes | F34: Listados/Listados Generales/Contaduría/Liquidaciones Agentes/resumen asiento con agentes | G34: Santiago del Estero | H34: Gamma | I34: Mantenimiento | J34: 31 | K34: A planificar | O34: autorizado por la direccción | Q34: SDE - GAMMA - Listado Resumen Asiento con PDV - 1.0.docx | S34: 24 | AA34: =_xlfn.XLOOKUP(Backlog[[#This Row],[Estado]],CatEstados[Estado],CatEstados[Fase],"Otro") -> Por hacer | AB34: =IF(OR(ISBLANK(Backlog[[#This Row],[Fecha comprometida (para UAT)]]),Backlog[[#This Row],[Fecha comprometida (para UAT)]]=""), "Sin fecha comprometida", IF( Backlog[[#This Row],[Fecha Real de Cierre]]="", TODAY()-Backlog[[#This Row],[Fecha comprometida (para UAT)]], Backlog[[#This Row],[Fecha Real de Cierre]]-Backlog[[#This Row],[Fecha comprometida (para UAT)]] ) ) -> Sin fecha comprometida | AC34: =IF(OR(#REF!="",NOT(ISNUMBER(Backlog[[#This Row],[Dias_abiertos]]))),"",IF(Backlog[[#This Row],[Dias_abiertos]]<=7,"En plazo",IFERROR(IF(Backlog[[#This Row],[Dias_abiertos]]=_xlfn.XLOOKUP(TRIM(#REF!),CatSLA[Prioridad],CatSLA[SLA_dias],""),"En plazo","Fuera de plazo"),"Sin SLA"))) -> #REF!
A35: 16417 | B35: Mantenimiento evolutivo | C35: Alta | D35: 46136 | E35: Listado - resumen asientos con saldos | F35: Listados/Listados Generales/Contaduría/Liquidaciones Agentes/resumen asientos con saldos (dif oficina) | G35: Santiago del Estero | H35: Gamma | I35: Mantenimiento | J35: 32 | K35: A planificar | O35: autorizado por la direccción | Q35: SDE - GAMMA - Listado Resumen Asiento con Saldo - 1.0.docx | S35: 24 | AA35: =_xlfn.XLOOKUP(Backlog[[#This Row],[Estado]],CatEstados[Estado],CatEstados[Fase],"Otro") -> Por hacer | AB35: =IF(OR(ISBLANK(Backlog[[#This Row],[Fecha comprometida (para UAT)]]),Backlog[[#This Row],[Fecha comprometida (para UAT)]]=""), "Sin fecha comprometida", IF( Backlog[[#This Row],[Fecha Real de Cierre]]="", TODAY()-Backlog[[#This Row],[Fecha comprometida (para UAT)]], Backlog[[#This Row],[Fecha Real de Cierre]]-Backlog[[#This Row],[Fecha comprometida (para UAT)]] ) ) -> Sin fecha comprometida | AC35: =IF(OR(#REF!="",NOT(ISNUMBER(Backlog[[#This Row],[Dias_abiertos]]))),"",IF(Backlog[[#This Row],[Dias_abiertos]]<=7,"En plazo",IFERROR(IF(Backlog[[#This Row],[Dias_abiertos]]=_xlfn.XLOOKUP(TRIM(#REF!),CatSLA[Prioridad],CatSLA[SLA_dias],""),"En plazo","Fuera de plazo"),"Sin SLA"))) -> #REF!
A36: 16673 | B36: Mantenimiento evolutivo | C36: Alta | D36: 46146 | E36: Listado - estado de cuenta corriente | F36: Listados/Listados Generales/Contaduría/Liquidaciones Agentes/Resúmenes para Lotería/estado de cuenta corriente | G36: Santiago del Estero | H36: Gamma | I36: Mantenimiento | J36: 35 | K36: A planificar | O36: autorizado por la direccción | Q36: SDE - GAMMA - Listado - Estado de Cuenta Corriente - ver 1.0.docx | S36: 24 | AA36: =_xlfn.XLOOKUP(Backlog[[#This Row],[Estado]],CatEstados[Estado],CatEstados[Fase],"Otro") -> Por hacer | AB36: =IF(OR(ISBLANK(Backlog[[#This Row],[Fecha comprometida (para UAT)]]),Backlog[[#This Row],[Fecha comprometida (para UAT)]]=""), "Sin fecha comprometida", IF( Backlog[[#This Row],[Fecha Real de Cierre]]="", TODAY()-Backlog[[#This Row],[Fecha comprometida (para UAT)]], Backlog[[#This Row],[Fecha Real de Cierre]]-Backlog[[#This Row],[Fecha comprometida (para UAT)]] ) ) -> Sin fecha comprometida | AC36: =IF(OR(#REF!="",NOT(ISNUMBER(Backlog[[#This Row],[Dias_abiertos]]))),"",IF(Backlog[[#This Row],[Dias_abiertos]]<=7,"En plazo",IFERROR(IF(Backlog[[#This Row],[Dias_abiertos]]=_xlfn.XLOOKUP(TRIM(#REF!),CatSLA[Prioridad],CatSLA[SLA_dias],""),"En plazo","Fuera de plazo"),"Sin SLA"))) -> #REF!
A37: 16448 | B37: Mantenimiento evolutivo | C37: Alta | D37: 46136 | E37: Listado - Descuentos y bonificaciones | F37: Listados/Listados Generales/Agentes/Liquidación/Descuentos y bonificaciones | G37: Santiago del Estero | H37: Gamma | I37: Mantenimiento | J37: 39 | K37: A planificar | O37: autorizado por la direccción | Q37: SDE - GAMMA - Listado - Descuentos y bonificaciones - ver 1.0.docx | S37: 24 | AA37: =_xlfn.XLOOKUP(Backlog[[#This Row],[Estado]],CatEstados[Estado],CatEstados[Fase],"Otro") -> Por hacer | AB37: =IF(OR(ISBLANK(Backlog[[#This Row],[Fecha comprometida (para UAT)]]),Backlog[[#This Row],[Fecha comprometida (para UAT)]]=""), "Sin fecha comprometida", IF( Backlog[[#This Row],[Fecha Real de Cierre]]="", TODAY()-Backlog[[#This Row],[Fecha comprometida (para UAT)]], Backlog[[#This Row],[Fecha Real de Cierre]]-Backlog[[#This Row],[Fecha comprometida (para UAT)]] ) ) -> Sin fecha comprometida | AC37: =IF(OR(#REF!="",NOT(ISNUMBER(Backlog[[#This Row],[Dias_abiertos]]))),"",IF(Backlog[[#This Row],[Dias_abiertos]]<=7,"En plazo",IFERROR(IF(Backlog[[#This Row],[Dias_abiertos]]=_xlfn.XLOOKUP(TRIM(#REF!),CatSLA[Prioridad],CatSLA[SLA_dias],""),"En plazo","Fuera de plazo"),"Sin SLA"))) -> #REF!
A38: 16674 | B38: Mantenimiento evolutivo | C38: Alta | D38: 46146 | E38: Excel de preliquidacion con nueva información | F38: Desde la loteria solicitan que los excel que se descargan durante la liquidacion en GAMMA, figure detallado el N° de sorteo y la fecha del mismo. | G38: Santiago del Estero | H38: Gamma | I38: Mantenimiento | J38: 47 | K38: A planificar | O38: autorizado por la direccción | S38: 24 | AA38: =_xlfn.XLOOKUP(Backlog[[#This Row],[Estado]],CatEstados[Estado],CatEstados[Fase],"Otro") -> Por hacer | AB38: =IF(OR(ISBLANK(Backlog[[#This Row],[Fecha comprometida (para UAT)]]),Backlog[[#This Row],[Fecha comprometida (para UAT)]]=""), "Sin fecha comprometida", IF( Backlog[[#This Row],[Fecha Real de Cierre]]="", TODAY()-Backlog[[#This Row],[Fecha comprometida (para UAT)]], Backlog[[#This Row],[Fecha Real de Cierre]]-Backlog[[#This Row],[Fecha comprometida (para UAT)]] ) ) -> Sin fecha comprometida | AC38: =IF(OR(#REF!="",NOT(ISNUMBER(Backlog[[#This Row],[Dias_abiertos]]))),"",IF(Backlog[[#This Row],[Dias_abiertos]]<=7,"En plazo",IFERROR(IF(Backlog[[#This Row],[Dias_abiertos]]=_xlfn.XLOOKUP(TRIM(#REF!),CatSLA[Prioridad],CatSLA[SLA_dias],""),"En plazo","Fuera de plazo"),"Sin SLA"))) -> #REF!
A39: 16675 | B39: Mantenimiento evolutivo | C39: Alta | D39: 46146 | E39: ID716 - Tesoreria - Fecha valor en cobros manuales | G39: Corrientes | H39: Gamma | I39: SAC | J39: 100 | K39: A priorizar | O39: autorizado por la direccción | Q39: ID716 - COR - Gamma - Tesoreria - Fecha valor en cobros manuales - 1.0.docx | S39: 80 | AA39: =_xlfn.XLOOKUP(Backlog[[#This Row],[Estado]],CatEstados[Estado],CatEstados[Fase],"Otro") -> Por hacer | AB39: =IF(OR(ISBLANK(Backlog[[#This Row],[Fecha comprometida (para UAT)]]),Backlog[[#This Row],[Fecha comprometida (para UAT)]]=""), "Sin fecha comprometida", IF( Backlog[[#This Row],[Fecha Real de Cierre]]="", TODAY()-Backlog[[#This Row],[Fecha comprometida (para UAT)]], Backlog[[#This Row],[Fecha Real de Cierre]]-Backlog[[#This Row],[Fecha comprometida (para UAT)]] ) ) -> Sin fecha comprometida | AC39: =IF(OR(#REF!="",NOT(ISNUMBER(Backlog[[#This Row],[Dias_abiertos]]))),"",IF(Backlog[[#This Row],[Dias_abiertos]]<=7,"En plazo",IFERROR(IF(Backlog[[#This Row],[Dias_abiertos]]=_xlfn.XLOOKUP(TRIM(#REF!),CatSLA[Prioridad],CatSLA[SLA_dias],""),"En plazo","Fuera de plazo"),"Sin SLA"))) -> #REF!
A40: 16676 | B40: Mantenimiento evolutivo | C40: Alta | D40: 46146 | E40: ID718 - Resumenes de preliquidacion en PDF | G40: Corrientes | H40: Gamma | I40: SAC | J40: 101 | K40: A priorizar | O40: autorizado por la direccción | Q40: ID718 - COR - Gamma - Resumenes de preliquidacion en PDF - 1.0.docx | S40: 80 | AA40: =_xlfn.XLOOKUP(Backlog[[#This Row],[Estado]],CatEstados[Estado],CatEstados[Fase],"Otro") -> Por hacer | AB40: =IF(OR(ISBLANK(Backlog[[#This Row],[Fecha comprometida (para UAT)]]),Backlog[[#This Row],[Fecha comprometida (para UAT)]]=""), "Sin fecha comprometida", IF( Backlog[[#This Row],[Fecha Real de Cierre]]="", TODAY()-Backlog[[#This Row],[Fecha comprometida (para UAT)]], Backlog[[#This Row],[Fecha Real de Cierre]]-Backlog[[#This Row],[Fecha comprometida (para UAT)]] ) ) -> Sin fecha comprometida | AC40: =IF(OR(#REF!="",NOT(ISNUMBER(Backlog[[#This Row],[Dias_abiertos]]))),"",IF(Backlog[[#This Row],[Dias_abiertos]]<=7,"En plazo",IFERROR(IF(Backlog[[#This Row],[Dias_abiertos]]=_xlfn.XLOOKUP(TRIM(#REF!),CatSLA[Prioridad],CatSLA[SLA_dias],""),"En plazo","Fuera de plazo"),"Sin SLA"))) -> #REF!
A41: 16677 | B41: Mantenimiento evolutivo | C41: Alta | D41: 46146 | E41: ID719 - Movimientos manuales con PDV | G41: Corrientes | H41: Gamma | I41: SAC | J41: 102 | K41: A priorizar | O41: autorizado por la direccción | Q41: ID719 - COR - Gamma - Movimientos Manuales con PDV - 1.0.docx | S41: 80 | AA41: =_xlfn.XLOOKUP(Backlog[[#This Row],[Estado]],CatEstados[Estado],CatEstados[Fase],"Otro") -> Por hacer | AB41: =IF(OR(ISBLANK(Backlog[[#This Row],[Fecha comprometida (para UAT)]]),Backlog[[#This Row],[Fecha comprometida (para UAT)]]=""), "Sin fecha comprometida", IF( Backlog[[#This Row],[Fecha Real de Cierre]]="", TODAY()-Backlog[[#This Row],[Fecha comprometida (para UAT)]], Backlog[[#This Row],[Fecha Real de Cierre]]-Backlog[[#This Row],[Fecha comprometida (para UAT)]] ) ) -> Sin fecha comprometida | AC41: =IF(OR(#REF!="",NOT(ISNUMBER(Backlog[[#This Row],[Dias_abiertos]]))),"",IF(Backlog[[#This Row],[Dias_abiertos]]<=7,"En plazo",IFERROR(IF(Backlog[[#This Row],[Dias_abiertos]]=_xlfn.XLOOKUP(TRIM(#REF!),CatSLA[Prioridad],CatSLA[SLA_dias],""),"En plazo","Fuera de plazo"),"Sin SLA"))) -> #REF!
A42: 16678 | B42: Mantenimiento evolutivo | C42: Alta | D42: 46146 | E42: ID721 - Resumen pagado/cobrado fuera de término | G42: Corrientes | H42: Gamma | I42: SAC | J42: 103 | K42: A priorizar | O42: autorizado por la direccción | Q42: ID721 - COR - Gamma - Resumen pagado-cobrado fuera de término - 1.0.docx | S42: 40 | AA42: =_xlfn.XLOOKUP(Backlog[[#This Row],[Estado]],CatEstados[Estado],CatEstados[Fase],"Otro") -> Por hacer | AB42: =IF(OR(ISBLANK(Backlog[[#This Row],[Fecha comprometida (para UAT)]]),Backlog[[#This Row],[Fecha comprometida (para UAT)]]=""), "Sin fecha comprometida", IF( Backlog[[#This Row],[Fecha Real de Cierre]]="", TODAY()-Backlog[[#This Row],[Fecha comprometida (para UAT)]], Backlog[[#This Row],[Fecha Real de Cierre]]-Backlog[[#This Row],[Fecha comprometida (para UAT)]] ) ) -> Sin fecha comprometida | AC42: =IF(OR(#REF!="",NOT(ISNUMBER(Backlog[[#This Row],[Dias_abiertos]]))),"",IF(Backlog[[#This Row],[Dias_abiertos]]<=7,"En plazo",IFERROR(IF(Backlog[[#This Row],[Dias_abiertos]]=_xlfn.XLOOKUP(TRIM(#REF!),CatSLA[Prioridad],CatSLA[SLA_dias],""),"En plazo","Fuera de plazo"),"Sin SLA"))) -> #REF!
A43: 16679 | B43: Mantenimiento evolutivo | C43: Alta | D43: 46146 | E43: ID765 - Excepción de sorteos: se borra config al ejecutar EP de sorteos | F43: Probado FF el 26/09 en UAT no funciona la solucion o el workarround. | G43: Corrientes | H43: Gamma | I43: SAC | J43: 104 | K43: A priorizar | O43: autorizado por la direccción | Q43: ID765 – COR - Gamma - Excepción de sorteos - 1.0.docx | S43: 40 | AA43: =_xlfn.XLOOKUP(Backlog[[#This Row],[Estado]],CatEstados[Estado],CatEstados[Fase],"Otro") -> Por hacer | AB43: =IF(OR(ISBLANK(Backlog[[#This Row],[Fecha comprometida (para UAT)]]),Backlog[[#This Row],[Fecha comprometida (para UAT)]]=""), "Sin fecha comprometida", IF( Backlog[[#This Row],[Fecha Real de Cierre]]="", TODAY()-Backlog[[#This Row],[Fecha comprometida (para UAT)]], Backlog[[#This Row],[Fecha Real de Cierre]]-Backlog[[#This Row],[Fecha comprometida (para UAT)]] ) ) -> Sin fecha comprometida | AC43: =IF(OR(#REF!="",NOT(ISNUMBER(Backlog[[#This Row],[Dias_abiertos]]))),"",IF(Backlog[[#This Row],[Dias_abiertos]]<=7,"En plazo",IFERROR(IF(Backlog[[#This Row],[Dias_abiertos]]=_xlfn.XLOOKUP(TRIM(#REF!),CatSLA[Prioridad],CatSLA[SLA_dias],""),"En plazo","Fuera de plazo"),"Sin SLA"))) -> #REF!
A44: MAN-674 SF16019 | B44: Mantenimiento evolutivo | D44: 46126 | E44: Aumento del tiempo de caducidad de contraseñas | F44: Solicitan si es factible modificar el período de 45 días para el cambio de contraseña en el Lotemóvil a raíz de las reiteradas quejas de las agencias, las cuales consideran ése período muy corto y les genera inconvenientes. | G44: Todas las provincias | H44: Panel Agentes-Abaco | I44: SAC | K44: A priorizar | P44: Que lo resuelva SAC, porque requeriria muhas horas de trabajo | S44: 80
A45: MAN-679 SF16067 | B45: Mantenimiento correctivo | D45: 46126 | E45: Error en calendario al configuridad un dia sin actividad | F45: Error al configurar un dia feriado o sin actividad. Ya paso antes estaba solucionado y ahora volvio a surgir. Al liquidar en el paralelo de SIGA /GAMMA en TDF en el 1 de abril hasta el 4 de abril. Se vió trabada la operatoria por no poder avanzar ya que al momento de intentar liquidar el dia 1° saltaBa al dia 4 sin liquidar el 1 de abril 2026 | G45: Tierra del Fuego | H45: Gamma | I45: SAC | K45: A priorizar | S45: 24
A46: MAN-697 15940 | B46: Mantenimiento correctivo | C46: Muy alta | D46: 46132 | E46: Gamma- Costo papel | F46: En GAMMA no esta saliendo los movimientos n° 6 de Consumo Papel en todos los juegos de la provincia. Si ya esta abierto en otra provincia lo desconozco y desestimar el caso de ser asi | G46: Tierra del Fuego | H46: Gamma | K46: Planificado | O46: Duplicado de 15068? Eso dicen | P46: Ya se lo pidieron y lo va a encarar | S46: 24
A47: MAN-698 16245 | B47: Mantenimiento correctivo | D47: 46132 | E47: Gamma - Error en Preliquidacion | F47: Lotería informó un error al intentar iniciar la preliquidación del día domingo 19-04-2026, se visualiza en pantalla "No value present - NoSuchElementException". | G47: Jujuy | H47: Gamma | I47: SAC | K47: A priorizar | S47: 16
A48: 00009750 Gamma - 000048 | B48: Mantenimiento evolutivo | C48: Alta | D48: 15/10/2025 | E48: COR-Abaco-Control de Caja en Lotemovil | F48: El registro de cupones en Lotemóvil (por PDV, juego, concepto: Validado/Pagado y monto totalizado), se visualiza correctamente y como tal, pero no detalla información específica de cada jugada. El agente solicita el mismo a fin de controlar la correcta validación de cupones, por ejemplo cuando la TJ no genera el ticket. | G48: Corrientes | H48: Abaco | I48: SAC | K48: A priorizar | S48: 8 | AA48: =_xlfn.XLOOKUP(Backlog[[#This Row],[Estado]],CatEstados[Estado],CatEstados[Fase],"Otro") -> Por hacer | AB48: =IF(OR(ISBLANK(Backlog[[#This Row],[Fecha comprometida (para UAT)]]),Backlog[[#This Row],[Fecha comprometida (para UAT)]]=""), "Sin fecha comprometida", IF( Backlog[[#This Row],[Fecha Real de Cierre]]="", TODAY()-Backlog[[#This Row],[Fecha comprometida (para UAT)]], Backlog[[#This Row],[Fecha Real de Cierre]]-Backlog[[#This Row],[Fecha comprometida (para UAT)]] ) ) -> Sin fecha comprometida | AC48: =IF(OR(#REF!="",NOT(ISNUMBER(Backlog[[#This Row],[Dias_abiertos]]))),"",IF(Backlog[[#This Row],[Dias_abiertos]]<=7,"En plazo",IFERROR(IF(Backlog[[#This Row],[Dias_abiertos]]=_xlfn.XLOOKUP(TRIM(#REF!),CatSLA[Prioridad],CatSLA[SLA_dias],""),"En plazo","Fuera de plazo"),"Sin SLA"))) -> #REF!
A49: 00008124 | B49: Mantenimiento correctivo | D49: 45915 | E49: Gamma-T.L.P.-Agregar nuevas localidades | F49: Impacta en creacion nuevos PDV. Bloqueante para asignacion a pdv | G49: Todas las provincias | H49: Gamma | I49: SAC | K49: A priorizar | O49: Horacio preguntará al cliente | S49: 60 | AA49: =_xlfn.XLOOKUP(Backlog[[#This Row],[Estado]],CatEstados[Estado],CatEstados[Fase],"Otro") -> Por hacer | AB49: =IF(OR(ISBLANK(Backlog[[#This Row],[Fecha comprometida (para UAT)]]),Backlog[[#This Row],[Fecha comprometida (para UAT)]]=""), "Sin fecha comprometida", IF( Backlog[[#This Row],[Fecha Real de Cierre]]="", TODAY()-Backlog[[#This Row],[Fecha comprometida (para UAT)]], Backlog[[#This Row],[Fecha Real de Cierre]]-Backlog[[#This Row],[Fecha comprometida (para UAT)]] ) ) -> Sin fecha comprometida | AC49: =IF(OR(#REF!="",NOT(ISNUMBER(Backlog[[#This Row],[Dias_abiertos]]))),"",IF(Backlog[[#This Row],[Dias_abiertos]]<=7,"En plazo",IFERROR(IF(Backlog[[#This Row],[Dias_abiertos]]=_xlfn.XLOOKUP(TRIM(#REF!),CatSLA[Prioridad],CatSLA[SLA_dias],""),"En plazo","Fuera de plazo"),"Sin SLA"))) -> #REF!
A50: 00008127 | B50: Mantenimiento evolutivo | D50: 15/9/2025 | E50: Gamma-T.L.P.-Generación de archivos para descuentos y bonificaciones: | F50: Codigos contables y montos, MD5 etc. Convertimos el formato xls a txt | G50: Todas las provincias | H50: Gamma | I50: SAC | K50: A priorizar | O50: Averiguar como se puede ya que cada Lotería es diferente. | S50: 120 | AA50: =_xlfn.XLOOKUP(Backlog[[#This Row],[Estado]],CatEstados[Estado],CatEstados[Fase],"Otro") -> Por hacer | AB50: =IF(OR(ISBLANK(Backlog[[#This Row],[Fecha comprometida (para UAT)]]),Backlog[[#This Row],[Fecha comprometida (para UAT)]]=""), "Sin fecha comprometida", IF( Backlog[[#This Row],[Fecha Real de Cierre]]="", TODAY()-Backlog[[#This Row],[Fecha comprometida (para UAT)]], Backlog[[#This Row],[Fecha Real de Cierre]]-Backlog[[#This Row],[Fecha comprometida (para UAT)]] ) ) -> Sin fecha comprometida | AC50: =IF(OR(#REF!="",NOT(ISNUMBER(Backlog[[#This Row],[Dias_abiertos]]))),"",IF(Backlog[[#This Row],[Dias_abiertos]]<=7,"En plazo",IFERROR(IF(Backlog[[#This Row],[Dias_abiertos]]=_xlfn.XLOOKUP(TRIM(#REF!),CatSLA[Prioridad],CatSLA[SLA_dias],""),"En plazo","Fuera de plazo"),"Sin SLA"))) -> #REF!
A51: 00008140 | B51: Mantenimiento evolutivo | D51: 15/9/2025 | E51: Gamma-T.L.P.- Solicitud de reporte de reglas configuradas | G51: Todas las provincias | H51: Gamma | I51: SAC | K51: A priorizar | S51: 120 | AA51: =_xlfn.XLOOKUP(Backlog[[#This Row],[Estado]],CatEstados[Estado],CatEstados[Fase],"Otro") -> Por hacer | AB51: =IF(OR(ISBLANK(Backlog[[#This Row],[Fecha comprometida (para UAT)]]),Backlog[[#This Row],[Fecha comprometida (para UAT)]]=""), "Sin fecha comprometida", IF( Backlog[[#This Row],[Fecha Real de Cierre]]="", TODAY()-Backlog[[#This Row],[Fecha comprometida (para UAT)]], Backlog[[#This Row],[Fecha Real de Cierre]]-Backlog[[#This Row],[Fecha comprometida (para UAT)]] ) ) -> Sin fecha comprometida | AC51: =IF(OR(#REF!="",NOT(ISNUMBER(Backlog[[#This Row],[Dias_abiertos]]))),"",IF(Backlog[[#This Row],[Dias_abiertos]]<=7,"En plazo",IFERROR(IF(Backlog[[#This Row],[Dias_abiertos]]=_xlfn.XLOOKUP(TRIM(#REF!),CatSLA[Prioridad],CatSLA[SLA_dias],""),"En plazo","Fuera de plazo"),"Sin SLA"))) -> #REF!
A52: 00008121 | B52: Mantenimiento correctivo | D52: 15/9/2025 | E52: Gamma-T.L.P.-ETL-No ingresan movimientos para la liquidacion | F52: datos de sistemas perifericos (medios digitales, lotline etc) , a veces bloqueante a veces permite realizar el proceso pero con faltante de informacion | G52: Todas las provincias | H52: Gamma | I52: SAC | K52: A priorizar | R52: FE para homologar casos por el operador sin intervención de tecno | S52: 180 | AA52: =_xlfn.XLOOKUP(Backlog[[#This Row],[Estado]],CatEstados[Estado],CatEstados[Fase],"Otro") -> Por hacer | AB52: =IF(OR(ISBLANK(Backlog[[#This Row],[Fecha comprometida (para UAT)]]),Backlog[[#This Row],[Fecha comprometida (para UAT)]]=""), "Sin fecha comprometida", IF( Backlog[[#This Row],[Fecha Real de Cierre]]="", TODAY()-Backlog[[#This Row],[Fecha comprometida (para UAT)]], Backlog[[#This Row],[Fecha Real de Cierre]]-Backlog[[#This Row],[Fecha comprometida (para UAT)]] ) ) -> Sin fecha comprometida | AC52: =IF(OR(#REF!="",NOT(ISNUMBER(Backlog[[#This Row],[Dias_abiertos]]))),"",IF(Backlog[[#This Row],[Dias_abiertos]]<=7,"En plazo",IFERROR(IF(Backlog[[#This Row],[Dias_abiertos]]=_xlfn.XLOOKUP(TRIM(#REF!),CatSLA[Prioridad],CatSLA[SLA_dias],""),"En plazo","Fuera de plazo"),"Sin SLA"))) -> #REF!
A53: 00008128 | B53: Mantenimiento evolutivo | D53: 15/9/2025 | E53: Gamma-T.L.P- Devoluciones CSA e IVA CSA. (Mensualmente). entre otros | F53: Codigos contables y montos, MD5 etc, aca son 2 archivos. Convertimos el formato xls a txt. | G53: Todas las provincias | H53: Gamma | I53: SAC | K53: QA | R53: hecho | S53: 0 | AA53: =_xlfn.XLOOKUP(Backlog[[#This Row],[Estado]],CatEstados[Estado],CatEstados[Fase],"Otro") -> Otro | AB53: =IF(OR(ISBLANK(Backlog[[#This Row],[Fecha comprometida (para UAT)]]),Backlog[[#This Row],[Fecha comprometida (para UAT)]]=""), "Sin fecha comprometida", IF( Backlog[[#This Row],[Fecha Real de Cierre]]="", TODAY()-Backlog[[#This Row],[Fecha comprometida (para UAT)]], Backlog[[#This Row],[Fecha Real de Cierre]]-Backlog[[#This Row],[Fecha comprometida (para UAT)]] ) ) -> Sin fecha comprometida | AC53: =IF(OR(#REF!="",NOT(ISNUMBER(Backlog[[#This Row],[Dias_abiertos]]))),"",IF(Backlog[[#This Row],[Dias_abiertos]]<=7,"En plazo",IFERROR(IF(Backlog[[#This Row],[Dias_abiertos]]=_xlfn.XLOOKUP(TRIM(#REF!),CatSLA[Prioridad],CatSLA[SLA_dias],""),"En plazo","Fuera de plazo"),"Sin SLA"))) -> #REF!
A54: 00008133 | B54: Mantenimiento correctivo | D54: 15/9/2025 | E54: Gamma-T.L.P.-Nuevo concepto no se actualiza en BD ETL, tabla accounting_codes | F54: Ante la aparición de un nuevo concepto proveniente de algún endpoint, es necesario modificar datos en la BD ETL, tabla accounting_codes Previamente, la Lotería debe crear el código contable correspondiente. No imputan movimientos en la cuenta corriente generando diferencias | G54: Todas las provincias | H54: Gamma | I54: SAC | K54: A priorizar | O54: HB: 12/02 Similar a 00008136 | R54: mismo req que el man8121 | S54: 60 | AA54: =_xlfn.XLOOKUP(Backlog[[#This Row],[Estado]],CatEstados[Estado],CatEstados[Fase],"Otro") -> Por hacer | AB54: =IF(OR(ISBLANK(Backlog[[#This Row],[Fecha comprometida (para UAT)]]),Backlog[[#This Row],[Fecha comprometida (para UAT)]]=""), "Sin fecha comprometida", IF( Backlog[[#This Row],[Fecha Real de Cierre]]="", TODAY()-Backlog[[#This Row],[Fecha comprometida (para UAT)]], Backlog[[#This Row],[Fecha Real de Cierre]]-Backlog[[#This Row],[Fecha comprometida (para UAT)]] ) ) -> Sin fecha comprometida | AC54: =IF(OR(#REF!="",NOT(ISNUMBER(Backlog[[#This Row],[Dias_abiertos]]))),"",IF(Backlog[[#This Row],[Dias_abiertos]]<=7,"En plazo",IFERROR(IF(Backlog[[#This Row],[Dias_abiertos]]=_xlfn.XLOOKUP(TRIM(#REF!),CatSLA[Prioridad],CatSLA[SLA_dias],""),"En plazo","Fuera de plazo"),"Sin SLA"))) -> #REF!
A55: 00008138 | B55: Mantenimiento evolutivo | D55: 15/9/2025 | E55: Gamma-T.L.P- Actualizacion de PDV | F55: No permite modificar datos como por ej localidad | G55: Todas las provincias | H55: Gamma | I55: SAC | K55: Validar estado | O55: Esto está en producción. Debe validar SAC. | AA55: =_xlfn.XLOOKUP(Backlog[[#This Row],[Estado]],CatEstados[Estado],CatEstados[Fase],"Otro") -> Implementación | AB55: =IF(OR(ISBLANK(Backlog[[#This Row],[Fecha comprometida (para UAT)]]),Backlog[[#This Row],[Fecha comprometida (para UAT)]]=""), "Sin fecha comprometida", IF( Backlog[[#This Row],[Fecha Real de Cierre]]="", TODAY()-Backlog[[#This Row],[Fecha comprometida (para UAT)]], Backlog[[#This Row],[Fecha Real de Cierre]]-Backlog[[#This Row],[Fecha comprometida (para UAT)]] ) ) -> Sin fecha comprometida | AC55: =IF(OR(#REF!="",NOT(ISNUMBER(Backlog[[#This Row],[Dias_abiertos]]))),"",IF(Backlog[[#This Row],[Dias_abiertos]]<=7,"En plazo",IFERROR(IF(Backlog[[#This Row],[Dias_abiertos]]=_xlfn.XLOOKUP(TRIM(#REF!),CatSLA[Prioridad],CatSLA[SLA_dias],""),"En plazo","Fuera de plazo"),"Sin SLA"))) -> #REF!
B56: Mantenimiento preventivo | D56: 45849 | E56: Plan controlado de despliegues integrales - integrar devops | F56: Acordar con DevOps como se organizan despliegues. | G56: Todas las provincias | H56: Gamma | I56: SAC | K56: A priorizar | O56: Leo armó un docuemento que debe consensuarse con Infra | S56: 8 | AA56: =_xlfn.XLOOKUP(Backlog[[#This Row],[Estado]],CatEstados[Estado],CatEstados[Fase],"Otro") -> Por hacer | AB56: =IF(OR(ISBLANK(Backlog[[#This Row],[Fecha comprometida (para UAT)]]),Backlog[[#This Row],[Fecha comprometida (para UAT)]]=""), "Sin fecha comprometida", IF( Backlog[[#This Row],[Fecha Real de Cierre]]="", TODAY()-Backlog[[#This Row],[Fecha comprometida (para UAT)]], Backlog[[#This Row],[Fecha Real de Cierre]]-Backlog[[#This Row],[Fecha comprometida (para UAT)]] ) ) -> Sin fecha comprometida | AC56: =IF(OR(#REF!="",NOT(ISNUMBER(Backlog[[#This Row],[Dias_abiertos]]))),"",IF(Backlog[[#This Row],[Dias_abiertos]]<=7,"En plazo",IFERROR(IF(Backlog[[#This Row],[Dias_abiertos]]=_xlfn.XLOOKUP(TRIM(#REF!),CatSLA[Prioridad],CatSLA[SLA_dias],""),"En plazo","Fuera de plazo"),"Sin SLA"))) -> #REF! | AJ56: Validar si está solucionado
A57: 690 | B57: Mantenimiento preventivo | D57: 45853 | E57: Revisión completa del uso de Kafka | F57: En UAT anda mal (resto ambientes ok) con problemas en UAT y potencial para PRD.Analisis en Desarrollo. Luego ver con DevOps | G57: Todas las provincias | H57: Gamma | I57: SAC | K57: A priorizar | P57: Es de Infra el tema. Desarrollo que se entere por Infra y listo. | S57: 0 | AA57: =_xlfn.XLOOKUP(Backlog[[#This Row],[Estado]],CatEstados[Estado],CatEstados[Fase],"Otro") -> Por hacer | AB57: =IF(OR(ISBLANK(Backlog[[#This Row],[Fecha comprometida (para UAT)]]),Backlog[[#This Row],[Fecha comprometida (para UAT)]]=""), "Sin fecha comprometida", IF( Backlog[[#This Row],[Fecha Real de Cierre]]="", TODAY()-Backlog[[#This Row],[Fecha comprometida (para UAT)]], Backlog[[#This Row],[Fecha Real de Cierre]]-Backlog[[#This Row],[Fecha comprometida (para UAT)]] ) ) -> Sin fecha comprometida | AC57: =IF(OR(#REF!="",NOT(ISNUMBER(Backlog[[#This Row],[Dias_abiertos]]))),"",IF(Backlog[[#This Row],[Dias_abiertos]]<=7,"En plazo",IFERROR(IF(Backlog[[#This Row],[Dias_abiertos]]=_xlfn.XLOOKUP(TRIM(#REF!),CatSLA[Prioridad],CatSLA[SLA_dias],""),"En plazo","Fuera de plazo"),"Sin SLA"))) -> #REF!
A58: 708 | B58: Mantenimiento preventivo | D58: 45861 | E58: Revisión de políticas de respaldo en general para info sensible o auditable x entes | F58: Backup de archivos de presentaciones en general, y estructura de almacenamiento. Hablar con Luis. | G58: Todas las provincias | H58: Gamma | I58: SAC | K58: A priorizar | S58: 0 | AA58: =_xlfn.XLOOKUP(Backlog[[#This Row],[Estado]],CatEstados[Estado],CatEstados[Fase],"Otro") -> Por hacer | AB58: =IF(OR(ISBLANK(Backlog[[#This Row],[Fecha comprometida (para UAT)]]),Backlog[[#This Row],[Fecha comprometida (para UAT)]]=""), "Sin fecha comprometida", IF( Backlog[[#This Row],[Fecha Real de Cierre]]="", TODAY()-Backlog[[#This Row],[Fecha comprometida (para UAT)]], Backlog[[#This Row],[Fecha Real de Cierre]]-Backlog[[#This Row],[Fecha comprometida (para UAT)]] ) ) -> Sin fecha comprometida | AC58: =IF(OR(#REF!="",NOT(ISNUMBER(Backlog[[#This Row],[Dias_abiertos]]))),"",IF(Backlog[[#This Row],[Dias_abiertos]]<=7,"En plazo",IFERROR(IF(Backlog[[#This Row],[Dias_abiertos]]=_xlfn.XLOOKUP(TRIM(#REF!),CatSLA[Prioridad],CatSLA[SLA_dias],""),"En plazo","Fuera de plazo"),"Sin SLA"))) -> #REF!
A59: 871 | B59: Mantenimiento preventivo | D59: 45939 | E59: Versión de Keycloak deprecada | F59: Ver con Infra | G59: Todas las provincias | H59: Gamma | I59: SAC | K59: A priorizar | P59: Es de Infra el tema. Que expliquen a desarrollo que van a hacer | S59: 0 | AA59: =_xlfn.XLOOKUP(Backlog[[#This Row],[Estado]],CatEstados[Estado],CatEstados[Fase],"Otro") -> Por hacer | AB59: =IF(OR(ISBLANK(Backlog[[#This Row],[Fecha comprometida (para UAT)]]),Backlog[[#This Row],[Fecha comprometida (para UAT)]]=""), "Sin fecha comprometida", IF( Backlog[[#This Row],[Fecha Real de Cierre]]="", TODAY()-Backlog[[#This Row],[Fecha comprometida (para UAT)]], Backlog[[#This Row],[Fecha Real de Cierre]]-Backlog[[#This Row],[Fecha comprometida (para UAT)]] ) ) -> Sin fecha comprometida | AC59: =IF(OR(#REF!="",NOT(ISNUMBER(Backlog[[#This Row],[Dias_abiertos]]))),"",IF(Backlog[[#This Row],[Dias_abiertos]]<=7,"En plazo",IFERROR(IF(Backlog[[#This Row],[Dias_abiertos]]=_xlfn.XLOOKUP(TRIM(#REF!),CatSLA[Prioridad],CatSLA[SLA_dias],""),"En plazo","Fuera de plazo"),"Sin SLA"))) -> #REF!
A60: 902 | B60: Mantenimiento preventivo | D60: 45939 | E60: Kafka - revisar versión | F60: Ver con Infra | G60: Todas las provincias | H60: Gamma | I60: SAC | K60: A priorizar | P60: Es de Infra el tema. Que expliquen a desarrollo que van a hacer | S60: 0 | AA60: =_xlfn.XLOOKUP(Backlog[[#This Row],[Estado]],CatEstados[Estado],CatEstados[Fase],"Otro") -> Por hacer | AB60: =IF(OR(ISBLANK(Backlog[[#This Row],[Fecha comprometida (para UAT)]]),Backlog[[#This Row],[Fecha comprometida (para UAT)]]=""), "Sin fecha comprometida", IF( Backlog[[#This Row],[Fecha Real de Cierre]]="", TODAY()-Backlog[[#This Row],[Fecha comprometida (para UAT)]], Backlog[[#This Row],[Fecha Real de Cierre]]-Backlog[[#This Row],[Fecha comprometida (para UAT)]] ) ) -> Sin fecha comprometida | AC60: =IF(OR(#REF!="",NOT(ISNUMBER(Backlog[[#This Row],[Dias_abiertos]]))),"",IF(Backlog[[#This Row],[Dias_abiertos]]<=7,"En plazo",IFERROR(IF(Backlog[[#This Row],[Dias_abiertos]]=_xlfn.XLOOKUP(TRIM(#REF!),CatSLA[Prioridad],CatSLA[SLA_dias],""),"En plazo","Fuera de plazo"),"Sin SLA"))) -> #REF!
A61: 903 | B61: Mantenimiento preventivo | D61: 45939 | E61: zookeeper - revisar versión | F61: Ver con Infra | G61: Todas las provincias | H61: Gamma | I61: SAC | K61: A priorizar | P61: Es de Infra el tema. Que expliquen a desarrollo que van a hacer | S61: 0 | AA61: =_xlfn.XLOOKUP(Backlog[[#This Row],[Estado]],CatEstados[Estado],CatEstados[Fase],"Otro") -> Por hacer | AB61: =IF(OR(ISBLANK(Backlog[[#This Row],[Fecha comprometida (para UAT)]]),Backlog[[#This Row],[Fecha comprometida (para UAT)]]=""), "Sin fecha comprometida", IF( Backlog[[#This Row],[Fecha Real de Cierre]]="", TODAY()-Backlog[[#This Row],[Fecha comprometida (para UAT)]], Backlog[[#This Row],[Fecha Real de Cierre]]-Backlog[[#This Row],[Fecha comprometida (para UAT)]] ) ) -> Sin fecha comprometida | AC61: =IF(OR(#REF!="",NOT(ISNUMBER(Backlog[[#This Row],[Dias_abiertos]]))),"",IF(Backlog[[#This Row],[Dias_abiertos]]<=7,"En plazo",IFERROR(IF(Backlog[[#This Row],[Dias_abiertos]]=_xlfn.XLOOKUP(TRIM(#REF!),CatSLA[Prioridad],CatSLA[SLA_dias],""),"En plazo","Fuera de plazo"),"Sin SLA"))) -> #REF!
A62: MAN-620 | B62: Mantenimiento correctivo | D62: 45856 | E62: SLA- Solicitud API sincronizar SAA-GAMMA(ver si corresponde al equipo de Fabiana) | F62: Se solicita habilitación Api para sincronizar SAA-Gamma, sobre todo tema relacionado con las agencias activas y su identificación comercial. Cuit-cuil/cambios de domicilios etc | G62: Todas las provincias | H62: Gamma | I62: SAC | K62: A priorizar | L62: MARZO | P62: Hay que arreglar el sincroagencias para multilotería. ver con Fabiana. | S62: 0 | AA62: =_xlfn.XLOOKUP(Backlog[[#This Row],[Estado]],CatEstados[Estado],CatEstados[Fase],"Otro") -> Por hacer | AB62: =IF(OR(ISBLANK(Backlog[[#This Row],[Fecha comprometida (para UAT)]]),Backlog[[#This Row],[Fecha comprometida (para UAT)]]=""), "Sin fecha comprometida", IF( Backlog[[#This Row],[Fecha Real de Cierre]]="", TODAY()-Backlog[[#This Row],[Fecha comprometida (para UAT)]], Backlog[[#This Row],[Fecha Real de Cierre]]-Backlog[[#This Row],[Fecha comprometida (para UAT)]] ) ) -> Sin fecha comprometida | AC62: =IF(OR(#REF!="",NOT(ISNUMBER(Backlog[[#This Row],[Dias_abiertos]]))),"",IF(Backlog[[#This Row],[Dias_abiertos]]<=7,"En plazo",IFERROR(IF(Backlog[[#This Row],[Dias_abiertos]]=_xlfn.XLOOKUP(TRIM(#REF!),CatSLA[Prioridad],CatSLA[SLA_dias],""),"En plazo","Fuera de plazo"),"Sin SLA"))) -> #REF!
A63: MAN-00011119 | B63: Mantenimiento evolutivo | D63: 45974 | E63: COR- Modificacion de listado Movimientos Diarios(Sf Casos 11119-11127-11122 | F63: Lotería solicita que el listado de movimientos diarios - Se emita y/o visualice en una sola hoja. - Quitar la impresión de "Liquidaciones Pendientes". - Aumentar el tamaño de la letra del importe a pagar y agregar la fecha de vencimiento al lado. | G63: Corrientes | H63: Gamma | I63: SAC | K63: Validar estado | O63: Parece imposible con la cantidad de datos que hay. Son muchos pedidos para un solo ticket. Que hagan tickets individuales y lo valide SAC | S63: 0 | AA63: =_xlfn.XLOOKUP(Backlog[[#This Row],[Estado]],CatEstados[Estado],CatEstados[Fase],"Otro") -> Implementación | AB63: =IF(OR(ISBLANK(Backlog[[#This Row],[Fecha comprometida (para UAT)]]),Backlog[[#This Row],[Fecha comprometida (para UAT)]]=""), "Sin fecha comprometida", IF( Backlog[[#This Row],[Fecha Real de Cierre]]="", TODAY()-Backlog[[#This Row],[Fecha comprometida (para UAT)]], Backlog[[#This Row],[Fecha Real de Cierre]]-Backlog[[#This Row],[Fecha comprometida (para UAT)]] ) ) -> Sin fecha comprometida | AC63: =IF(OR(#REF!="",NOT(ISNUMBER(Backlog[[#This Row],[Dias_abiertos]]))),"",IF(Backlog[[#This Row],[Dias_abiertos]]<=7,"En plazo",IFERROR(IF(Backlog[[#This Row],[Dias_abiertos]]=_xlfn.XLOOKUP(TRIM(#REF!),CatSLA[Prioridad],CatSLA[SLA_dias],""),"En plazo","Fuera de plazo"),"Sin SLA"))) -> #REF!
A64: MAN-00011282 | B64: Mantenimiento evolutivo | D64: 45978 | E64: JUJ-NOA- Modificación carga de archivos externos | F64: La Lotería solicita que el sistema NOA se adapte a la carga de archivos generados por los proveedores (para la carga de entregas, devoluciones de ser necesario, premios y retenciones), con el objetivo de automatizar el procedimiento y reducir al mínimo la intervención manual en el proceso. Esta mejora busca optimizar tiempos y disminuir riesgos asociados a la manipulación humana. | G64: Jujuy | H64: NOA | I64: SAC | K64: A priorizar | O64: Hay que llevarlo a algo concreto y claro. Que se pide exactamente? | S64: 60 | AA64: =_xlfn.XLOOKUP(Backlog[[#This Row],[Estado]],CatEstados[Estado],CatEstados[Fase],"Otro") -> Por hacer | AB64: =IF(OR(ISBLANK(Backlog[[#This Row],[Fecha comprometida (para UAT)]]),Backlog[[#This Row],[Fecha comprometida (para UAT)]]=""), "Sin fecha comprometida", IF( Backlog[[#This Row],[Fecha Real de Cierre]]="", TODAY()-Backlog[[#This Row],[Fecha comprometida (para UAT)]], Backlog[[#This Row],[Fecha Real de Cierre]]-Backlog[[#This Row],[Fecha comprometida (para UAT)]] ) ) -> Sin fecha comprometida | AC64: =IF(OR(#REF!="",NOT(ISNUMBER(Backlog[[#This Row],[Dias_abiertos]]))),"",IF(Backlog[[#This Row],[Dias_abiertos]]<=7,"En plazo",IFERROR(IF(Backlog[[#This Row],[Dias_abiertos]]=_xlfn.XLOOKUP(TRIM(#REF!),CatSLA[Prioridad],CatSLA[SLA_dias],""),"En plazo","Fuera de plazo"),"Sin SLA"))) -> #REF!
A65: MAN-00014262 | B65: Mantenimiento correctivo | D65: 46059 | E65: Gamma-COR Error en la liquidación | F65: Al iniciar la liquidación aparece un error de ETL. Se consulta al Soporte Gamma. Se verifica que un Alta nuevo en SAA estaba duplicado en gamma. Ag 440-005. | G65: Corrientes | H65: Gamma | I65: Mantenimiento | K65: Validar estado | O65: Sucedió porque dos máquinas se habilitaron al mismo tiempo. Fue un error operativo. | P65: Se puede evitar desde el sistema. | S65: 24 | AA65: =_xlfn.XLOOKUP(Backlog[[#This Row],[Estado]],CatEstados[Estado],CatEstados[Fase],"Otro") -> Implementación | AB65: =IF(OR(ISBLANK(Backlog[[#This Row],[Fecha comprometida (para UAT)]]),Backlog[[#This Row],[Fecha comprometida (para UAT)]]=""), "Sin fecha comprometida", IF( Backlog[[#This Row],[Fecha Real de Cierre]]="", TODAY()-Backlog[[#This Row],[Fecha comprometida (para UAT)]], Backlog[[#This Row],[Fecha Real de Cierre]]-Backlog[[#This Row],[Fecha comprometida (para UAT)]] ) ) -> Sin fecha comprometida | AC65: =IF(OR(#REF!="",NOT(ISNUMBER(Backlog[[#This Row],[Dias_abiertos]]))),"",IF(Backlog[[#This Row],[Dias_abiertos]]<=7,"En plazo",IFERROR(IF(Backlog[[#This Row],[Dias_abiertos]]=_xlfn.XLOOKUP(TRIM(#REF!),CatSLA[Prioridad],CatSLA[SLA_dias],""),"En plazo","Fuera de plazo"),"Sin SLA"))) -> #REF!
A66: MAN-14000 MAN - 000458 | B66: Mantenimiento evolutivo | D66: 46050 | E66: NOA Habilitar Editar / Anular Remito | F66: Se solicita habilitar las opciones de NOA para poder editar y/o eliminar remitos de entrada/salida. Se adjunta imagen | G66: Corrientes | H66: NOA | I66: SAC | K66: Validar estado | O66: Esto puede traer quilombo. No deberían editar o elimiar remitos. Es por seguridad y consistecia del sistema | S66: 0 | AA66: =_xlfn.XLOOKUP(Backlog[[#This Row],[Estado]],CatEstados[Estado],CatEstados[Fase],"Otro") -> Implementación | AB66: =IF(OR(ISBLANK(Backlog[[#This Row],[Fecha comprometida (para UAT)]]),Backlog[[#This Row],[Fecha comprometida (para UAT)]]=""), "Sin fecha comprometida", IF( Backlog[[#This Row],[Fecha Real de Cierre]]="", TODAY()-Backlog[[#This Row],[Fecha comprometida (para UAT)]], Backlog[[#This Row],[Fecha Real de Cierre]]-Backlog[[#This Row],[Fecha comprometida (para UAT)]] ) ) -> Sin fecha comprometida | AC66: =IF(OR(#REF!="",NOT(ISNUMBER(Backlog[[#This Row],[Dias_abiertos]]))),"",IF(Backlog[[#This Row],[Dias_abiertos]]<=7,"En plazo",IFERROR(IF(Backlog[[#This Row],[Dias_abiertos]]=_xlfn.XLOOKUP(TRIM(#REF!),CatSLA[Prioridad],CatSLA[SLA_dias],""),"En plazo","Fuera de plazo"),"Sin SLA"))) -> #REF!
A67: MAN-517 SF13331 | B67: Mantenimiento correctivo | D67: 46030 | E67: GAMMA no genera el certificado de Retención de IIBB | F67: GAMMA no genera el certificado de Retención de IIBB como se hace en el SIGA. Adjunto como tendria que salir, Tiene que salir dentro de constancia de retención dentro del modulo Contabilidad. Por mas que se pruebe con varios numero de presentación el certificado no lo genera. | G67: Santa Cruz | H67: Gamma | K67: QA | S67: 0 | AA67: =_xlfn.XLOOKUP(Backlog[[#This Row],[Estado]],CatEstados[Estado],CatEstados[Fase],"Otro") -> Otro | AB67: =IF(OR(ISBLANK(Backlog[[#This Row],[Fecha comprometida (para UAT)]]),Backlog[[#This Row],[Fecha comprometida (para UAT)]]=""), "Sin fecha comprometida", IF( Backlog[[#This Row],[Fecha Real de Cierre]]="", TODAY()-Backlog[[#This Row],[Fecha comprometida (para UAT)]], Backlog[[#This Row],[Fecha Real de Cierre]]-Backlog[[#This Row],[Fecha comprometida (para UAT)]] ) ) -> Sin fecha comprometida | AC67: =IF(OR(#REF!="",NOT(ISNUMBER(Backlog[[#This Row],[Dias_abiertos]]))),"",IF(Backlog[[#This Row],[Dias_abiertos]]<=7,"En plazo",IFERROR(IF(Backlog[[#This Row],[Dias_abiertos]]=_xlfn.XLOOKUP(TRIM(#REF!),CatSLA[Prioridad],CatSLA[SLA_dias],""),"En plazo","Fuera de plazo"),"Sin SLA"))) -> #REF!
A68: MAN-521 SF14871 | B68: Mantenimiento correctivo | D68: 46084 | E68: Gamma- No se visualizan nros de movimientos manuales | F68: En el GAMMA los movimientos que se cargan de forma manual y ya fue probado en las liquidaciones no se visualizan por mas que esten cargados los datos. Se adjunta las capturas de un ejemplo. El Movimiento manual cargado del Tele ag 300 con 5100 con el numero de sorteo cargado. Se liquidó. En la preliquidacion no se ve y tampoco en la el movimiento liquidado de la misma agencia. | G68: Santa Cruz | H68: Gamma | K68: Validar estado | O68: No se entiende. Ver con Luis y SAC. | S68: 0
A69: MAN-615 SF15068 | B69: Mantenimiento evolutivo | C69: Muy alta | D69: 46088 | E69: Gamma- Costo por Cupon - TK Proy MAN-811 | F69: Gamma- En las liquidaciones del Paralelo falta que se solicita que se cargue a todas la agencias se refleje en todas las liquidaciones diarias el costo por cupon actualmente es por 2,00 (valor variable). | G69: Tierra del Fuego | H69: Gamma | I69: SAC | K69: En desarrollo | Q69: https://tecnoaccionsa-my.sharepoint.com/:w:/g/personal/fgarufi_tecnoaccion_com_ar/IQBAU4fS_sleT4jYnVlJU-FWAUWpxBIkeJ-jw92j_gNhWsY?e=J8GuAl | S69: 60
A70: MAN-652 SF15835 | B70: Mantenimiento evolutivo | D70: 46118 | E70: Padron de agentes IIBB (Nota 013/26) | F70: La loteria de Santa Cruz el padron de IIBB lo genera en txt y la loteria lo pide con el formato que se adjunta en pdf. El padron debe respetar exactamente igual a las constancias que se emiten a los agencieros y consecuente mente los totales de importe retenido y el retenido. y como todo reporte piden que tenga el logo de la loteria | G70: Santa Cruz | H70: Gamma | K70: QA | Q70: Esto se desprende luego de la nota 013/26 enviada por Fernanda Serrano | S70: 0
A71: MAN-00011662 | B71: Mantenimiento preventivo | D71: 45986 | E71: Gamma- Consumo de memoria | F71: análisis y eventual solicitud de ampliación de memoria siendo que hoy las loterías en dicho entorno son Salta / Jujuy / La Rioja / Corrientes / Santa Cruz y estamos en las puertas de incorporar a Santiago del Estero. | G71: Todas las provincias | H71: Gamma | K71: Implementado / Soporte | S71: 0 | AA71: =_xlfn.XLOOKUP(Backlog[[#This Row],[Estado]],CatEstados[Estado],CatEstados[Fase],"Otro") -> Otro | AB71: =IF(OR(ISBLANK(Backlog[[#This Row],[Fecha comprometida (para UAT)]]),Backlog[[#This Row],[Fecha comprometida (para UAT)]]=""), "Sin fecha comprometida", IF( Backlog[[#This Row],[Fecha Real de Cierre]]="", TODAY()-Backlog[[#This Row],[Fecha comprometida (para UAT)]], Backlog[[#This Row],[Fecha Real de Cierre]]-Backlog[[#This Row],[Fecha comprometida (para UAT)]] ) ) -> Sin fecha comprometida | AC71: =IF(OR(#REF!="",NOT(ISNUMBER(Backlog[[#This Row],[Dias_abiertos]]))),"",IF(Backlog[[#This Row],[Dias_abiertos]]<=7,"En plazo",IFERROR(IF(Backlog[[#This Row],[Dias_abiertos]]=_xlfn.XLOOKUP(TRIM(#REF!),CatSLA[Prioridad],CatSLA[SLA_dias],""),"En plazo","Fuera de plazo"),"Sin SLA"))) -> #REF!
A72: MAN-00011639 | B72: Mantenimiento evolutivo | D72: 45986 | E72: Gamma Reporte de ventas y Comisiones | F72: Loteria solicita un reporte en Excel con la información de ventas y comisiones que se enviaba con anterioridad de manera mensual (se adjunta el Excel del mes pasado de referencia) pero además incluir códigos liquidados de VLT mes noviembre. Esta información adicional anteriormente se descargaban desde SIGA en el módulo Consulta > Contaduría > Liquidación de Agentes > Matriz de Códigos Liquidados. El reporte Excel final con toda la información debe ser enviado el 2 de diciembre por Mail a la siguiente dirección: evera@loteriacorrentina.gov.ar . Se adjunta ejemplos descriptivos. | G72: Corrientes | H72: Gamma | I72: SAC | K72: A priorizar | L72: 45993 | S72: 20 | AA72: =_xlfn.XLOOKUP(Backlog[[#This Row],[Estado]],CatEstados[Estado],CatEstados[Fase],"Otro") -> Por hacer | AB72: =IF(OR(ISBLANK(Backlog[[#This Row],[Fecha comprometida (para UAT)]]),Backlog[[#This Row],[Fecha comprometida (para UAT)]]=""), "Sin fecha comprometida", IF( Backlog[[#This Row],[Fecha Real de Cierre]]="", TODAY()-Backlog[[#This Row],[Fecha comprometida (para UAT)]], Backlog[[#This Row],[Fecha Real de Cierre]]-Backlog[[#This Row],[Fecha comprometida (para UAT)]] ) ) -> Sin fecha comprometida | AC72: =IF(OR(#REF!="",NOT(ISNUMBER(Backlog[[#This Row],[Dias_abiertos]]))),"",IF(Backlog[[#This Row],[Dias_abiertos]]<=7,"En plazo",IFERROR(IF(Backlog[[#This Row],[Dias_abiertos]]=_xlfn.XLOOKUP(TRIM(#REF!),CatSLA[Prioridad],CatSLA[SLA_dias],""),"En plazo","Fuera de plazo"),"Sin SLA"))) -> #REF!
A73: 1 | B73: Mantenimiento preventivo | D73: 45994 | E73: Revisión de microservicios que no se usan | G73: Todas las provincias | H73: Gamma | I73: SAC | K73: A priorizar | S73: 8 | AA73: =_xlfn.XLOOKUP(Backlog[[#This Row],[Estado]],CatEstados[Estado],CatEstados[Fase],"Otro") -> Por hacer | AB73: =IF(OR(ISBLANK(Backlog[[#This Row],[Fecha comprometida (para UAT)]]),Backlog[[#This Row],[Fecha comprometida (para UAT)]]=""), "Sin fecha comprometida", IF( Backlog[[#This Row],[Fecha Real de Cierre]]="", TODAY()-Backlog[[#This Row],[Fecha comprometida (para UAT)]], Backlog[[#This Row],[Fecha Real de Cierre]]-Backlog[[#This Row],[Fecha comprometida (para UAT)]] ) ) -> Sin fecha comprometida | AC73: =IF(OR(#REF!="",NOT(ISNUMBER(Backlog[[#This Row],[Dias_abiertos]]))),"",IF(Backlog[[#This Row],[Dias_abiertos]]<=7,"En plazo",IFERROR(IF(Backlog[[#This Row],[Dias_abiertos]]=_xlfn.XLOOKUP(TRIM(#REF!),CatSLA[Prioridad],CatSLA[SLA_dias],""),"En plazo","Fuera de plazo"),"Sin SLA"))) -> #REF!
A74: 2 | B74: Mantenimiento preventivo | D74: 45994 | E74: Revisión de procesos ETL que no se usan | G74: Todas las provincias | H74: Gamma | K74: En desarrollo | S74: 0 | AA74: =_xlfn.XLOOKUP(Backlog[[#This Row],[Estado]],CatEstados[Estado],CatEstados[Fase],"Otro") -> En curso | AB74: =IF(OR(ISBLANK(Backlog[[#This Row],[Fecha comprometida (para UAT)]]),Backlog[[#This Row],[Fecha comprometida (para UAT)]]=""), "Sin fecha comprometida", IF( Backlog[[#This Row],[Fecha Real de Cierre]]="", TODAY()-Backlog[[#This Row],[Fecha comprometida (para UAT)]], Backlog[[#This Row],[Fecha Real de Cierre]]-Backlog[[#This Row],[Fecha comprometida (para UAT)]] ) ) -> Sin fecha comprometida | AC74: =IF(OR(#REF!="",NOT(ISNUMBER(Backlog[[#This Row],[Dias_abiertos]]))),"",IF(Backlog[[#This Row],[Dias_abiertos]]<=7,"En plazo",IFERROR(IF(Backlog[[#This Row],[Dias_abiertos]]=_xlfn.XLOOKUP(TRIM(#REF!),CatSLA[Prioridad],CatSLA[SLA_dias],""),"En plazo","Fuera de plazo"),"Sin SLA"))) -> #REF!
A75: 3 | B75: Mantenimiento preventivo | D75: 45994 | E75: Revisión de memoria redis y cache | G75: Todas las provincias | H75: Gamma | I75: SAC | K75: A priorizar | S75: 20 | AA75: =_xlfn.XLOOKUP(Backlog[[#This Row],[Estado]],CatEstados[Estado],CatEstados[Fase],"Otro") -> Por hacer | AB75: =IF(OR(ISBLANK(Backlog[[#This Row],[Fecha comprometida (para UAT)]]),Backlog[[#This Row],[Fecha comprometida (para UAT)]]=""), "Sin fecha comprometida", IF( Backlog[[#This Row],[Fecha Real de Cierre]]="", TODAY()-Backlog[[#This Row],[Fecha comprometida (para UAT)]], Backlog[[#This Row],[Fecha Real de Cierre]]-Backlog[[#This Row],[Fecha comprometida (para UAT)]] ) ) -> Sin fecha comprometida | AC75: =IF(OR(#REF!="",NOT(ISNUMBER(Backlog[[#This Row],[Dias_abiertos]]))),"",IF(Backlog[[#This Row],[Dias_abiertos]]<=7,"En plazo",IFERROR(IF(Backlog[[#This Row],[Dias_abiertos]]=_xlfn.XLOOKUP(TRIM(#REF!),CatSLA[Prioridad],CatSLA[SLA_dias],""),"En plazo","Fuera de plazo"),"Sin SLA"))) -> #REF!
A76: 4 | B76: Mantenimiento preventivo | D76: 45994 | E76: Revisión de tareas programadas que no se usan. | G76: Todas las provincias | H76: Gamma | K76: Implementado / Soporte | S76: 0 | AA76: =_xlfn.XLOOKUP(Backlog[[#This Row],[Estado]],CatEstados[Estado],CatEstados[Fase],"Otro") -> Otro | AB76: =IF(OR(ISBLANK(Backlog[[#This Row],[Fecha comprometida (para UAT)]]),Backlog[[#This Row],[Fecha comprometida (para UAT)]]=""), "Sin fecha comprometida", IF( Backlog[[#This Row],[Fecha Real de Cierre]]="", TODAY()-Backlog[[#This Row],[Fecha comprometida (para UAT)]], Backlog[[#This Row],[Fecha Real de Cierre]]-Backlog[[#This Row],[Fecha comprometida (para UAT)]] ) ) -> Sin fecha comprometida | AC76: =IF(OR(#REF!="",NOT(ISNUMBER(Backlog[[#This Row],[Dias_abiertos]]))),"",IF(Backlog[[#This Row],[Dias_abiertos]]<=7,"En plazo",IFERROR(IF(Backlog[[#This Row],[Dias_abiertos]]=_xlfn.XLOOKUP(TRIM(#REF!),CatSLA[Prioridad],CatSLA[SLA_dias],""),"En plazo","Fuera de plazo"),"Sin SLA"))) -> #REF!
A77: MAN-00012125 | B77: Mantenimiento correctivo | D77: 46000 | E77: presentación de IIBB. casino | F77: Se realizaron pruebas en el entorno UAT con la propuesta de solución de Luis Rodríguez, pero no se obtuvo el resultado esperado. Él continúa trabajando en una alternativa. Una vez que esté lista para su validación, se llevará a cabo una nueva verificación en UAT, y si la prueba es exitosa, procederemos a su implementación en producción. | G77: Corrientes | H77: Gamma | I77: SAC | K77: A priorizar | S77: 16 | AA77: =_xlfn.XLOOKUP(Backlog[[#This Row],[Estado]],CatEstados[Estado],CatEstados[Fase],"Otro") -> Por hacer | AB77: =IF(OR(ISBLANK(Backlog[[#This Row],[Fecha comprometida (para UAT)]]),Backlog[[#This Row],[Fecha comprometida (para UAT)]]=""), "Sin fecha comprometida", IF( Backlog[[#This Row],[Fecha Real de Cierre]]="", TODAY()-Backlog[[#This Row],[Fecha comprometida (para UAT)]], Backlog[[#This Row],[Fecha Real de Cierre]]-Backlog[[#This Row],[Fecha comprometida (para UAT)]] ) ) -> Sin fecha comprometida | AC77: =IF(OR(#REF!="",NOT(ISNUMBER(Backlog[[#This Row],[Dias_abiertos]]))),"",IF(Backlog[[#This Row],[Dias_abiertos]]<=7,"En plazo",IFERROR(IF(Backlog[[#This Row],[Dias_abiertos]]=_xlfn.XLOOKUP(TRIM(#REF!),CatSLA[Prioridad],CatSLA[SLA_dias],""),"En plazo","Fuera de plazo"),"Sin SLA"))) -> #REF!
A78: MAN-00012726 | B78: Mantenimiento evolutivo | D78: 46010 | E78: SAL Integración Lotix y convivencia con Lotline | F78: Se necesita analizar la integración con Gamma-Lotix | G78: Salta | H78: Gamma | I78: SAC | K78: A priorizar | S78: 40 | AA78: =_xlfn.XLOOKUP(Backlog[[#This Row],[Estado]],CatEstados[Estado],CatEstados[Fase],"Otro") -> Por hacer | AB78: =IF(OR(ISBLANK(Backlog[[#This Row],[Fecha comprometida (para UAT)]]),Backlog[[#This Row],[Fecha comprometida (para UAT)]]=""), "Sin fecha comprometida", IF( Backlog[[#This Row],[Fecha Real de Cierre]]="", TODAY()-Backlog[[#This Row],[Fecha comprometida (para UAT)]], Backlog[[#This Row],[Fecha Real de Cierre]]-Backlog[[#This Row],[Fecha comprometida (para UAT)]] ) ) -> Sin fecha comprometida | AC78: =IF(OR(#REF!="",NOT(ISNUMBER(Backlog[[#This Row],[Dias_abiertos]]))),"",IF(Backlog[[#This Row],[Dias_abiertos]]<=7,"En plazo",IFERROR(IF(Backlog[[#This Row],[Dias_abiertos]]=_xlfn.XLOOKUP(TRIM(#REF!),CatSLA[Prioridad],CatSLA[SLA_dias],""),"En plazo","Fuera de plazo"),"Sin SLA"))) -> #REF!
A79: 16953 | B79: Mantenimiento evolutivo | C79: Media | D79: 46154 | E79: LR-Gamma Solicitud de Mejora para el Listado Estado General de Resúmenes en la Rioja | F79: Se solicita una mejora en el listado estado general de resúmenes para La Rioja , ya que según el personal que lo opera necesita ciertas mejoras para poder usarlo - adjunto informe .- | G79: La Rioja | H79: Gamma | I79: Mantenimiento | K79: A estimar | O79: Esto afecta a todas las provincias. Tener en cuenta. | P79: Detallar bien para todas. Que sea bien claro para evitar retrabajos. | S79: 40 | AA79: =_xlfn.XLOOKUP(Backlog[[#This Row],[Estado]],CatEstados[Estado],CatEstados[Fase],"Otro") -> Por hacer | AB79: =IF(OR(ISBLANK(Backlog[[#This Row],[Fecha comprometida (para UAT)]]),Backlog[[#This Row],[Fecha comprometida (para UAT)]]=""), "Sin fecha comprometida", IF( Backlog[[#This Row],[Fecha Real de Cierre]]="", TODAY()-Backlog[[#This Row],[Fecha comprometida (para UAT)]], Backlog[[#This Row],[Fecha Real de Cierre]]-Backlog[[#This Row],[Fecha comprometida (para UAT)]] ) ) -> Sin fecha comprometida | AC79: =IF(OR(#REF!="",NOT(ISNUMBER(Backlog[[#This Row],[Dias_abiertos]]))),"",IF(Backlog[[#This Row],[Dias_abiertos]]<=7,"En plazo",IFERROR(IF(Backlog[[#This Row],[Dias_abiertos]]=_xlfn.XLOOKUP(TRIM(#REF!),CatSLA[Prioridad],CatSLA[SLA_dias],""),"En plazo","Fuera de plazo"),"Sin SLA"))) -> #REF!
A80: 16954 | B80: Mantenimiento evolutivo | C80: Media | D80: 46154 | E80: Se solicita la generación de un comprobante al realizar un movimiento Manual | F80: Por razones administrativas se requiere la generación de un comprobante manual en Formato PDF , incluyendo los items mencionados en le informe . | G80: La Rioja | H80: Gamma | I80: Mantenimiento | K80: A priorizar | S80: 24 | AA80: =_xlfn.XLOOKUP(Backlog[[#This Row],[Estado]],CatEstados[Estado],CatEstados[Fase],"Otro") -> Por hacer | AB80: =IF(OR(ISBLANK(Backlog[[#This Row],[Fecha comprometida (para UAT)]]),Backlog[[#This Row],[Fecha comprometida (para UAT)]]=""), "Sin fecha comprometida", IF( Backlog[[#This Row],[Fecha Real de Cierre]]="", TODAY()-Backlog[[#This Row],[Fecha comprometida (para UAT)]], Backlog[[#This Row],[Fecha Real de Cierre]]-Backlog[[#This Row],[Fecha comprometida (para UAT)]] ) ) -> Sin fecha comprometida | AC80: =IF(OR(#REF!="",NOT(ISNUMBER(Backlog[[#This Row],[Dias_abiertos]]))),"",IF(Backlog[[#This Row],[Dias_abiertos]]<=7,"En plazo",IFERROR(IF(Backlog[[#This Row],[Dias_abiertos]]=_xlfn.XLOOKUP(TRIM(#REF!),CatSLA[Prioridad],CatSLA[SLA_dias],""),"En plazo","Fuera de plazo"),"Sin SLA"))) -> #REF!
A81: MAN-13030 | B81: Mantenimiento correctivo | D81: 46020 | E81: SC- Formato archivo de banco | F81: Verificar por favor el formato del archivo de banco de para los Cobros. El archivo de ejemplo es el que analizó el Banco Santa Cruz con el que trabaja ésta Loteria. Adjunto los archivos en cuestion y lo que pidió el banco. Solicitamos el analisis de los mismo para que sean modificados como pide el banco para su proceso correcto, | G81: Santa Cruz | H81: Gamma | K81: Validar estado | S81: 0 | AA81: =_xlfn.XLOOKUP(Backlog[[#This Row],[Estado]],CatEstados[Estado],CatEstados[Fase],"Otro") -> Implementación | AB81: =IF(OR(ISBLANK(Backlog[[#This Row],[Fecha comprometida (para UAT)]]),Backlog[[#This Row],[Fecha comprometida (para UAT)]]=""), "Sin fecha comprometida", IF( Backlog[[#This Row],[Fecha Real de Cierre]]="", TODAY()-Backlog[[#This Row],[Fecha comprometida (para UAT)]], Backlog[[#This Row],[Fecha Real de Cierre]]-Backlog[[#This Row],[Fecha comprometida (para UAT)]] ) ) -> Sin fecha comprometida | AC81: =IF(OR(#REF!="",NOT(ISNUMBER(Backlog[[#This Row],[Dias_abiertos]]))),"",IF(Backlog[[#This Row],[Dias_abiertos]]<=7,"En plazo",IFERROR(IF(Backlog[[#This Row],[Dias_abiertos]]=_xlfn.XLOOKUP(TRIM(#REF!),CatSLA[Prioridad],CatSLA[SLA_dias],""),"En plazo","Fuera de plazo"),"Sin SLA"))) -> #REF! | AJ81: Validar si está solucionado
A82: MAN-0010257 | B82: Mantenimiento correctivo | D82: 46027 | E82: COR- Gamma-Reporte | F82: Cuando se incorpora un archivo bancario cancelando un resumen vencido el sistema no refleja correctamente el balanceo en cta cte. Si cambia correctamente el estado del mismo. Lo mismo sucede en S. Cruz caso en SF. 9950 de dicha Prov. | G82: Corrientes | H82: Gamma | K82: Validar estado | M82: MARZO | S82: 0 | AA82: =_xlfn.XLOOKUP(Backlog[[#This Row],[Estado]],CatEstados[Estado],CatEstados[Fase],"Otro") -> Implementación | AB82: =IF(OR(ISBLANK(Backlog[[#This Row],[Fecha comprometida (para UAT)]]),Backlog[[#This Row],[Fecha comprometida (para UAT)]]=""), "Sin fecha comprometida", IF( Backlog[[#This Row],[Fecha Real de Cierre]]="", TODAY()-Backlog[[#This Row],[Fecha comprometida (para UAT)]], Backlog[[#This Row],[Fecha Real de Cierre]]-Backlog[[#This Row],[Fecha comprometida (para UAT)]] ) ) -> #VALUE! | AC82: =IF(OR(#REF!="",NOT(ISNUMBER(Backlog[[#This Row],[Dias_abiertos]]))),"",IF(Backlog[[#This Row],[Dias_abiertos]]<=7,"En plazo",IFERROR(IF(Backlog[[#This Row],[Dias_abiertos]]=_xlfn.XLOOKUP(TRIM(#REF!),CatSLA[Prioridad],CatSLA[SLA_dias],""),"En plazo","Fuera de plazo"),"Sin SLA"))) -> #REF! | AJ82: Validar si está solucionado
A83: MAN - 000561 SF15148 | B83: Mantenimiento correctivo | D83: 46036 | E83: Gamma- Registro de pagos cobros en el modulo de caja, Agencia nueva | F83: Lotería comenta que desde que se dió de alta la agencia 220 no se puede procesar en caja para cobrar o pagar. Se intentó procesar las liquidaciones de a una o grupales como las demás y en todos los casos da "Error de conexión" | G83: Jujuy | H83: Gamma | K83: A priorizar | L83: MARZO | S83: 36 | AA83: =_xlfn.XLOOKUP(Backlog[[#This Row],[Estado]],CatEstados[Estado],CatEstados[Fase],"Otro") -> Por hacer | AB83: =IF(OR(ISBLANK(Backlog[[#This Row],[Fecha comprometida (para UAT)]]),Backlog[[#This Row],[Fecha comprometida (para UAT)]]=""), "Sin fecha comprometida", IF( Backlog[[#This Row],[Fecha Real de Cierre]]="", TODAY()-Backlog[[#This Row],[Fecha comprometida (para UAT)]], Backlog[[#This Row],[Fecha Real de Cierre]]-Backlog[[#This Row],[Fecha comprometida (para UAT)]] ) ) -> Sin fecha comprometida | AC83: =IF(OR(#REF!="",NOT(ISNUMBER(Backlog[[#This Row],[Dias_abiertos]]))),"",IF(Backlog[[#This Row],[Dias_abiertos]]<=7,"En plazo",IFERROR(IF(Backlog[[#This Row],[Dias_abiertos]]=_xlfn.XLOOKUP(TRIM(#REF!),CatSLA[Prioridad],CatSLA[SLA_dias],""),"En plazo","Fuera de plazo"),"Sin SLA"))) -> #REF!
A84: MAN-191 SF10881 | B84: Mantenimiento evolutivo | D84: 46052 | E84: Gamma- RN- Exportacion de archivos a Bejerman Web. | F84: Solicitan que el archivo que sale en txt de exportación de asientos lo puedan sacar en XLS con el nuevo formato para Bejerman Web | G84: Río Negro | H84: Gamma | K84: A priorizar | M84: MARZO | S84: 40 | AA84: =_xlfn.XLOOKUP(Backlog[[#This Row],[Estado]],CatEstados[Estado],CatEstados[Fase],"Otro") -> Por hacer | AB84: =IF(OR(ISBLANK(Backlog[[#This Row],[Fecha comprometida (para UAT)]]),Backlog[[#This Row],[Fecha comprometida (para UAT)]]=""), "Sin fecha comprometida", IF( Backlog[[#This Row],[Fecha Real de Cierre]]="", TODAY()-Backlog[[#This Row],[Fecha comprometida (para UAT)]], Backlog[[#This Row],[Fecha Real de Cierre]]-Backlog[[#This Row],[Fecha comprometida (para UAT)]] ) ) -> #VALUE! | AC84: =IF(OR(#REF!="",NOT(ISNUMBER(Backlog[[#This Row],[Dias_abiertos]]))),"",IF(Backlog[[#This Row],[Dias_abiertos]]<=7,"En plazo",IFERROR(IF(Backlog[[#This Row],[Dias_abiertos]]=_xlfn.XLOOKUP(TRIM(#REF!),CatSLA[Prioridad],CatSLA[SLA_dias],""),"En plazo","Fuera de plazo"),"Sin SLA"))) -> #REF! | AJ84: Validar si está solucionado
A85: MAN-00014048 | B85: Mantenimiento correctivo | D85: 46052 | E85: Gamma | CHECKINGACCOUNT – Caídas de servicio | F85: Se adjunta log y captura de pantalla con los horarios de las caidas. Se detectaron dos caídas del servicio CHECKINGACCOUNT del aplicativo Gamma, una el viernes 23/01 pasado alrededor de las 00:00 hs y otra el viernes 30/01, en un horario similar. Se solicita análisis del incidente, causa raíz y acciones correctivas/preventivas. | G85: Todas las provincias | H85: Gamma | K85: Validar estado | S85: 0 | AA85: =_xlfn.XLOOKUP(Backlog[[#This Row],[Estado]],CatEstados[Estado],CatEstados[Fase],"Otro") -> Implementación | AB85: =IF(OR(ISBLANK(Backlog[[#This Row],[Fecha comprometida (para UAT)]]),Backlog[[#This Row],[Fecha comprometida (para UAT)]]=""), "Sin fecha comprometida", IF( Backlog[[#This Row],[Fecha Real de Cierre]]="", TODAY()-Backlog[[#This Row],[Fecha comprometida (para UAT)]], Backlog[[#This Row],[Fecha Real de Cierre]]-Backlog[[#This Row],[Fecha comprometida (para UAT)]] ) ) -> Sin fecha comprometida | AC85: =IF(OR(#REF!="",NOT(ISNUMBER(Backlog[[#This Row],[Dias_abiertos]]))),"",IF(Backlog[[#This Row],[Dias_abiertos]]<=7,"En plazo",IFERROR(IF(Backlog[[#This Row],[Dias_abiertos]]=_xlfn.XLOOKUP(TRIM(#REF!),CatSLA[Prioridad],CatSLA[SLA_dias],""),"En plazo","Fuera de plazo"),"Sin SLA"))) -> #REF! | AJ85: Validar si está solucionado con Santaigo Aoki
A86: MAN-12357 | B86: Mantenimiento evolutivo | D86: 46007 | E86: Modulo de Caja - Permitir cargar la fecha de pago del resumen | F86: Lotería solicita lo antes posible que en el modulo CAJA exista la opción de elegir fecha de pago, a los fines de incorporar cobros manuales con fechas anteriores a la fecha actual del sistema. Tiene relación directa con el MAN ID716 - Tesoreria - Fecha valor en cobros manuales | G86: Corrientes | H86: Gamma | K86: A priorizar | S86: 36 | AA86: =_xlfn.XLOOKUP(Backlog[[#This Row],[Estado]],CatEstados[Estado],CatEstados[Fase],"Otro") -> Por hacer | AB86: =IF(OR(ISBLANK(Backlog[[#This Row],[Fecha comprometida (para UAT)]]),Backlog[[#This Row],[Fecha comprometida (para UAT)]]=""), "Sin fecha comprometida", IF( Backlog[[#This Row],[Fecha Real de Cierre]]="", TODAY()-Backlog[[#This Row],[Fecha comprometida (para UAT)]], Backlog[[#This Row],[Fecha Real de Cierre]]-Backlog[[#This Row],[Fecha comprometida (para UAT)]] ) ) -> Sin fecha comprometida | AC86: =IF(OR(#REF!="",NOT(ISNUMBER(Backlog[[#This Row],[Dias_abiertos]]))),"",IF(Backlog[[#This Row],[Dias_abiertos]]<=7,"En plazo",IFERROR(IF(Backlog[[#This Row],[Dias_abiertos]]=_xlfn.XLOOKUP(TRIM(#REF!),CatSLA[Prioridad],CatSLA[SLA_dias],""),"En plazo","Fuera de plazo"),"Sin SLA"))) -> #REF! | AJ86: Validar con Napoleon Mena
A87: MAN - 000466 SF 14508 | B87: Mantenimiento correctivo | C87: Alta | D87: 15/9/2025 | E87: Gamma-LR-No entran los movimientos en las liquidaciones | F87: Es necesario cambiar manualmente el estado de liquidación de los días domingos, desmarcando el estado “liquidado” y configurándolo en false. | G87: Todas las provincias | H87: Gamma | I87: Mantenimiento | J87: 7 | K87: A planificar | L87: 46053 | M87: MARZO | O87: El problema sigue. El paliativo es no configurar el domingo hasta el dia que lo vas a liquidar. (El martes mismo que liquidan) Bajaría la prioridad. Hay que documentar. Solución que otra provincia no impacte en la que no tiene actividad. | Q87: LR - GAMMA - CASO 8134 - No entran los movimientos en las liquidaciones - 1.2.DOC | S87: 13 | AA87: =_xlfn.XLOOKUP(Backlog[[#This Row],[Estado]],CatEstados[Estado],CatEstados[Fase],"Otro") -> Por hacer | AB87: =IF(OR(ISBLANK(Backlog[[#This Row],[Fecha comprometida (para UAT)]]),Backlog[[#This Row],[Fecha comprometida (para UAT)]]=""), "Sin fecha comprometida", IF( Backlog[[#This Row],[Fecha Real de Cierre]]="", TODAY()-Backlog[[#This Row],[Fecha comprometida (para UAT)]], Backlog[[#This Row],[Fecha Real de Cierre]]-Backlog[[#This Row],[Fecha comprometida (para UAT)]] ) ) -> #VALUE! | AC87: =IF(OR(#REF!="",NOT(ISNUMBER(Backlog[[#This Row],[Dias_abiertos]]))),"",IF(Backlog[[#This Row],[Dias_abiertos]]<=7,"En plazo",IFERROR(IF(Backlog[[#This Row],[Dias_abiertos]]=_xlfn.XLOOKUP(TRIM(#REF!),CatSLA[Prioridad],CatSLA[SLA_dias],""),"En plazo","Fuera de plazo"),"Sin SLA"))) -> #REF! | AJ87: Validar con Napoleon Mena
A88: MAN-00008136 | B88: Mantenimiento correctivo | C88: Alta | D88: 15/9/2025 | E88: Gamma-T.L.P.- Agregar modulo de homologación. Caso 8136 | F88: Homologación de Imputación y Código Contable para el servicio Discount Para que nuevos movimientos puedan ser ingresados mediante el servicio, deben insertarse registros en la BD-Discount, tabla Homologation_imputation | G88: Todas las provincias | H88: Gamma | I88: Mantenimiento | J88: 8 | K88: A planificar | L88: 46053 | M88: MARZO | Q88: Caso 8136 - Homologación de códigos contables en DISCON - 1.1.docx | S88: 68 | U88: Jimena | AA88: =_xlfn.XLOOKUP(Backlog[[#This Row],[Estado]],CatEstados[Estado],CatEstados[Fase],"Otro") -> Por hacer | AB88: =IF(OR(ISBLANK(Backlog[[#This Row],[Fecha comprometida (para UAT)]]),Backlog[[#This Row],[Fecha comprometida (para UAT)]]=""), "Sin fecha comprometida", IF( Backlog[[#This Row],[Fecha Real de Cierre]]="", TODAY()-Backlog[[#This Row],[Fecha comprometida (para UAT)]], Backlog[[#This Row],[Fecha Real de Cierre]]-Backlog[[#This Row],[Fecha comprometida (para UAT)]] ) ) -> #VALUE! | AC88: =IF(OR(#REF!="",NOT(ISNUMBER(Backlog[[#This Row],[Dias_abiertos]]))),"",IF(Backlog[[#This Row],[Dias_abiertos]]<=7,"En plazo",IFERROR(IF(Backlog[[#This Row],[Dias_abiertos]]=_xlfn.XLOOKUP(TRIM(#REF!),CatSLA[Prioridad],CatSLA[SLA_dias],""),"En plazo","Fuera de plazo"),"Sin SLA"))) -> #REF! | AJ88: Validar con Napoleon Mena
A89: 00008135 | B89: Mantenimiento evolutivo | C89: Alta | D89: 15/9/2025 | E89: Gamma-T.L.P.-ABM para reglas | F89: a. Cambios de alícuotas, nuevos conceptos o creación de nuevas zonas que impacten en los cálculos requieren la creación de nuevas reglas en BD Calculator, de forma manual. b. Generación de reglas particulares según necesidad específica. | G89: Todas las provincias | H89: Gamma | I89: Mantenimiento | J89: 10 | K89: A planificar | L89: 46053 | M89: MARZO | O89: Cumple con los parámetros de la dirección. En desarrolo ABM de comisiones. No hay ABM de impuestos (faltarían los impuestos) | Q89: https://tecnoaccionsa.sharepoint.com/:w:/s/GAMMA.2024/IQAdK3QuBWdcQLY7heyCwY-hAet-gDt7lWKMOA3O1k2O1zw?e=j9Sbue | S89: 51 | U89: Marcos | AA89: =_xlfn.XLOOKUP(Backlog[[#This Row],[Estado]],CatEstados[Estado],CatEstados[Fase],"Otro") -> Por hacer | AB89: =IF(OR(ISBLANK(Backlog[[#This Row],[Fecha comprometida (para UAT)]]),Backlog[[#This Row],[Fecha comprometida (para UAT)]]=""), "Sin fecha comprometida", IF( Backlog[[#This Row],[Fecha Real de Cierre]]="", TODAY()-Backlog[[#This Row],[Fecha comprometida (para UAT)]], Backlog[[#This Row],[Fecha Real de Cierre]]-Backlog[[#This Row],[Fecha comprometida (para UAT)]] ) ) -> #VALUE! | AC89: =IF(OR(#REF!="",NOT(ISNUMBER(Backlog[[#This Row],[Dias_abiertos]]))),"",IF(Backlog[[#This Row],[Dias_abiertos]]<=7,"En plazo",IFERROR(IF(Backlog[[#This Row],[Dias_abiertos]]=_xlfn.XLOOKUP(TRIM(#REF!),CatSLA[Prioridad],CatSLA[SLA_dias],""),"En plazo","Fuera de plazo"),"Sin SLA"))) -> #REF! | AJ89: Validar con Napoleon Mena
A90: MAN-511 | B90: Mantenimiento correctivo | C90: Media | D90: 45812 | E90: 45812 | F90: Jujuy Gamma Desde contable comentan que para el periodo de mayo, no es posible descargar las declaraciones juradas y las constancias de lo que se genera en impuestos a las Ganancias y lo que se genera para el cobro de IIBB. Está mal la información como el formato. Por lo que teniendo fecha de vencimiento de presentación hasta este viernes 06/06/25, solicitan la corrección urgente de la misma. Por lo que solicito un Jira que permita ver y solucionar este tema. Luis Rodriguez como Mario están al tanto del problema. | G90: Jujuy | H90: Gamma | I90: Mantenimiento | J90: 11 | K90: A planificar | M90: MARZO | O90: Está Ingresos Brutos. Falta GANANCIAS. HACER OTRO TICKET CON EL ERROR ESPECIFICO PARA GANANCIAS!!!!!!!!! | R90: 2 | S90: 41 | U90: Paolo | AA90: =_xlfn.XLOOKUP(Backlog[[#This Row],[Estado]],CatEstados[Estado],CatEstados[Fase],"Otro") -> Por hacer | AB90: =IF(OR(ISBLANK(Backlog[[#This Row],[Fecha comprometida (para UAT)]]),Backlog[[#This Row],[Fecha comprometida (para UAT)]]=""), "Sin fecha comprometida", IF( Backlog[[#This Row],[Fecha Real de Cierre]]="", TODAY()-Backlog[[#This Row],[Fecha comprometida (para UAT)]], Backlog[[#This Row],[Fecha Real de Cierre]]-Backlog[[#This Row],[Fecha comprometida (para UAT)]] ) ) -> #VALUE! | AC90: =IF(OR(#REF!="",NOT(ISNUMBER(Backlog[[#This Row],[Dias_abiertos]]))),"",IF(Backlog[[#This Row],[Dias_abiertos]]<=7,"En plazo",IFERROR(IF(Backlog[[#This Row],[Dias_abiertos]]=_xlfn.XLOOKUP(TRIM(#REF!),CatSLA[Prioridad],CatSLA[SLA_dias],""),"En plazo","Fuera de plazo"),"Sin SLA"))) -> #REF!
A91: 7855 | B91: Mantenimiento correctivo | C91: Media | D91: 45970 | E91: Duplicados en reporte Resumen de Obligaciones | F91: Problema en el Excel exportado en el proceso de Liquidación, es decir en el Reporte Resumen de Obligaciones. Duplicado la Agencia 10 | G91: Corrientes | H91: Gamma | I91: Mantenimiento | J91: 12 | K91: A planificar | O91: Registros duplicados de obligación de pagos para la agencia 10 Análisis: Se detectó que el endpoint que consulta las obligaciones de cobros y pagos durante una preliquidación devuelve registros duplicados para la agencia 10. La causa se debe a que en la tabla banking_accounts existen dos registros asociados a la misma agencia, de los cuales uno se encuentra en estado deleted. La duplicación se produce porque, para la generación del reporte, la información se extrae desde dos bases de datos distintas (Agencies y Checking_accounts). De ambas se obtienen los resúmenes y los datos complementarios de las agencias (CUIT, CBU, etc.), lo que provoca la inconsistencia. Solución propuesta: Modificar los scripts de consulta de manera que el endpoint: Considere únicamente los registros de banking_accounts cuyo campo deleted sea NULL. Filtre adicionalmente por el campo organization_id correspondiente tanto en la base de datos Agencies como en Checking_accounts | P91: Ver esfuerzo. | Q91: MAN-7855 - COR - GAMMA - Duplicados reporte Resumen de Obligaciones - 1.0.docx | S91: 14 | U91: Jimena | AA91: =_xlfn.XLOOKUP(Backlog[[#This Row],[Estado]],CatEstados[Estado],CatEstados[Fase],"Otro") -> Por hacer | AB91: =IF(OR(ISBLANK(Backlog[[#This Row],[Fecha comprometida (para UAT)]]),Backlog[[#This Row],[Fecha comprometida (para UAT)]]=""), "Sin fecha comprometida", IF( Backlog[[#This Row],[Fecha Real de Cierre]]="", TODAY()-Backlog[[#This Row],[Fecha comprometida (para UAT)]], Backlog[[#This Row],[Fecha Real de Cierre]]-Backlog[[#This Row],[Fecha comprometida (para UAT)]] ) ) -> Sin fecha comprometida | AC91: =IF(OR(#REF!="",NOT(ISNUMBER(Backlog[[#This Row],[Dias_abiertos]]))),"",IF(Backlog[[#This Row],[Dias_abiertos]]<=7,"En plazo",IFERROR(IF(Backlog[[#This Row],[Dias_abiertos]]=_xlfn.XLOOKUP(TRIM(#REF!),CatSLA[Prioridad],CatSLA[SLA_dias],""),"En plazo","Fuera de plazo"),"Sin SLA"))) -> #REF!
A92: MAN - 000093 10708 | B92: Mantenimiento correctivo | C92: Alta | D92: 45964 | E92: Error en reporte 104 - Gamma. Caso SF 00010708 MAN-573 | F92: Lotería reclama un error en el reporte 104, que desde hoy aparece (aparentemente a causa de la implementación del viernes 31-10-25). En la selección de agencias para emitir reportes, el sistema muestra en pantalla el reporte con otros números de agencia que no existen siquiera. El área de fiscalización contable reclama por estár haciendo controles por el mes de Octubre. | G92: Jujuy | H92: Gamma | I92: Mantenimiento | J92: 13 | K92: A planificar | O92: Sería de bajo esfuerzo solucionarlo. Ver con Tejerina | Q92: MAN 0483 - Error en reporte 104 - 1.0.docx | S92: 14 | U92: Alejandro | AA92: =_xlfn.XLOOKUP(Backlog[[#This Row],[Estado]],CatEstados[Estado],CatEstados[Fase],"Otro") -> Por hacer | AB92: =IF(OR(ISBLANK(Backlog[[#This Row],[Fecha comprometida (para UAT)]]),Backlog[[#This Row],[Fecha comprometida (para UAT)]]=""), "Sin fecha comprometida", IF( Backlog[[#This Row],[Fecha Real de Cierre]]="", TODAY()-Backlog[[#This Row],[Fecha comprometida (para UAT)]], Backlog[[#This Row],[Fecha Real de Cierre]]-Backlog[[#This Row],[Fecha comprometida (para UAT)]] ) ) -> Sin fecha comprometida | AC92: =IF(OR(#REF!="",NOT(ISNUMBER(Backlog[[#This Row],[Dias_abiertos]]))),"",IF(Backlog[[#This Row],[Dias_abiertos]]<=7,"En plazo",IFERROR(IF(Backlog[[#This Row],[Dias_abiertos]]=_xlfn.XLOOKUP(TRIM(#REF!),CatSLA[Prioridad],CatSLA[SLA_dias],""),"En plazo","Fuera de plazo"),"Sin SLA"))) -> #REF!
A93: MAN-483 | B93: Mantenimiento correctivo | C93: Alta | D93: 45805 | E93: JUY-Gamma Reporte movimientos de la lotería por la agencia 998 Ver Caso 6675 | F93: Luego de revisar un poco los reportes, se encontró que los movimientos de la lotería por la agencia 998 por pago de premios por tesorería o de otra agencia, se están perdiendo por no registrarse. Por lo que los reportes tienen faltante de información. Solicitamos revisar el problema y sugerir una solución a la misma, para poder presentar los reportes a lotería antes de fin de mes. | G93: Jujuy | H93: Gamma | I93: Mantenimiento | J93: 14 | K93: A planificar | O93: Este es por el 104. Detallar bien que se quiere. | P93: Consenso con Fabiana | S93: 34 | U93: Tejerina | AA93: =_xlfn.XLOOKUP(Backlog[[#This Row],[Estado]],CatEstados[Estado],CatEstados[Fase],"Otro") -> Por hacer | AB93: =IF(OR(ISBLANK(Backlog[[#This Row],[Fecha comprometida (para UAT)]]),Backlog[[#This Row],[Fecha comprometida (para UAT)]]=""), "Sin fecha comprometida", IF( Backlog[[#This Row],[Fecha Real de Cierre]]="", TODAY()-Backlog[[#This Row],[Fecha comprometida (para UAT)]], Backlog[[#This Row],[Fecha Real de Cierre]]-Backlog[[#This Row],[Fecha comprometida (para UAT)]] ) ) -> Sin fecha comprometida | AC93: =IF(OR(#REF!="",NOT(ISNUMBER(Backlog[[#This Row],[Dias_abiertos]]))),"",IF(Backlog[[#This Row],[Dias_abiertos]]<=7,"En plazo",IFERROR(IF(Backlog[[#This Row],[Dias_abiertos]]=_xlfn.XLOOKUP(TRIM(#REF!),CatSLA[Prioridad],CatSLA[SLA_dias],""),"En plazo","Fuera de plazo"),"Sin SLA"))) -> #REF!
A94: MAN - 000061 | B94: Mantenimiento correctivo | C94: Alta | D94: 45953 | E94: BD propia de NOA no sincroniza con agencias del GAMMA (Prioridad ALTA). Caso SF 00010300 | F94: Al modificar los datos de una agencia existente o crear una nueva en GAMMA, NOA no actualiza la información.Para Priorizar | G94: Todas las provincias | H94: NOA | I94: Mantenimiento | J94: 15 | K94: A planificar | L94: 45992 | M94: MARZO | O94: Estaría para desplegar el lunes? | P94: Se desplegó? Implementado? | R94: 1 | S94: 4 | U94: 1 | W94: 4 | AA94: =_xlfn.XLOOKUP(Backlog[[#This Row],[Estado]],CatEstados[Estado],CatEstados[Fase],"Otro") -> Por hacer | AB94: =IF(OR(ISBLANK(Backlog[[#This Row],[Fecha comprometida (para UAT)]]),Backlog[[#This Row],[Fecha comprometida (para UAT)]]=""), "Sin fecha comprometida", IF( Backlog[[#This Row],[Fecha Real de Cierre]]="", TODAY()-Backlog[[#This Row],[Fecha comprometida (para UAT)]], Backlog[[#This Row],[Fecha Real de Cierre]]-Backlog[[#This Row],[Fecha comprometida (para UAT)]] ) ) -> #VALUE! | AC94: =IF(OR(#REF!="",NOT(ISNUMBER(Backlog[[#This Row],[Dias_abiertos]]))),"",IF(Backlog[[#This Row],[Dias_abiertos]]<=7,"En plazo",IFERROR(IF(Backlog[[#This Row],[Dias_abiertos]]=_xlfn.XLOOKUP(TRIM(#REF!),CatSLA[Prioridad],CatSLA[SLA_dias],""),"En plazo","Fuera de plazo"),"Sin SLA"))) -> #REF!
A95: MAN-00012574 | B95: Mantenimiento correctivo | C95: Media | D95: 45987 | E95: NOA- Generación Archivo Entregas | F95: Lotería utiliza . sacan el reporte de siga en preimpresos> generación de archivos para entregas. EN NOA/Procesamiento de archivos/Ventas Telekino - Archivo de Salida (No Funciona o no esta desarrollado) | G95: Corrientes | H95: NOA | J95: 16 | K95: A planificar | M95: MARZO | Q95: NOA - MAN 12574 - Generación archivo de entregas - 1.0.docx | S95: 41 | U95: Paolo | AA95: =_xlfn.XLOOKUP(Backlog[[#This Row],[Estado]],CatEstados[Estado],CatEstados[Fase],"Otro") -> Por hacer | AB95: =IF(OR(ISBLANK(Backlog[[#This Row],[Fecha comprometida (para UAT)]]),Backlog[[#This Row],[Fecha comprometida (para UAT)]]=""), "Sin fecha comprometida", IF( Backlog[[#This Row],[Fecha Real de Cierre]]="", TODAY()-Backlog[[#This Row],[Fecha comprometida (para UAT)]], Backlog[[#This Row],[Fecha Real de Cierre]]-Backlog[[#This Row],[Fecha comprometida (para UAT)]] ) ) -> #VALUE! | AC95: =IF(OR(#REF!="",NOT(ISNUMBER(Backlog[[#This Row],[Dias_abiertos]]))),"",IF(Backlog[[#This Row],[Dias_abiertos]]<=7,"En plazo",IFERROR(IF(Backlog[[#This Row],[Dias_abiertos]]=_xlfn.XLOOKUP(TRIM(#REF!),CatSLA[Prioridad],CatSLA[SLA_dias],""),"En plazo","Fuera de plazo"),"Sin SLA"))) -> #REF!
A96: MAN - 000094 10705 | B96: Mantenimiento correctivo | C96: Alta | D96: 45964 | E96: *Resúmenes de crédito con fecha errónea de vencimiento* Reporte resumen de obligaciones solo figura total a cobrar. Caso SF 00010705 | F96: En la liquidación del día Domingo 2 de noviembre, en el paso "Resumen de Obligaciones" en pantalla vemos tanto "Total a Pagar" como "Total a cobrar" sin embargo al exportar el Excel solo figura total a cobrar, falta que se visualice en el archivo de Excel la información correspondiente a total a pagar. | G96: Corrientes | H96: Gamma | I96: Mantenimiento | J96: 17 | K96: A planificar | M96: MARZO | O96: Ocurrió solo una vez luego de una actualización de Gamma y solo ocurrió en Corrientes. No se sabe que pasó. Se supone que fue algo colateral de esa implementación en particular. Se recomienda observa si vuelve a ocurrir alguna vez. Corriente asumiría que este de desestime si no se repite. | S96: 4 | U96: Jimena | AA96: =_xlfn.XLOOKUP(Backlog[[#This Row],[Estado]],CatEstados[Estado],CatEstados[Fase],"Otro") -> Por hacer | AB96: =IF(OR(ISBLANK(Backlog[[#This Row],[Fecha comprometida (para UAT)]]),Backlog[[#This Row],[Fecha comprometida (para UAT)]]=""), "Sin fecha comprometida", IF( Backlog[[#This Row],[Fecha Real de Cierre]]="", TODAY()-Backlog[[#This Row],[Fecha comprometida (para UAT)]], Backlog[[#This Row],[Fecha Real de Cierre]]-Backlog[[#This Row],[Fecha comprometida (para UAT)]] ) ) -> #VALUE! | AC96: =IF(OR(#REF!="",NOT(ISNUMBER(Backlog[[#This Row],[Dias_abiertos]]))),"",IF(Backlog[[#This Row],[Dias_abiertos]]<=7,"En plazo",IFERROR(IF(Backlog[[#This Row],[Dias_abiertos]]=_xlfn.XLOOKUP(TRIM(#REF!),CatSLA[Prioridad],CatSLA[SLA_dias],""),"En plazo","Fuera de plazo"),"Sin SLA"))) -> #REF!
A97: 558 | B97: Mantenimiento preventivo | C97: Alta | D97: 45800 | E97: Investigar funcionamiento de los procesos de depuración | F97: Analisis en Desarrollo. Proceso de depuración. Luego Infra corre depuración a pedido. | G97: Todas las provincias | H97: Gamma | I97: Mantenimiento | J97: 18 | K97: A planificar | S97: 8 | U97: Tejerina | AA97: =_xlfn.XLOOKUP(Backlog[[#This Row],[Estado]],CatEstados[Estado],CatEstados[Fase],"Otro") -> Por hacer | AB97: =IF(OR(ISBLANK(Backlog[[#This Row],[Fecha comprometida (para UAT)]]),Backlog[[#This Row],[Fecha comprometida (para UAT)]]=""), "Sin fecha comprometida", IF( Backlog[[#This Row],[Fecha Real de Cierre]]="", TODAY()-Backlog[[#This Row],[Fecha comprometida (para UAT)]], Backlog[[#This Row],[Fecha Real de Cierre]]-Backlog[[#This Row],[Fecha comprometida (para UAT)]] ) ) -> Sin fecha comprometida | AC97: =IF(OR(#REF!="",NOT(ISNUMBER(Backlog[[#This Row],[Dias_abiertos]]))),"",IF(Backlog[[#This Row],[Dias_abiertos]]<=7,"En plazo",IFERROR(IF(Backlog[[#This Row],[Dias_abiertos]]=_xlfn.XLOOKUP(TRIM(#REF!),CatSLA[Prioridad],CatSLA[SLA_dias],""),"En plazo","Fuera de plazo"),"Sin SLA"))) -> #REF!
A98: 595 | B98: Mantenimiento preventivo | C98: Alta | D98: 45814 | E98: planificar depuraciones | F98: Analisis en Desarrollo. Proceso de depuración. Luego Infra corre depuración a pedido. | G98: Todas las provincias | H98: Gamma | I98: Mantenimiento | J98: 19 | K98: A planificar | S98: 4 | U98: Tejerina | AA98: =_xlfn.XLOOKUP(Backlog[[#This Row],[Estado]],CatEstados[Estado],CatEstados[Fase],"Otro") -> Por hacer | AB98: =IF(OR(ISBLANK(Backlog[[#This Row],[Fecha comprometida (para UAT)]]),Backlog[[#This Row],[Fecha comprometida (para UAT)]]=""), "Sin fecha comprometida", IF( Backlog[[#This Row],[Fecha Real de Cierre]]="", TODAY()-Backlog[[#This Row],[Fecha comprometida (para UAT)]], Backlog[[#This Row],[Fecha Real de Cierre]]-Backlog[[#This Row],[Fecha comprometida (para UAT)]] ) ) -> Sin fecha comprometida | AC98: =IF(OR(#REF!="",NOT(ISNUMBER(Backlog[[#This Row],[Dias_abiertos]]))),"",IF(Backlog[[#This Row],[Dias_abiertos]]<=7,"En plazo",IFERROR(IF(Backlog[[#This Row],[Dias_abiertos]]=_xlfn.XLOOKUP(TRIM(#REF!),CatSLA[Prioridad],CatSLA[SLA_dias],""),"En plazo","Fuera de plazo"),"Sin SLA"))) -> #REF!
A99: MAN-71 | B99: Mantenimiento correctivo | C99: Media | D99: 45660 | E99: SLA GAMMA MAN-9524 Modulo Contabilidad-Generacion de constancias no guarda nro de presentacion en tablas. Caso 6637. | G99: Salta | H99: Gamma | I99: Mantenimiento | J99: 1 | K99: A planificar | M99: MARZO | N99: 45967 | O99: Sabrina indicó en el correo del 14/11/2025 que este sigue abierto. Que es un PROBLEMA de Media y el responsable interno es Santiago. Ver con Santiago y Luis. Estaría resuelto. | R99: 1 | S99: 4 | U99: Tejerina | AA99: =_xlfn.XLOOKUP(Backlog[[#This Row],[Estado]],CatEstados[Estado],CatEstados[Fase],"Otro") -> Por hacer | AB99: =IF(OR(ISBLANK(Backlog[[#This Row],[Fecha comprometida (para UAT)]]),Backlog[[#This Row],[Fecha comprometida (para UAT)]]=""), "Sin fecha comprometida", IF( Backlog[[#This Row],[Fecha Real de Cierre]]="", TODAY()-Backlog[[#This Row],[Fecha comprometida (para UAT)]], Backlog[[#This Row],[Fecha Real de Cierre]]-Backlog[[#This Row],[Fecha comprometida (para UAT)]] ) ) -> #VALUE! | AC99: =IF(OR(#REF!="",NOT(ISNUMBER(Backlog[[#This Row],[Dias_abiertos]]))),"",IF(Backlog[[#This Row],[Dias_abiertos]]<=7,"En plazo",IFERROR(IF(Backlog[[#This Row],[Dias_abiertos]]=_xlfn.XLOOKUP(TRIM(#REF!),CatSLA[Prioridad],CatSLA[SLA_dias],""),"En plazo","Fuera de plazo"),"Sin SLA"))) -> #REF! | AJ99: Validar con Franco
A100: 00009746 | B100: Mantenimiento correctivo | C100: Alta | D100: 14/10/2025 | E100: Caso 9746- COR-Gamma -Declaración Jurada IIBB | F100: El archivo txt generado por GAMMA no contiene el CUIT de lotería ni el periodo. Adjunto imagen de como genera en gamma y como lo debería generar. | G100: Corrientes | H100: Gamma | I100: Mantenimiento | J100: 20 | K100: A planificar | N100: 45967 | O100: Quedó algo que se pedirá en otro caso de SF. Este se cierra. QUE SE CIERRE. LO VALIDEN!!! | S100: 6 | U100: Alejandro | AA100: =_xlfn.XLOOKUP(Backlog[[#This Row],[Estado]],CatEstados[Estado],CatEstados[Fase],"Otro") -> Por hacer | AB100: =IF(OR(ISBLANK(Backlog[[#This Row],[Fecha comprometida (para UAT)]]),Backlog[[#This Row],[Fecha comprometida (para UAT)]]=""), "Sin fecha comprometida", IF( Backlog[[#This Row],[Fecha Real de Cierre]]="", TODAY()-Backlog[[#This Row],[Fecha comprometida (para UAT)]], Backlog[[#This Row],[Fecha Real de Cierre]]-Backlog[[#This Row],[Fecha comprometida (para UAT)]] ) ) -> Sin fecha comprometida | AC100: =IF(OR(#REF!="",NOT(ISNUMBER(Backlog[[#This Row],[Dias_abiertos]]))),"",IF(Backlog[[#This Row],[Dias_abiertos]]<=7,"En plazo",IFERROR(IF(Backlog[[#This Row],[Dias_abiertos]]=_xlfn.XLOOKUP(TRIM(#REF!),CatSLA[Prioridad],CatSLA[SLA_dias],""),"En plazo","Fuera de plazo"),"Sin SLA"))) -> #REF! | AJ100: Validar con Franco
...

Sheet Indicadores Control
B1: Casos de Mantenimiento de Gamma
B3: Correctivos totales | C3: =COUNTIFS(Backlog!$B:$B,"Mantenimiento Correctivo") -> 95 | E3: Correctivos cerrados | F3: =COUNTIFS(Backlog!$B:$B,"Mantenimiento Correctivo",Backlog!$K:$K,"Cerrado") -> 48 | H3: Correctivos abiertos | I3: =COUNTIFS(Backlog!$B:$B,"Mantenimiento Correctivo",Backlog!$K:$K,"<>Cerrado") -> 47 | K3: Correctivos por hacer | L3: {=SUM(COUNTIFS( Backlog!$B:$B,"Mantenimiento correctivo", Backlog!$K:$K,{"Por hacer";"A planificar";"Planificado";"A estimar";"A priorizar"} ))} -> 39 | N3: Errores En curso | O3: =COUNTIFS( Backlog!$B:$B,"Mantenimiento correctivo", Backlog!$K:$K,"<>Cerrado", Backlog!$K:$K,"<>Por hacer", Backlog!$K:$K,"<>A planificar", Backlog!$K:$K,"<>Planificado", Backlog!$K:$K,"<>A estimar", Backlog!$K:$K,"<>A priorizar" ) -> 8
B4: Evolutivos totales | C4: =COUNTIFS(Backlog!$B:$B,"Mantenimiento evolutivo") -> 100 | E4: Evolutivos cerrados | F4: =COUNTIFS(Backlog!$B:$B,"Mantenimiento evolutivo",Backlog!$K:$K,"Cerrado") -> 14 | H4: Evolutivos abiertos | I4: =COUNTIFS(Backlog!$B:$B,"Mantenimiento evolutivo",Backlog!$K:$K,"<>Cerrado") -> 86 | K4: Evolutivos por hacer | L4: {=SUM(COUNTIFS( Backlog!$B:$B,"Mantenimiento evolutivo", Backlog!$K:$K,{"Por hacer";"A planificar";"Planificado";"A estimar";"A priorizar"} ))} -> 71 | N4: Requerimientos En curso | O4: =COUNTIFS( Backlog!$B:$B,"Mantenimiento evolutivo", Backlog!$K:$K,"<>Cerrado", Backlog!$K:$K,"<>Por hacer", Backlog!$K:$K,"<>A planificar", Backlog!$K:$K,"<>Planificado", Backlog!$K:$K,"<>A estimar", Backlog!$K:$K,"<>A priorizar" ) -> 15
B5: Preventivos totales | C5: =COUNTIFS(Backlog!$B:$B,"Mantenimiento preventivo") -> 27 | E5: Preventivos cerrados | F5: =COUNTIFS(Backlog!$B:$B,"Mantenimiento preventivo",Backlog!$K:$K,"Cerrado") -> 0 | H5: Preventivos abiertos | I5: =COUNTIFS(Backlog!$B:$B,"Mantenimiento preventivo",Backlog!$K:$K,"<>Cerrado") -> 27 | K5: Preventivos por hacer | L5: {=SUM(COUNTIFS( Backlog!$B:$B,"Mantenimiento preventivo", Backlog!$K:$K,{"Por hacer";"A planificar";"Planificado";"A estimar";"A priorizar"} ))} -> 24 | N5: Mantenimiento En curso | O5: =COUNTIFS( Backlog!$B:$B,"Mantenimiento preventivo", Backlog!$K:$K,"<>Cerrado", Backlog!$K:$K,"<>Por hacer", Backlog!$K:$K,"<>A planificar", Backlog!$K:$K,"<>Planificado", Backlog!$K:$K,"<>A estimar", Backlog!$K:$K,"<>A priorizar" ) -> 3
B6: Consultas }totales | C6: =COUNTIFS(Backlog!$B:$B,"Consulta") -> 1 | E6: Consultas cerradas | F6: =COUNTIFS(Backlog!$B:$B,"Consulta",Backlog!$K:$K,"Cerrado") -> 0 | H6: Consultas abiertos | I6: =COUNTIFS(Backlog!$B:$B,"Consulta",Backlog!$K:$K,"<>Cerrado") -> 1 | K6: Consultas por hacer | L6: {=SUM(COUNTIFS( Backlog!$B:$B,"Consulta", Backlog!$K:$K,{"Por hacer";"A planificar";"Planificado";"A estimar";"A priorizar"} ))} -> 1 | N6: Mantenimiento En curso | O6: =COUNTIFS( Backlog!$B:$B,"Consulta", Backlog!$K:$K,"<>Cerrado", Backlog!$K:$K,"<>Por hacer", Backlog!$K:$K,"<>A planificar", Backlog!$K:$K,"<>Planificado", Backlog!$K:$K,"<>A estimar", Backlog!$K:$K,"<>A priorizar" ) -> 0
B8: Casos totales | C8: =COUNTIFS(Backlog!$B$3:$B$9912,"<>") -> 222 | E8: Casos cerrados totales | F8: =COUNTIFS(Backlog!$B$3:$B$9912,"<>",Backlog!$K$3:$K$9912,"Cerrado") -> 62 | H8: Casos abiertos totales | I8: =COUNTIFS(Backlog!$B$3:$B$9912,"<>",Backlog!$K$3:$K$9912,"<>Cerrado") -> 160 | K8: Totales Por hacer | L8: =SUM( COUNTIFS(Backlog!$B$4:$B$9910,"<>",Backlog!$K$4:$K$9910,"Por hacer"), COUNTIFS(Backlog!$B$4:$B$9910,"<>",Backlog!$K$4:$K$9910,"A planificar"), COUNTIFS(Backlog!$B$4:$B$9910,"<>",Backlog!$K$4:$K$9910,"Planificado"), COUNTIFS(Backlog!$B$4:$B$9910,"<>",Backlog!$K$4:$K$9910,"A estimar"), COUNTIFS(Backlog!$B$4:$B$9910,"<>",Backlog!$K$4:$K$9910,"A priorizar") ) -> 134 | N8: Totales En curso | O8: =COUNTIFS(Backlog!$B$3:$B$9910,"<>",Backlog!$K$3:$K$9910,"<>Cerrado",Backlog!$K$3:$K$9910,"<>Por hacer", Backlog!$K$3:$K$9910,"<>A planificar", Backlog!$K$3:$K$9910,"<>Planificado", Backlog!$K$3:$K$9910,"<>A estimar", Backlog!$K$3:$K$9910,"<>A priorizar" ) -> 25
B10: Estado de situación de los casos de Mantenimiento de Gamma por hacer
B13: Correctivos a Estimar | C13: =COUNTIFS(Backlog!$B:$B,"Mantenimiento correctivo",Backlog!$K:$K,"A estimar") -> 0 | E13: Correctivos a priorizar | F13: =COUNTIFS(Backlog!$B:$B,"Mantenimiento correctivo",Backlog!$K:$K,"A priorizar") -> 19 | H13: Correctivos a planificar | I13: =COUNTIFS(Backlog!$B:$B,"Mantenimiento correctivo",Backlog!$K:$K,"A planificar") -> 16 | K13: Correctivos planificados | L13: =COUNTIFS(Backlog!$B:$B,"Mantenimiento correctivo",Backlog!$K:$K,"Planificado") -> 4
B14: Evolutivos a Estimar | C14: =COUNTIFS(Backlog!$B:$B,"Mantenimiento evolutivo",Backlog!$K:$K,"A estimar") -> 1 | E14: Evolutivos a priorizar | F14: =COUNTIFS(Backlog!$B:$B,"Mantenimiento evolutivo",Backlog!$K:$K,"A priorizar") -> 54 | H14: Evolutivos a planificar | I14: =COUNTIFS(Backlog!$B:$B,"Mantenimiento evolutivo",Backlog!$K:$K,"A planificar") -> 16 | K14: Evolutivos planificados | L14: =COUNTIFS(Backlog!$B:$B,"Mantenimiento evolutivo",Backlog!$K:$K,"Planificado") -> 0
B15: Preventivos s Estimar | C15: =COUNTIFS(Backlog!$B:$B,"Mantenimiento preventivo",Backlog!$K:$K,"A Estimar") -> 0 | E15: Preventivos a priorizar | F15: =COUNTIFS(Backlog!$B:$B,"Mantenimiento preventivo",Backlog!$K:$K,"A priorizar") -> 10 | H15: Preventivos a planificar | I15: =COUNTIFS(Backlog!$B:$B,"Mantenimiento preventivo",Backlog!$K:$K,"A planificar") -> 14 | K15: Preventivos planificados | L15: =COUNTIFS(Backlog!$B:$B,"Mantenimiento preventivo",Backlog!$K:$K,"Planificado") -> 0
B16: Consultas a Estimar | C16: =COUNTIFS(Backlog!$B:$B,"Consulta",Backlog!$K:$K,"A Estimar") -> 0 | E16: Consultas a priorizar | F16: =COUNTIFS(Backlog!$B:$B,"Consulta",Backlog!$K:$K,"A priorizar") -> 1 | H16: Consultas a planificar | I16: =COUNTIFS(Backlog!$B:$B,"Consulta",Backlog!$K:$K,"A planificar") -> 0 | K16: Consultas planificados | L16: =COUNTIFS(Backlog!$B:$B,"Consulta",Backlog!$K:$K,"Planificado") -> 0
B18: Totales a Estimar | C18: =COUNTIFS(Backlog!$B$3:$B$9912,"<>",Backlog!$K$3:$K$9912,"A Estimar") -> 1 | E18: Totales a priorizar | F18: =COUNTIFS(Backlog!$B$3:$B$9912,"<>",Backlog!$K$3:$K$9912,"A priorizar") -> 84 | H18: Totales a planificar | I18: =COUNTIFS(Backlog!$B$3:$B$9912,"<>",Backlog!$K$3:$K$9912,"A planificar") -> 46 | K18: Totales planificados | L18: =COUNTIFS(Backlog!$B$3:$B$9912,"<>",Backlog!$K$3:$K$9912,"Planificado") -> 4
B20: Estado de situación de los casos de Mantenimiento de Gamma en Curso
B22: Correctivos por hacer | C22: {=SUM(COUNTIFS( Backlog!$B:$B,"Mantenimiento correctivo", Backlog!$K:$K,{"Por hacer";"A planificar";"Planificado";"A estimar";"A priorizar"} ))} -> 39 | E22: Correctivos a priorizar | F22: =COUNTIFS(Backlog!$B:$B,"Mantenimiento correctivo",Backlog!$K:$K,"A priorizar") -> 19 | H22: Correctivos a planificar | I22: =COUNTIFS(Backlog!$B:$B,"Mantenimiento correctivo",Backlog!$K:$K,"A planificar") -> 16 | K22: Correctivos planificados | L22: =COUNTIFS(Backlog!$B:$B,"Mantenimiento correctivo",Backlog!$K:$K,"Planificado") -> 4
B23: Evolutivos por hacer | C23: {=SUM(COUNTIFS( Backlog!$B:$B,"Mantenimiento evolutivo", Backlog!$K:$K,{"Por hacer";"A planificar";"Planificado";"A estimar";"A priorizar"} ))} -> 71 | E23: Evolutivos a priorizar | F23: =COUNTIFS(Backlog!$B:$B,"Mantenimiento evolutivo",Backlog!$K:$K,"A priorizar") -> 54 | H23: Evolutivos a planificar | I23: =COUNTIFS(Backlog!$B:$B,"Mantenimiento evolutivo",Backlog!$K:$K,"A planificar") -> 16 | K23: Evolutivos planificados | L23: =COUNTIFS(Backlog!$B:$B,"Mantenimiento evolutivo",Backlog!$K:$K,"Planificado") -> 0
B24: Preventivos por hacer | C24: {=SUM(COUNTIFS( Backlog!$B:$B,"Mantenimiento preventivo", Backlog!$K:$K,{"Por hacer";"A planificar";"Planificado";"A estimar";"A priorizar"} ))} -> 24 | E24: Preventivos a priorizar | F24: =COUNTIFS(Backlog!$B:$B,"Mantenimiento preventivo",Backlog!$K:$K,"A priorizar") -> 10 | H24: Preventivos a planificar | I24: =COUNTIFS(Backlog!$B:$B,"Mantenimiento preventivo",Backlog!$K:$K,"A planificar") -> 14 | K24: Preventivos planificados | L24: =COUNTIFS(Backlog!$B:$B,"Mantenimiento preventivo",Backlog!$K:$K,"Planificado") -> 0
B25: Consultas por hacer | C25: {=SUM(COUNTIFS( Backlog!$B:$B,"Consulta", Backlog!$K:$K,{"Por hacer";"A planificar";"Planificado";"A estimar";"A priorizar"} ))} -> 1 | E25: Consultas a priorizar | F25: =COUNTIFS(Backlog!$B:$B,"Consulta",Backlog!$K:$K,"A priorizar") -> 1 | H25: Consultas a planificar | I25: =COUNTIFS(Backlog!$B:$B,"Consulta",Backlog!$K:$K,"A planificar") -> 0 | K25: Consultas planificados | L25: =COUNTIFS(Backlog!$B:$B,"Consulta",Backlog!$K:$K,"Planificado") -> 0
B27: Totales Por hacer | C27: =SUM( COUNTIFS(Backlog!$B$4:$B$9910,"<>",Backlog!$K$4:$K$9910,"Por hacer"), COUNTIFS(Backlog!$B$4:$B$9910,"<>",Backlog!$K$4:$K$9910,"A planificar"), COUNTIFS(Backlog!$B$4:$B$9910,"<>",Backlog!$K$4:$K$9910,"Planificado"), COUNTIFS(Backlog!$B$4:$B$9910,"<>",Backlog!$K$4:$K$9910,"A estimar"), COUNTIFS(Backlog!$B$4:$B$9910,"<>",Backlog!$K$4:$K$9910,"A priorizar") ) -> 134 | E27: Totales a priorizar | F27: =COUNTIFS(Backlog!$B$3:$B$9912,"<>",Backlog!$K$3:$K$9912,"A priorizar") -> 84 | H27: Totales a planificar | I27: =COUNTIFS(Backlog!$B$3:$B$9912,"<>",Backlog!$K$3:$K$9912,"A planificar") -> 46 | K27: Totales planificados | L27: =COUNTIFS(Backlog!$B$3:$B$9912,"<>",Backlog!$K$3:$K$9912,"Planificado") -> 4
E32: Errores en análisis Técnico | F32: =COUNTIFS(Backlog!#REF!,"Error",Backlog!$K:$K,"En análisis Técnico") -> #REF! | H32: Errores en análisis func. | I32: =COUNTIFS(Backlog!#REF!,"Error",Backlog!$K:$K,"En análisis funcional") -> #REF! | K32: Errores en desarrollo | L32: =COUNTIFS(Backlog!#REF!,"Error",Backlog!$K:$K,"En desarrollo") -> #REF! | N32: Errores en Testing | O32: =COUNTIFS(Backlog!#REF!,"Error",Backlog!$K:$K,"En Testing") -> #REF!
E33: Req. en análisis Técnico | F33: =COUNTIFS(Backlog!#REF!,"Requerimiento",Backlog!$K:$K,"En análisis Técnico") -> #REF! | H33: Req. en análisis func. | I33: =COUNTIFS(Backlog!#REF!,"Requerimiento",Backlog!$K:$K,"En análisis funcional") -> #REF! | K33: Req. en desarrollo | L33: =COUNTIFS(Backlog!#REF!,"Requerimiento",Backlog!$K:$K,"En desarrollo") -> #REF! | N33: Req. en Testing | O33: =COUNTIFS(Backlog!#REF!,"Requerimiento",Backlog!$K:$K,"En Testing") -> #REF!
E34: Req. script en análisis Téc. | F34: =COUNTIFS(Backlog!#REF!,"Req. scripts",Backlog!$K:$K,"En análisis Técnico") -> #REF! | H34: Req. script en análisis func. | I34: =COUNTIFS(Backlog!#REF!,"Req. scripts",Backlog!$K:$K,"En análisis funcional") -> #REF! | K34: Req. script en desarrollo | L34: =COUNTIFS(Backlog!#REF!,"Req. scripts",Backlog!$K:$K,"En desarrollo") -> #REF! | N34: Req. script en Testing | O34: =COUNTIFS(Backlog!#REF!,"Req. scripts",Backlog!$K:$K,"En Testing") -> #REF!
E35: Man en análisis Técnico | F35: =COUNTIFS(Backlog!#REF!,"Mantenimiento",Backlog!$K:$K,"En análisis Técnico") -> #REF! | H35: Man en análisis func. | I35: =COUNTIFS(Backlog!#REF!,"Mantenimiento",Backlog!$K:$K,"En análisis funcional") -> #REF! | K35: Man en desarrollo | L35: =COUNTIFS(Backlog!#REF!,"Mantenimiento",Backlog!$K:$K,"En desarrollo") -> #REF! | N35: Man en Testing | O35: =COUNTIFS(Backlog!#REF!,"Mantenimiento",Backlog!$K:$K,"En Testing") -> #REF!
E36: DevOps en análisis Técnico | F36: =COUNTIFS(Backlog!#REF!,"DevOps",Backlog!$K:$K,"En análisis Técnico") -> #REF! | H36: DevOps en análisis func. | I36: =COUNTIFS(Backlog!#REF!,"DevOps",Backlog!$K:$K,"En análisis funcional") -> #REF! | K36: DevOps en desarrollo | L36: =COUNTIFS(Backlog!#REF!,"DevOps",Backlog!$K:$K,"En desarrollo") -> #REF! | N36: DevOps Testing | O36: =COUNTIFS(Backlog!#REF!,"DevOps",Backlog!$K:$K,"En Testing") -> #REF!
E38: Totales en análisis Técnico | F38: =COUNTIFS(Backlog!#REF!,"<>",Backlog!$K$4:$K$9910,"En análisis Técnico") -> #REF! | H38: Totales en análisis func. | I38: =COUNTIFS(Backlog!#REF!,"<>",Backlog!$K$4:$K$9910,"En análisis funcional") -> #REF! | K38: Totales en desarrollo | L38: =COUNTIFS(Backlog!#REF!,"<>",Backlog!$K$4:$K$9910,"En desarrollo") -> #REF! | N38: Totales en Testing | O38: =COUNTIFS(Backlog!#REF!,"<>",Backlog!$K$4:$K$9910,"En Testing") -> #REF!
E41: Errores a validar | F41: =COUNTIFS(Backlog!#REF!,"Error",Backlog!$K:$K,"Validar estado") -> #REF! | H41: Errores en UAT | I41: =COUNTIFS(Backlog!#REF!,"Error",Backlog!$K:$K,"UAT") -> #REF! | K41: Errores P/ Implementar | L41: =COUNTIFS(Backlog!#REF!,"Error",Backlog!$K:$K,"Para implementar") -> #REF! | N41: Errores implementados | O41: =COUNTIFS(Backlog!#REF!,"Error",Backlog!$K:$K,"Implementado") -> #REF!
E42: Req. a validar | F42: =COUNTIFS(Backlog!#REF!,"Requerimiento",Backlog!$K:$K,"Validar estado") -> #REF! | H42: Req. en UAT | I42: =COUNTIFS(Backlog!#REF!,"Requerimiento",Backlog!$K:$K,"UAT") -> #REF! | K42: Req. P/ Implementar | L42: =COUNTIFS(Backlog!#REF!,"Requerimiento",Backlog!$K:$K,"Para implementar") -> #REF! | N42: Req. implementados | O42: =COUNTIFS(Backlog!#REF!,"Requerimiento",Backlog!$K:$K,"Implementado") -> #REF!
E43: Req. script a validar | F43: =COUNTIFS(Backlog!#REF!,"Req. scripts",Backlog!$K:$K,"Validar estado") -> #REF! | H43: Req. script UAT | I43: =COUNTIFS(Backlog!#REF!,"Req. scripts",Backlog!$K:$K,"UAT") -> #REF! | K43: Req. script p/Implem | L43: =COUNTIFS(Backlog!#REF!,"Req. scripts",Backlog!$K:$K,"Para implementar") -> #REF! | N43: Req. script implementados | O43: =COUNTIFS(Backlog!#REF!,"Req. scripts",Backlog!$K:$K,"Implementado") -> #REF!
E44: Man a validar | F44: =COUNTIFS(Backlog!#REF!,"Mantenimiento",Backlog!$K:$K,"Validar estado") -> #REF! | H44: Man. en UAT | I44: =COUNTIFS(Backlog!#REF!,"Mantenimiento",Backlog!$K:$K,"UAT") -> #REF! | K44: Man P/ Implementar | L44: =COUNTIFS(Backlog!#REF!,"Mantenimiento",Backlog!$K:$K,"Para implementar") -> #REF! | N44: Man implementados | O44: =COUNTIFS(Backlog!#REF!,"Mantenimiento",Backlog!$K:$K,"Implementado") -> #REF!
E45: DevOps a validar | F45: =COUNTIFS(Backlog!#REF!,"DevOps",Backlog!$K:$K,"Implementado") -> #REF! | H45: DevOps en UAT | I45: =COUNTIFS(Backlog!#REF!,"DevOps",Backlog!$K:$K,"UAT") -> #REF! | K45: DevOps P/ Implementar | L45: =COUNTIFS(Backlog!#REF!,"DevOps",Backlog!$K:$K,"Para implementar") -> #REF! | N45: DevOps implementados | O45: =COUNTIFS(Backlog!#REF!,"DevOps",Backlog!$K:$K,"Implementado") -> #REF!
E47: Totales a validar | F47: =COUNTIFS(Backlog!#REF!,"<>",Backlog!$K$4:$K$9910,"Validar estado") -> #REF! | H47: Totales en UAT | I47: =COUNTIFS(Backlog!#REF!,"<>",Backlog!$K$4:$K$9910,"UAT") -> #REF! | K47: Totales P/ Implementar | L47: =COUNTIFS(Backlog!#REF!,"<>",Backlog!$K$4:$K$9910,"Para implementar") -> #REF! | N47: Totales implementados | O47: =COUNTIFS(Backlog!#REF!,"<>",Backlog!$K$4:$K$9910,"Implementado") -> #REF!

Sheet Horas estimadas
C1: Cantidad de casos abiertos | F1: Estimación de horas | I1: Capacity mensual | L1: Tiempos estimados en meses
C3: Casos correctivos | D3: =COUNTIFS(Backlog!$B:$B,"Mantenimiento correctivo",Backlog!$K:$K,"<>Cerrado") -> 47 | F3: Horas correctivos | G3: =SUMIFS(Backlog!$S:$S,Backlog!$B:$B,"Mantenimiento correctivo",Backlog!$K:$K,"<>Cerrado") -> 1099 | I3: Marcos | J3: 160 | L3: Casos correctivos | M3: =+G3/$J$8 -> 4.5791667
C4: Casos evolutivos | D4: =COUNTIFS(Backlog!$B:$B,"Mantenimiento evolutivo",Backlog!$K:$K,"<>Cerrado") -> 86 | F4: Horas evolutivos | G4: =SUMIFS(Backlog!$S:$S,Backlog!$B:$B,"Mantenimiento evolutivo",Backlog!$K:$K,"<>Cerrado") -> 4487 | I4: Tejerina | J4: 80 | L4: Casos evolutivos | M4: =+G4/$J$8 -> 18.695833
C5: Casos preventivos | D5: =COUNTIFS(Backlog!$B:$B,"Mantenimiento preventivo",Backlog!$K:$K,"<>Cerrado") -> 27 | F5: Horas preventivos | G5: =SUMIFS(Backlog!$S:$S,Backlog!$B:$B,"Mantenimiento preventivo",Backlog!$K:$K,"<>Cerrado") -> 64 | I5: Otro | J5: 0 | L5: Casos preventivos | M5: =+G5/$J$8 -> 0.26666667
C6: Casos Consultas | D6: =COUNTIFS(Backlog!$B:$B,"Consulta",Backlog!$K:$K,"<>Cerrado") -> 1 | F6: Horas Consultas | G6: =SUMIFS(Backlog!$S:$S,Backlog!$B:$B,"Consulta",Backlog!$K:$K,"<>Cerrado") -> 0 | J6: =SUMIFS(Backlog!$S:$S,Backlog!$B:$B,"Consulta",Backlog!$K:$K,"<>Cerrado") -> 0 | L6: Casos Consultas | M6: =+G6/$J$8 -> 0
C8: Casos abiertos totales | D8: =COUNTIFS(Backlog!$B$4:$B$9910,"<>",Backlog!$K$4:$K$9910,"<>Cerrado") -> 159 | F8: Horas abiertos totales | G8: =SUMIFS(Backlog!$S$4:$S$9910,Backlog!$B$4:$B$9910,"<>",Backlog!$K$4:$K$9910,"<>Cerrado") -> 5650 | I8: Horas abiertos totales | J8: =SUM(J3:J6) -> 240 | L8: Casos abiertos totales | M8: =SUM(M3:M6) -> 23.541667

Sheet Indicadores
A1: Indicadores de Mantenimiento Gamma
B4: Casos totales | C4: =COUNTIF(Backlog[Estado],"<>") -> 223
B5: Casos cerrados | C5: =COUNTIF(Backlog[Estado],"Cerrado") -> 62
B6: Casos abiertos | C6: =COUNTIFS(Backlog[Estado],"<>Cerrado",Backlog[Estado],"<>") -> 161
B9: En plazo | C9: =COUNTIF(Backlog[En_plazo],"En plazo") -> 0
B10: Fuera de plazo | C10: =COUNTIF(Backlog[En_plazo],"Fuera de plazo") -> 0
B11: % Cumplimiento SLA | C11: =IFERROR(C9/(C9+C10),0) -> 0
B14: Por hacer | C14: =COUNTIF(Backlog[Fase],"Por hacer") -> 125
B15: En curso | C15: =COUNTIF(Backlog[Fase],"En curso") -> 10
B16: Implementación | C16: =COUNTIF(Backlog[Fase],"Implementación") -> 9
B17: Cerrado | C17: =COUNTIF(Backlog[Fase],"Cerrado") -> 57
B18: Total | C18: =SUM(C14:C17) -> 201

Sheet _Catalogos
A1: Estado | B1: Fase | D1: Prioridad | E1: SLA_dias | G1: Tipo | H1: Agrupación | J1: Responsables | K1: Áreas | L1: Componentes | N1: Parametro | O1: valor
A2: Por hacer | B2: Por hacer | D2: Critica | E2: 1 | G2: Error | H2: Error | J2: Rodrigo Albitre | K2: SAC | L2: Gamma | N2: Fecha_corte_inicio
A3: A priorizar | B3: Por hacer | D3: Muy Alta | E3: 2 | G3: Requerimiento | H3: Funcional | J3: Luis Rodriguez | K3: Funcional | L3: Lotemovil Panel | N3: Fecha_corte_fin
A4: A estimar | B4: Por hacer | D4: Alta | E4: 7 | G4: Mantenimiento | H4: Técnico | J4: Ricardo Tejerina | K4: Desarrollo | L4: NOA
A5: A planificar | B5: Por hacer | D5: Media | E5: 15 | G5: DevOps | H5: Técnico | J5: Horacio Braun | K5: SAC | L5: Kafka
A6: Planificado | B6: Por hacer | D6: Baja | E6: 30 | J6: Fabian Romero | K6: SAC | L6: Keycloak
A7: En análisis Funcional | B7: En curso | J7: Christian Torreblanca | K7: Gestión | L7: Eureka
A8: En análisis Técnico | B8: En curso
A9: En desarrollo | B9: En curso
A10: En Testing | B10: En curso
A11: UAT | B11: En curso
A12: Para implementar | B12: Implementación
A13: Implementado | B13: Implementación
A14: Validar estado | B14: Implementación
A15: Cerrado | B15: Cerrado
A16: Cancelado | B16: Cerrado

Sheet Calendario noviembre
F4: 45962
B5: Domingo | D5: Lunes | F5: Martes | H5: Miércoles | J5: Jueves | L5: Viernes | N5: Sábado
D6: =+B6+1 -> 1 | F6: =+D6+1 -> 2 | H6: =+F6+1 -> 3 | J6: =+H6+1 -> 4 | L6: =+J6+1 -> 5 | N6: =+L6+1 -> 6
R7: Por Hacer
R9: En curso
R11: UAT
B12: =+N6+1 -> 7 | D12: =+B12+1 -> 8 | F12: =+D12+1 -> 9 | H12: =+F12+1 -> 10 | J12: =+H12+1 -> 11 | L12: =+J12+1 -> 12 | N12: =+L12+1 -> 13
R13: Cerrado
R15: Cancelado
R17: Suspendido
B18: =+N12+1 -> 14 | D18: =+B18+1 -> 15 | F18: =+D18+1 -> 16 | H18: =+F18+1 -> 17 | J18: =+H18+1 -> 18 | L18: =+J18+1 -> 19 | N18: =+L18+1 -> 20
B24: =+N18+1 -> 21 | D24: =+B24+1 -> 22 | F24: =+D24+1 -> 23 | H24: =+F24+1 -> 24 | J24: =+H24+1 -> 25 | L24: =+J24+1 -> 26 | N24: =+L24+1 -> 27
B30: =+N24+1 -> 28 | D30: =+B30+1 -> 29 | F30: =+D30+1 -> 30

Sheet Plan noviembre
A1: Tipo | B1: Clave | C1: Fecha solicitado | D1: Resumen | E1: Descripción | F1: Cliente | G1: Componente | H1: Asignada | I1: Area | J1: Informador | K1: Prioridad | L1: OP | M1: Estado | N1: Incremento | O1: Fecha Mandatoria | P1: Fecha desde | Q1: Fecha comprometida (para UAT) | R1: Fecha Real de Cierre | S1: Comentarios Funcionales | T1: Comentarios Técnicos | U1: Funcional | V1: Desarrollador | W1: Coordinador | X1: Orden de Magnitud | Y1: Estimacion | Z1: Gestión | AA1: Funcional | AB1: Análisis y Diseño Técnico | AC1: Desarrollo y Prueba Unitaria | AD1: Testing Integral | AE1: Instalacion | AF1: Seguimiento | AG1: Fecha para instalar | AH1: Skill Transfer

Sheet Solo lo importante
A1: Tipo de caso | B1: Clave del caso | C1: Evaluación de criticidad real | D1: Cliente | E1: Componente | F1: Area | G1: OP | H1: Estado | I1: Fecha Mandatoria | J1: Fecha comprometida (para UAT) | K1: Fecha Real de Cierre | L1: Desarrollador | M1: Responsable
A2: =#REF! -> #REF! | B2: =Backlog[[#This Row],[Clave del caso]] -> 16613 | C2: =#REF! -> #REF! | D2: =Backlog[[#This Row],[Cliente que solicita]] -> 0 | E2: =Backlog[[#This Row],[Componente]] -> Gamma | F2: =Backlog[[#This Row],[Area responsable de traccionar]] -> 0 | G2: =Backlog[[#This Row],[OP]] -> 0 | H2: =Backlog[[#This Row],[Estado]] -> Para implementar | I2: =IF(Backlog[[#This Row],[Fecha Requerida en Producción]]="","",Backlog[[#This Row],[Fecha Requerida en Producción]]) | J2: =IF(Backlog[[#This Row],[Fecha comprometida (para UAT)]]="","",Backlog[[#This Row],[Fecha comprometida (para UAT)]]) | K2: =IF(Backlog[[#This Row],[Fecha Real de Cierre]]="","",Backlog[[#This Row],[Fecha Real de Cierre]]) | L2: =IF(Backlog[[#This Row],[Fecha Real de Cierre]]="","",Backlog[[#This Row],[Fecha Real de Cierre]]) | M2: =IF(Backlog[[#This Row],[Fecha Real de Cierre]]="","",Backlog[[#This Row],[Fecha Real de Cierre]])
A3: =#REF! -> #REF! | B3: =Backlog[[#This Row],[Clave del caso]] -> GAMMA-817 SF16721 | C3: =#REF! -> #REF! | D3: =Backlog[[#This Row],[Cliente que solicita]] -> La Pampa | E3: =Backlog[[#This Row],[Componente]] -> Saaservice | F3: =Backlog[[#This Row],[Area responsable de traccionar]] -> Mantenimiento | G3: =Backlog[[#This Row],[OP]] -> 0 | H3: =Backlog[[#This Row],[Estado]] -> Planificado | I3: =IF(Backlog[[#This Row],[Fecha Requerida en Producción]]="","",Backlog[[#This Row],[Fecha Requerida en Producción]]) | J3: =IF(Backlog[[#This Row],[Fecha comprometida (para UAT)]]="","",Backlog[[#This Row],[Fecha comprometida (para UAT)]]) | K3: =IF(Backlog[[#This Row],[Fecha Real de Cierre]]="","",Backlog[[#This Row],[Fecha Real de Cierre]]) | L3: =IF(Backlog[[#This Row],[Fecha Real de Cierre]]="","",Backlog[[#This Row],[Fecha Real de Cierre]]) | M3: =IF(Backlog[[#This Row],[Fecha Real de Cierre]]="","",Backlog[[#This Row],[Fecha Real de Cierre]])
A4: =#REF! -> #REF! | B4: =Backlog[[#This Row],[Clave del caso]] -> GAMMA-746 SF16529 | C4: =#REF! -> #REF! | D4: =Backlog[[#This Row],[Cliente que solicita]] -> 0 | E4: =Backlog[[#This Row],[Componente]] -> Gamma | F4: =Backlog[[#This Row],[Area responsable de traccionar]] -> 0 | G4: =Backlog[[#This Row],[OP]] -> 0 | H4: =Backlog[[#This Row],[Estado]] -> A planificar | I4: =IF(Backlog[[#This Row],[Fecha Requerida en Producción]]="","",Backlog[[#This Row],[Fecha Requerida en Producción]]) | J4: =IF(Backlog[[#This Row],[Fecha comprometida (para UAT)]]="","",Backlog[[#This Row],[Fecha comprometida (para UAT)]]) | K4: =IF(Backlog[[#This Row],[Fecha Real de Cierre]]="","",Backlog[[#This Row],[Fecha Real de Cierre]]) | L4: =IF(Backlog[[#This Row],[Fecha Real de Cierre]]="","",Backlog[[#This Row],[Fecha Real de Cierre]]) | M4: =IF(Backlog[[#This Row],[Fecha Real de Cierre]]="","",Backlog[[#This Row],[Fecha Real de Cierre]])
A5: =#REF! -> #REF! | B5: =Backlog[[#This Row],[Clave del caso]] -> GAMMA-747 SF16530 | C5: =#REF! -> #REF! | D5: =Backlog[[#This Row],[Cliente que solicita]] -> 0 | E5: =Backlog[[#This Row],[Componente]] -> Gamma | F5: =Backlog[[#This Row],[Area responsable de traccionar]] -> 0 | G5: =Backlog[[#This Row],[OP]] -> 0 | H5: =Backlog[[#This Row],[Estado]] -> A planificar | I5: =IF(Backlog[[#This Row],[Fecha Requerida en Producción]]="","",Backlog[[#This Row],[Fecha Requerida en Producción]]) | J5: =IF(Backlog[[#This Row],[Fecha comprometida (para UAT)]]="","",Backlog[[#This Row],[Fecha comprometida (para UAT)]]) | K5: =IF(Backlog[[#This Row],[Fecha Real de Cierre]]="","",Backlog[[#This Row],[Fecha Real de Cierre]]) | L5: =IF(Backlog[[#This Row],[Fecha Real de Cierre]]="","",Backlog[[#This Row],[Fecha Real de Cierre]]) | M5: =IF(Backlog[[#This Row],[Fecha Real de Cierre]]="","",Backlog[[#This Row],[Fecha Real de Cierre]])
A6: =#REF! -> #REF! | B6: =Backlog[[#This Row],[Clave del caso]] -> GAMMA-748 SF16531 | C6: =#REF! -> #REF! | D6: =Backlog[[#This Row],[Cliente que solicita]] -> 0 | E6: =Backlog[[#This Row],[Componente]] -> Gamma | F6: =Backlog[[#This Row],[Area responsable de traccionar]] -> 0 | G6: =Backlog[[#This Row],[OP]] -> 0 | H6: =Backlog[[#This Row],[Estado]] -> A planificar | I6: =Backlog[[#This Row],[Fecha Requerida en Producción]] -> 0 | J6: =IF(Backlog[[#This Row],[Fecha comprometida (para UAT)]]="","",Backlog[[#This Row],[Fecha comprometida (para UAT)]]) | K6: =IF(Backlog[[#This Row],[Fecha Real de Cierre]]="","",Backlog[[#This Row],[Fecha Real de Cierre]]) | L6: =Backlog[[#This Row],[Estimación Desarrollo]] -> 0 | M6: =Backlog[[#This Row],[QA/UAT]] -> 0
A7: =#REF! -> #REF! | B7: =Backlog[[#This Row],[Clave del caso]] -> GAMMA-749 SF16532 | C7: =#REF! -> #REF! | D7: =Backlog[[#This Row],[Cliente que solicita]] -> 0 | E7: =Backlog[[#This Row],[Componente]] -> Gamma | F7: =Backlog[[#This Row],[Area responsable de traccionar]] -> 0 | G7: =Backlog[[#This Row],[OP]] -> 0 | H7: =Backlog[[#This Row],[Estado]] -> A planificar | I7: =IF(Backlog[[#This Row],[Fecha Requerida en Producción]]="","",Backlog[[#This Row],[Fecha Requerida en Producción]]) | J7: =IF(Backlog[[#This Row],[Fecha comprometida (para UAT)]]="","",Backlog[[#This Row],[Fecha comprometida (para UAT)]]) | K7: =IF(Backlog[[#This Row],[Fecha Real de Cierre]]="","",Backlog[[#This Row],[Fecha Real de Cierre]]) | L7: =Backlog[[#This Row],[Estimación Desarrollo]] -> 0 | M7: =Backlog[[#This Row],[QA/UAT]] -> 0
A8: =#REF! -> #REF! | B8: =Backlog[[#This Row],[Clave del caso]] -> GAMMA-750 SF16533 | C8: =#REF! -> #REF! | D8: =Backlog[[#This Row],[Cliente que solicita]] -> 0 | E8: =Backlog[[#This Row],[Componente]] -> Gamma | F8: =Backlog[[#This Row],[Area responsable de traccionar]] -> 0 | G8: =Backlog[[#This Row],[OP]] -> 0 | H8: =Backlog[[#This Row],[Estado]] -> A planificar | I8: =IF(Backlog[[#This Row],[Fecha Requerida en Producción]]="","",Backlog[[#This Row],[Fecha Requerida en Producción]]) | J8: =IF(Backlog[[#This Row],[Fecha comprometida (para UAT)]]="","",Backlog[[#This Row],[Fecha comprometida (para UAT)]]) | K8: =IF(Backlog[[#This Row],[Fecha Real de Cierre]]="","",Backlog[[#This Row],[Fecha Real de Cierre]]) | L8: =Backlog[[#This Row],[Estimación Desarrollo]] -> 0 | M8: =Backlog[[#This Row],[QA/UAT]] -> 0
A9: =#REF! -> #REF! | B9: =Backlog[[#This Row],[Clave del caso]] -> GAMMA-751 SF16534 | C9: =#REF! -> #REF! | D9: =Backlog[[#This Row],[Cliente que solicita]] -> 0 | E9: =Backlog[[#This Row],[Componente]] -> Gamma | F9: =Backlog[[#This Row],[Area responsable de traccionar]] -> 0 | G9: =Backlog[[#This Row],[OP]] -> 0 | H9: =Backlog[[#This Row],[Estado]] -> A planificar | I9: =IF(Backlog[[#This Row],[Fecha Requerida en Producción]]="","",Backlog[[#This Row],[Fecha Requerida en Producción]]) | J9: =IF(Backlog[[#This Row],[Fecha comprometida (para UAT)]]="","",Backlog[[#This Row],[Fecha comprometida (para UAT)]]) | K9: =IF(Backlog[[#This Row],[Fecha Real de Cierre]]="","",Backlog[[#This Row],[Fecha Real de Cierre]]) | L9: =Backlog[[#This Row],[Estimación Desarrollo]] -> 0 | M9: =Backlog[[#This Row],[QA/UAT]] -> 0
A10: =#REF! -> #REF! | B10: =Backlog[[#This Row],[Clave del caso]] -> GAMMA-752 SF16535 | C10: =#REF! -> #REF! | D10: =Backlog[[#This Row],[Cliente que solicita]] -> 0 | E10: =Backlog[[#This Row],[Componente]] -> Gamma | F10: =Backlog[[#This Row],[Area responsable de traccionar]] -> 0 | G10: =Backlog[[#This Row],[OP]] -> 0 | H10: =Backlog[[#This Row],[Estado]] -> A planificar | I10: =IF(Backlog[[#This Row],[Fecha Requerida en Producción]]="","",Backlog[[#This Row],[Fecha Requerida en Producción]]) | J10: =IF(Backlog[[#This Row],[Fecha comprometida (para UAT)]]="","",Backlog[[#This Row],[Fecha comprometida (para UAT)]]) | K10: =IF(Backlog[[#This Row],[Fecha Real de Cierre]]="","",Backlog[[#This Row],[Fecha Real de Cierre]]) | L10: =Backlog[[#This Row],[Estimación Desarrollo]] -> 0 | M10: =Backlog[[#This Row],[QA/UAT]] -> 0
A11: =#REF! -> #REF! | B11: =Backlog[[#This Row],[Clave del caso]] -> GAMMA-753 SF16536 | C11: =#REF! -> #REF! | D11: =Backlog[[#This Row],[Cliente que solicita]] -> 0 | E11: =Backlog[[#This Row],[Componente]] -> Gamma | F11: =Backlog[[#This Row],[Area responsable de traccionar]] -> 0 | G11: =Backlog[[#This Row],[OP]] -> 0 | H11: =Backlog[[#This Row],[Estado]] -> A planificar | I11: =IF(Backlog[[#This Row],[Fecha Requerida en Producción]]="","",Backlog[[#This Row],[Fecha Requerida en Producción]]) | J11: =IF(Backlog[[#This Row],[Fecha comprometida (para UAT)]]="","",Backlog[[#This Row],[Fecha comprometida (para UAT)]]) | K11: =IF(Backlog[[#This Row],[Fecha Real de Cierre]]="","",Backlog[[#This Row],[Fecha Real de Cierre]]) | L11: =Backlog[[#This Row],[Estimación Desarrollo]] -> 0 | M11: =Backlog[[#This Row],[QA/UAT]] -> 0
A12: =#REF! -> #REF! | B12: =Backlog[[#This Row],[Clave del caso]] -> GAMMA-754 SF16537 | C12: =#REF! -> #REF! | D12: =Backlog[[#This Row],[Cliente que solicita]] -> 0 | E12: =Backlog[[#This Row],[Componente]] -> Gamma | F12: =Backlog[[#This Row],[Area responsable de traccionar]] -> 0 | G12: =Backlog[[#This Row],[OP]] -> 0 | H12: =Backlog[[#This Row],[Estado]] -> A planificar | I12: =IF(Backlog[[#This Row],[Fecha Requerida en Producción]]="","",Backlog[[#This Row],[Fecha Requerida en Producción]]) | J12: =IF(Backlog[[#This Row],[Fecha comprometida (para UAT)]]="","",Backlog[[#This Row],[Fecha comprometida (para UAT)]]) | K12: =IF(Backlog[[#This Row],[Fecha Real de Cierre]]="","",Backlog[[#This Row],[Fecha Real de Cierre]]) | L12: =Backlog[[#This Row],[Estimación Desarrollo]] -> 0 | M12: =Backlog[[#This Row],[QA/UAT]] -> 0
A13: =#REF! -> #REF! | B13: =Backlog[[#This Row],[Clave del caso]] -> GAMMA-755 SF16538 | C13: =#REF! -> #REF! | D13: =Backlog[[#This Row],[Cliente que solicita]] -> 0 | E13: =Backlog[[#This Row],[Componente]] -> Gamma | F13: =Backlog[[#This Row],[Area responsable de traccionar]] -> 0 | G13: =Backlog[[#This Row],[OP]] -> 0 | H13: =Backlog[[#This Row],[Estado]] -> A planificar | I13: =IF(Backlog[[#This Row],[Fecha Requerida en Producción]]="","",Backlog[[#This Row],[Fecha Requerida en Producción]]) | J13: =IF(Backlog[[#This Row],[Fecha comprometida (para UAT)]]="","",Backlog[[#This Row],[Fecha comprometida (para UAT)]]) | K13: =IF(Backlog[[#This Row],[Fecha Real de Cierre]]="","",Backlog[[#This Row],[Fecha Real de Cierre]]) | L13: =Backlog[[#This Row],[Estimación Desarrollo]] -> 0 | M13: =Backlog[[#This Row],[QA/UAT]] -> 0
A14: =#REF! -> #REF! | B14: =Backlog[[#This Row],[Clave del caso]] -> GAMMA-756 SF16539 | C14: =#REF! -> #REF! | D14: =Backlog[[#This Row],[Cliente que solicita]] -> 0 | E14: =Backlog[[#This Row],[Componente]] -> Gamma | F14: =Backlog[[#This Row],[Area responsable de traccionar]] -> 0 | G14: =Backlog[[#This Row],[OP]] -> 0 | H14: =Backlog[[#This Row],[Estado]] -> A planificar | I14: =IF(Backlog[[#This Row],[Fecha Requerida en Producción]]="","",Backlog[[#This Row],[Fecha Requerida en Producción]]) | J14: =IF(Backlog[[#This Row],[Fecha comprometida (para UAT)]]="","",Backlog[[#This Row],[Fecha comprometida (para UAT)]]) | K14: =IF(Backlog[[#This Row],[Fecha Real de Cierre]]="","",Backlog[[#This Row],[Fecha Real de Cierre]]) | L14: =Backlog[[#This Row],[Estimación Desarrollo]] -> 0 | M14: =Backlog[[#This Row],[QA/UAT]] -> 0
A15: =#REF! -> #REF! | B15: =Backlog[[#This Row],[Clave del caso]] -> SF16554 | C15: =#REF! -> #REF! | D15: =Backlog[[#This Row],[Cliente que solicita]] -> Corrientes | E15: =Backlog[[#This Row],[Componente]] -> NOA | F15: =Backlog[[#This Row],[Area responsable de traccionar]] -> SAC | G15: =Backlog[[#This Row],[OP]] -> 0 | H15: =Backlog[[#This Row],[Estado]] -> A priorizar | I15: =IF(Backlog[[#This Row],[Fecha Requerida en Producción]]="","",Backlog[[#This Row],[Fecha Requerida en Producción]]) | J15: =IF(Backlog[[#This Row],[Fecha comprometida (para UAT)]]="","",Backlog[[#This Row],[Fecha comprometida (para UAT)]]) | K15: =IF(Backlog[[#This Row],[Fecha Real de Cierre]]="","",Backlog[[#This Row],[Fecha Real de Cierre]]) | L15: =Backlog[[#This Row],[Estimación Desarrollo]] -> 24 | M15: =Backlog[[#This Row],[QA/UAT]] -> 0
A16: =#REF! -> #REF! | B16: =Backlog[[#This Row],[Clave del caso]] -> GAMMA - 000719 SF16366 | C16: =#REF! -> #REF! | D16: =Backlog[[#This Row],[Cliente que solicita]] -> Santiago del Estero | E16: =Backlog[[#This Row],[Componente]] -> Gamma | F16: =Backlog[[#This Row],[Area responsable de traccionar]] -> Mantenimiento | G16: =Backlog[[#This Row],[OP]] -> 1 | H16: =Backlog[[#This Row],[Estado]] -> En desarrollo | I16: =IF(Backlog[[#This Row],[Fecha Requerida en Producción]]="","",Backlog[[#This Row],[Fecha Requerida en Producción]]) -> 46142 | J16: =IF(Backlog[[#This Row],[Fecha comprometida (para UAT)]]="","",Backlog[[#This Row],[Fecha comprometida (para UAT)]]) | K16: =IF(Backlog[[#This Row],[Fecha Real de Cierre]]="","",Backlog[[#This Row],[Fecha Real de Cierre]]) | L16: =Backlog[[#This Row],[Estimación Desarrollo]] -> 120 | M16: =Backlog[[#This Row],[QA/UAT]] -> 0
A17: =#REF! -> #REF! | B17: =Backlog[[#This Row],[Clave del caso]] -> GAMMA - 000722 SF16367 | C17: =#REF! -> #REF! | D17: =Backlog[[#This Row],[Cliente que solicita]] -> Santiago del Estero | E17: =Backlog[[#This Row],[Componente]] -> Gamma | F17: =Backlog[[#This Row],[Area responsable de traccionar]] -> Mantenimiento | G17: =Backlog[[#This Row],[OP]] -> 2 | H17: =Backlog[[#This Row],[Estado]] -> En desarrollo | I17: =IF(Backlog[[#This Row],[Fecha Requerida en Producción]]="","",Backlog[[#This Row],[Fecha Requerida en Producción]]) -> 46142 | J17: =IF(Backlog[[#This Row],[Fecha comprometida (para UAT)]]="","",Backlog[[#This Row],[Fecha comprometida (para UAT)]]) | K17: =IF(Backlog[[#This Row],[Fecha Real de Cierre]]="","",Backlog[[#This Row],[Fecha Real de Cierre]]) | L17: =Backlog[[#This Row],[Estimación Desarrollo]] -> 160 | M17: =Backlog[[#This Row],[QA/UAT]] -> 0
A18: =#REF! -> #REF! | B18: =Backlog[[#This Row],[Clave del caso]] -> 16608 | C18: =#REF! -> #REF! | D18: =Backlog[[#This Row],[Cliente que solicita]] -> Santiago del Estero | E18: =Backlog[[#This Row],[Componente]] -> Gamma | F18: =Backlog[[#This Row],[Area responsable de traccionar]] -> Mantenimiento | G18: =Backlog[[#This Row],[OP]] -> 5 | H18: =Backlog[[#This Row],[Estado]] -> En desarrollo | I18: =Backlog[[#This Row],[Fecha Requerida en Producción]] -> 46147 | J18: =IF(Backlog[[#This Row],[Fecha comprometida (para UAT)]]="","",Backlog[[#This Row],[Fecha comprometida (para UAT)]]) | K18: =IF(Backlog[[#This Row],[Fecha Real de Cierre]]="","",Backlog[[#This Row],[Fecha Real de Cierre]]) | L18: =Backlog[[#This Row],[Estimación Desarrollo]] -> 136 | M18: =Backlog[[#This Row],[QA/UAT]] -> 0
A19: =#REF! -> #REF! | B19: =Backlog[[#This Row],[Clave del caso]] -> 16609 | C19: =#REF! -> #REF! | D19: =Backlog[[#This Row],[Cliente que solicita]] -> Santiago del Estero | E19: =Backlog[[#This Row],[Componente]] -> Gamma | F19: =Backlog[[#This Row],[Area responsable de traccionar]] -> Mantenimiento | G19: =Backlog[[#This Row],[OP]] -> 6 | H19: =Backlog[[#This Row],[Estado]] -> A planificar | I19: =IF(Backlog[[#This Row],[Fecha Requerida en Producción]]="","",Backlog[[#This Row],[Fecha Requerida en Producción]]) | J19: =IF(Backlog[[#This Row],[Fecha comprometida (para UAT)]]="","",Backlog[[#This Row],[Fecha comprometida (para UAT)]]) | K19: =IF(Backlog[[#This Row],[Fecha Real de Cierre]]="","",Backlog[[#This Row],[Fecha Real de Cierre]]) | L19: =Backlog[[#This Row],[Estimación Desarrollo]] -> 160 | M19: =Backlog[[#This Row],[QA/UAT]] -> 0
